{
  "alerts": [
    {
      "title": "2 articles about paid protesters",
      "description": "News mentions paid protesters: FACT FOCUS: A Craigslist ad is not proof of paid protesters ",
      "confidence": 70,
      "sources": [
        "Google News",
        "DuckDuckGo"
      ],
      "timestamp": "2026-03-21T18:27:03.836443Z"
    },
    {
      "title": "Pattern: Naming Pattern",
      "description": "18 orgs with generic patriotic names typical of astroturf.",
      "confidence": 78,
      "sources": [
        "Org",
        "Org",
        "Org"
      ],
      "timestamp": "2026-03-21T18:27:03.836463Z"
    }
  ],
  "lastUpdated": "2026-03-21T18:27:03.839316Z"
}