{
  "alerts": [
    {
      "title": "1 articles about paid protesters",
      "description": "News mentions paid protesters: Iran sent Hezbollah hundreds of millions in 2025, and ordina",
      "confidence": 60,
      "sources": [
        "Google News",
        "DuckDuckGo"
      ],
      "timestamp": "2026-02-28T14:16:05.342079Z"
    },
    {
      "title": "Pattern: Naming Pattern",
      "description": "16 orgs with generic patriotic names typical of astroturf.",
      "confidence": 78,
      "sources": [
        "Org",
        "Org",
        "Org"
      ],
      "timestamp": "2026-02-28T14:16:05.342114Z"
    }
  ],
  "lastUpdated": "2026-02-28T14:16:05.345320Z"
}