{
  "alerts": [
    {
      "title": "Potential Astroturf Activity",
      "description": "The data indicates a pattern of 'paid protesters' rhetoric in the news, which is a common tactic used in astroturf campaigns to discredit grassroots movements. This, combined with the presence of flagged organizations and job postings, suggests a moderate risk of astroturfing.",
      "confidence": 72,
      "sources": [
        "News",
        "Orgs",
        "Jobs",
        "Correlations"
      ],
      "timestamp": "2026-01-29T04:02:35.458987Z"
    }
  ],
  "lastUpdated": "2026-01-29T04:02:35.461445Z"
}