{
  "lastScan": "2026-05-29T09:40:40.529500Z",
  "stats": {
    "events": 100,
    "alerts": 3,
    "orgs": 40,
    "newsArticles": 20
  },
  "systemConfidence": 60,
  "confidenceFactors": [
    {
      "factor": "News Coverage",
      "score": 80,
      "detail": "10 high-relevance articles"
    },
    {
      "factor": "Organization Risk",
      "score": 35,
      "detail": "0 high-risk orgs"
    },
    {
      "factor": "Job Postings",
      "score": 30,
      "detail": "0 suspicious postings"
    }
  ],
  "agentNotes": [
    {
      "summary": "Monitoring 10 news, 15 orgs, 58 jobs. 3 alerts.",
      "timestamp": "2026-05-29T09:40:40.528635Z"
    },
    {
      "summary": "Monitoring 15 news, 15 orgs, 60 jobs. 3 alerts.",
      "timestamp": "2026-05-29T05:08:36.164570Z"
    },
    {
      "summary": "Monitoring 15 news, 15 orgs, 60 jobs. 3 alerts.",
      "timestamp": "2026-05-29T00:05:24.878651Z"
    },
    {
      "summary": "Monitoring 10 news, 15 orgs, 58 jobs. 3 alerts.",
      "timestamp": "2026-05-28T22:28:28.252167Z"
    },
    {
      "summary": "Monitoring 10 news, 15 orgs, 58 jobs. 3 alerts.",
      "timestamp": "2026-05-28T20:25:54.873825Z"
    },
    {
      "summary": "Monitoring 15 news, 15 orgs, 58 jobs. 3 alerts.",
      "timestamp": "2026-05-28T17:58:43.916331Z"
    },
    {
      "summary": "Monitoring 15 news, 15 orgs, 58 jobs. 3 alerts.",
      "timestamp": "2026-05-28T14:31:44.998810Z"
    },
    {
      "summary": "Monitoring 10 news, 15 orgs, 58 jobs. 3 alerts.",
      "timestamp": "2026-05-28T10:48:53.118960Z"
    },
    {
      "summary": "Monitoring 15 news, 15 orgs, 58 jobs. 3 alerts.",
      "timestamp": "2026-05-28T06:47:11.804546Z"
    },
    {
      "summary": "Monitoring 9 news, 15 orgs, 58 jobs. 3 alerts.",
      "timestamp": "2026-05-28T02:44:01.116689Z"
    }
  ],
  "connections": [
    {
      "type": "Naming Pattern",
      "description": "17 orgs with generic patriotic names typical of astroturf.",
      "probability": 78,
      "evidence": [
        {
          "type": "Org",
          "detail": "Citizens For Sanity"
        },
        {
          "type": "Org",
          "detail": "Citizens For Education"
        },
        {
          "type": "Org",
          "detail": "Citizens For Peace"
        }
      ]
    },
    {
      "type": "Paid Protest News",
      "description": "4 articles specifically about paid protesters.",
      "probability": 72,
      "evidence": [
        {
          "type": "News",
          "detail": "Trump says Delaney Hall protesters are 'paid' as clashes escalate outside NJ ICE facility"
        },
        {
          "type": "News",
          "detail": "Are Minneapolis protesters paid, like the Trump administration says? Here's a fact check"
        }
      ]
    }
  ],
  "timeline": [
    {
      "type": "news",
      "title": "Trump says Delaney Hall protesters are 'paid' as clashes escalate outside NJ ICE facility",
      "date": "2026-05-29T09:40:40.529500Z",
      "sourceUrl": "https://www.msn.com/en-us/news/world/trump-says-delaney-hall-protesters-are-paid-as-clashes-escalate-outside-nj-ice-facility/ar-AA24dJjM"
    },
    {
      "type": "news",
      "title": "Are Minneapolis protesters paid, like the Trump administration says? Here's a fact check",
      "date": "2026-05-29T09:40:40.529500Z",
      "sourceUrl": "https://www.msn.com/en-ca/news/us/are-minneapolis-protesters-paid-like-the-trump-administration-says-here-s-a-fact-check/ar-AA1W1ReG"
    },
    {
      "type": "news",
      "title": "KFAN's Paul Allen returns after week away, reiterates apology for 'paid protesters' quip",
      "date": "2026-05-29T09:40:40.529500Z",
      "sourceUrl": "https://www.yahoo.com/entertainment/tv/articles/kfans-paul-allen-returns-week-194031958.html"
    },
    {
      "type": "news",
      "title": "Shark Tank's Kevin O'Leary called them paid protestors as 600 Utahns rallied...",
      "date": "2026-05-29T05:08:36.165160Z",
      "sourceUrl": "https://www.yahoo.com/news/us/articles/shark-tanks-kevin-oleary-called-010000191.html"
    },
    {
      "type": "news",
      "title": "Trump says Delaney Hall protesters are \u2018paid\u2019 as clashes escalate outside NJ ICE...",
      "date": "2026-05-29T05:08:36.165160Z",
      "sourceUrl": "https://www.yahoo.com/news/politics/articles/trump-says-delaney-hall-protesters-222333517.html"
    },
    {
      "type": "news",
      "title": "Protesters and ICE agents clashed overnight in Newark, arrests are reported. The...",
      "date": "2026-05-29T05:08:36.165160Z",
      "sourceUrl": "https://nj1015.com/delaney-hall-protests-nj-latest/"
    },
    {
      "type": "news",
      "title": "KFAN's Paul Allen returns after week away, reiterates apology for 'paid protesters' quip",
      "date": "2026-05-29T00:05:24.879541Z",
      "sourceUrl": "https://www.yahoo.com/entertainment/tv/articles/kfans-paul-allen-returns-week-194031958.html"
    },
    {
      "type": "news",
      "title": "Trump says Delaney Hall protesters are 'paid' as clashes escalate outside NJ ICE facility",
      "date": "2026-05-29T00:05:24.879541Z",
      "sourceUrl": "https://www.msn.com/en-us/news/world/trump-says-delaney-hall-protesters-are-paid-as-clashes-escalate-outside-nj-ice-facility/ar-AA24dJjM"
    },
    {
      "type": "news",
      "title": "Are Minneapolis protesters paid, like the Trump administration says? Here's a fact check",
      "date": "2026-05-29T00:05:24.879541Z",
      "sourceUrl": "https://www.msn.com/en-ca/news/us/are-minneapolis-protesters-paid-like-the-trump-administration-says-here-s-a-fact-check/ar-AA1W1ReG"
    },
    {
      "type": "news",
      "title": "Trump says Delaney Hall protesters are 'paid' as clashes escalate outside NJ ICE facility",
      "date": "2026-05-28T22:28:28.253132Z",
      "sourceUrl": "https://www.msn.com/en-us/news/world/trump-says-delaney-hall-protesters-are-paid-as-clashes-escalate-outside-nj-ice-facility/ar-AA24dJjM"
    },
    {
      "type": "news",
      "title": "Are Minneapolis protesters paid, like the Trump administration says? Here's a fact check",
      "date": "2026-05-28T22:28:28.253132Z",
      "sourceUrl": "https://www.msn.com/en-us/society-culture-and-history/human-rights/are-minneapolis-protesters-paid-like-the-trump-administration-says-here-s-a-fact-check/ar-AA1W1ReG"
    },
    {
      "type": "news",
      "title": "KFAN's Paul Allen returns after week away, reiterates apology for 'paid protesters' quip",
      "date": "2026-05-28T22:28:28.253132Z",
      "sourceUrl": "https://www.yahoo.com/entertainment/tv/articles/kfans-paul-allen-returns-week-194031958.html"
    },
    {
      "type": "news",
      "title": "Trump says Delaney Hall protesters are 'paid' as clashes escalate outside NJ ICE facility",
      "date": "2026-05-28T20:25:54.874598Z",
      "sourceUrl": "https://www.msn.com/en-us/news/world/trump-says-delaney-hall-protesters-are-paid-as-clashes-escalate-outside-nj-ice-facility/ar-AA24dJjM"
    },
    {
      "type": "news",
      "title": "Are Minneapolis protesters paid, like the Trump administration says? Here's a fact check",
      "date": "2026-05-28T20:25:54.874598Z",
      "sourceUrl": "https://www.msn.com/en-us/society-culture-and-history/human-rights/are-minneapolis-protesters-paid-like-the-trump-administration-says-here-s-a-fact-check/ar-AA1W1ReG"
    },
    {
      "type": "news",
      "title": "KFAN's Paul Allen returns after week away, reiterates apology for 'paid protesters' quip",
      "date": "2026-05-28T20:25:54.874598Z",
      "sourceUrl": "https://www.yahoo.com/entertainment/tv/articles/kfans-paul-allen-returns-week-194031958.html"
    },
    {
      "type": "news",
      "title": "Trump says Delaney Hall protesters are 'paid' as clashes escalate outside NJ ICE facility",
      "date": "2026-05-28T17:58:43.917189Z",
      "sourceUrl": "https://www.msn.com/en-us/news/world/trump-says-delaney-hall-protesters-are-paid-as-clashes-escalate-outside-nj-ice-facility/ar-AA24dJjM"
    },
    {
      "type": "news",
      "title": "KFAN's Paul Allen returns after week away, reiterates apology for 'paid protesters' quip",
      "date": "2026-05-28T17:58:43.917189Z",
      "sourceUrl": "https://www.yahoo.com/entertainment/tv/articles/kfans-paul-allen-returns-week-194031958.html"
    },
    {
      "type": "news",
      "title": "Shark Tank's Kevin O'Leary called them paid protestors as 600 Utahns rallied...",
      "date": "2026-05-28T17:58:43.917189Z",
      "sourceUrl": "https://www.yahoo.com/news/us/articles/shark-tanks-kevin-oleary-called-010000191.html"
    },
    {
      "type": "news",
      "title": "Phoenix officer accused of provoking student protesters on paid leave",
      "date": "2026-05-28T14:31:44.999868Z",
      "sourceUrl": "https://www.aol.com/articles/phoenix-officer-accused-provoking-student-015721361.html"
    },
    {
      "type": "news",
      "title": "The brazen ad for rent-a-crowd protesters to attend anti-Israel rally in Melbourne",
      "date": "2026-05-28T14:31:44.999868Z",
      "sourceUrl": "https://www.msn.com/en-us/news/world/the-brazen-ad-for-rent-a-crowd-protesters-to-attend-anti-israel-rally-in-melbourne/ar-AA1WVqrt?ocid=BingNewsVerp"
    },
    {
      "type": "news",
      "title": "KFAN's Paul Allen returns after week away, reiterates apology for 'paid protesters' quip",
      "date": "2026-05-28T14:31:44.999868Z",
      "sourceUrl": "https://www.msn.com/en-us/entertainment/celebrities/kfan-s-paul-allen-returns-after-week-away-reiterates-apology-for-paid-protesters-quip/ar-AA1VwlUt?ocid=BingNewsVerp"
    },
    {
      "type": "news",
      "title": "Trump says Delaney Hall protesters are 'paid' as clashes escalate outside NJ ICE facility",
      "date": "2026-05-28T10:48:53.119958Z",
      "sourceUrl": "https://www.aol.com/news/trump-says-delaney-hall-protesters-222333653.html"
    },
    {
      "type": "news",
      "title": "KFAN's Paul Allen returns after week away, reiterates apology for 'paid protesters' quip",
      "date": "2026-05-28T10:48:53.119958Z",
      "sourceUrl": "https://www.yahoo.com/entertainment/tv/articles/kfans-paul-allen-returns-week-194031958.html"
    },
    {
      "type": "news",
      "title": "Airbnb accused of paying protesters to attend California council hearing",
      "date": "2026-05-28T10:48:53.119958Z",
      "sourceUrl": "https://www.msn.com/en-us/news/us/airbnb-accused-of-paying-protesters-to-attend-california-council-hearing/ar-AA1VBDtY?ocid=BingNewsVerp"
    },
    {
      "type": "news",
      "title": "Trump says Delaney Hall protesters are 'paid' as clashes escalate outside NJ ICE facility",
      "date": "2026-05-28T06:47:11.805447Z",
      "sourceUrl": "https://www.msn.com/en-us/news/news/trump-says-delaney-hall-protesters-are-paid-as-clashes-escalate-outside-nj-ice-facility/ar-AA24dJjM"
    },
    {
      "type": "news",
      "title": "KFAN's Paul Allen returns after week away, reiterates apology for 'paid protesters' quip",
      "date": "2026-05-28T06:47:11.805447Z",
      "sourceUrl": "https://www.yahoo.com/entertainment/tv/articles/kfans-paul-allen-returns-week-194031958.html"
    },
    {
      "type": "news",
      "title": "Kevin O'Leary says data center campus protesters were 'bused in' from out of state",
      "date": "2026-05-28T06:47:11.805447Z",
      "sourceUrl": "https://www.sltrib.com/news/2026/05/05/kevin-oleary-says-protesters/"
    },
    {
      "type": "news",
      "title": "Trump says Delaney Hall protesters are 'paid' as clashes escalate outside NJ ICE facility",
      "date": "2026-05-28T02:44:01.117400Z",
      "sourceUrl": "https://www.msn.com/en-us/news/world/trump-says-delaney-hall-protesters-are-paid-as-clashes-escalate-outside-nj-ice-facility/ar-AA24dJjM"
    },
    {
      "type": "news",
      "title": "Are Minneapolis protesters paid, like the Trump administration says? Here's a fact check",
      "date": "2026-05-28T02:44:01.117400Z",
      "sourceUrl": "https://www.msn.com/en-ca/news/us/are-minneapolis-protesters-paid-like-the-trump-administration-says-here-s-a-fact-check/ar-AA1W1ReG"
    },
    {
      "type": "news",
      "title": "KFAN's Paul Allen returns after week away, reiterates apology for 'paid protesters' quip",
      "date": "2026-05-28T02:44:01.117400Z",
      "sourceUrl": "https://www.yahoo.com/entertainment/tv/articles/kfans-paul-allen-returns-week-194031958.html"
    },
    {
      "type": "news",
      "title": "The brazen ad for rent-a-crowd protesters to attend anti-Israel rally in Melbourne",
      "date": "2026-05-27T23:56:17.006593Z",
      "sourceUrl": "https://www.msn.com/en-us/news/world/the-brazen-ad-for-rent-a-crowd-protesters-to-attend-anti-israel-rally-in-melbourne/ar-AA1WVqrt?ocid=BingNewsVerp"
    },
    {
      "type": "news",
      "title": "Phoenix officer accused of provoking student protesters on paid leave",
      "date": "2026-05-27T23:56:17.006593Z",
      "sourceUrl": "https://www.usatoday.com/story/news/local/phoenix/2026/04/10/phoenix-police-officer-on-paid-leave-after-confrontation-at-protest/89560182007/"
    },
    {
      "type": "news",
      "title": "KFAN's Paul Allen returns after week away, reiterates apology for 'paid protesters' quip",
      "date": "2026-05-27T23:56:17.006593Z",
      "sourceUrl": "https://www.msn.com/en-us/entertainment/celebrities/kfan-s-paul-allen-returns-after-week-away-reiterates-apology-for-paid-protesters-quip/ar-AA1VwlUt?ocid=BingNewsVerp"
    },
    {
      "type": "news",
      "title": "Are Minneapolis protesters paid, like the Trump administration says? Here's a fact check",
      "date": "2026-05-27T22:27:17.565017Z",
      "sourceUrl": "https://www.msn.com/en-ca/news/us/are-minneapolis-protesters-paid-like-the-trump-administration-says-here-s-a-fact-check/ar-AA1W1ReG"
    },
    {
      "type": "news",
      "title": "KFAN's Paul Allen returns after week away, reiterates apology for 'paid protesters' quip",
      "date": "2026-05-27T22:27:17.565017Z",
      "sourceUrl": "https://www.yahoo.com/entertainment/tv/articles/kfans-paul-allen-returns-week-194031958.html"
    },
    {
      "type": "news",
      "title": "Phoenix officer accused of provoking student protesters on paid leave",
      "date": "2026-05-27T22:27:17.565017Z",
      "sourceUrl": "https://www.aol.com/articles/phoenix-officer-accused-provoking-student-015721361.html"
    },
    {
      "type": "news",
      "title": "Phoenix officer accused of provoking student protesters on paid leave",
      "date": "2026-05-27T20:05:25.597080Z",
      "sourceUrl": "https://www.aol.com/articles/phoenix-officer-accused-provoking-student-015721361.html"
    },
    {
      "type": "news",
      "title": "KFAN's Paul Allen returns after week away, reiterates apology for 'paid protesters' quip",
      "date": "2026-05-27T20:05:25.597080Z",
      "sourceUrl": "https://www.msn.com/en-us/news/us/kfans-paul-allen-returns-after-week-away-reiterates-apology-for-paid-protesters-quip/ar-AA1VwlUt?ocid=BingNewsVerp"
    },
    {
      "type": "news",
      "title": "Phoenix officer accused of provoking student protesters on paid leave",
      "date": "2026-05-27T20:05:25.597080Z",
      "sourceUrl": "https://www.usatoday.com/story/news/local/phoenix/2026/04/10/phoenix-police-officer-on-paid-leave-after-confrontation-at-protest/89560182007/"
    },
    {
      "type": "news",
      "title": "Phoenix officer accused of provoking student protesters on paid leave",
      "date": "2026-05-27T17:53:58.086401Z",
      "sourceUrl": "https://www.usatoday.com/story/news/local/phoenix/2026/04/10/phoenix-police-officer-on-paid-leave-after-confrontation-at-protest/89560182007/"
    },
    {
      "type": "news",
      "title": "KFAN's Paul Allen returns after week away, reiterates apology for 'paid protesters' quip",
      "date": "2026-05-27T17:53:58.086401Z",
      "sourceUrl": "https://www.msn.com/en-us/entertainment/celebrities/kfan-s-paul-allen-returns-after-week-away-reiterates-apology-for-paid-protesters-quip/ar-AA1VwlUt?ocid=BingNewsVerp"
    },
    {
      "type": "news",
      "title": "The brazen ad for rent-a-crowd protesters to attend anti-Israel rally in Melbourne",
      "date": "2026-05-27T17:53:58.086401Z",
      "sourceUrl": "https://www.msn.com/en-in/news/other/the-brazen-ad-for-rent-a-crowd-protesters-to-attend-anti-israel-rally-in-melbourne/ar-AA1WVqBb?ocid=BingNewsVerp"
    },
    {
      "type": "news",
      "title": "Phoenix officer accused of provoking student protesters on paid leave",
      "date": "2026-05-27T14:23:25.433213Z",
      "sourceUrl": "https://www.usatoday.com/story/news/local/phoenix/2026/04/10/phoenix-police-officer-on-paid-leave-after-confrontation-at-protest/89560182007/"
    },
    {
      "type": "news",
      "title": "KFAN's Paul Allen returns after week away, reiterates apology for 'paid protesters' quip",
      "date": "2026-05-27T14:23:25.433213Z",
      "sourceUrl": "https://www.msn.com/en-us/entertainment/celebrities/kfan-s-paul-allen-returns-after-week-away-reiterates-apology-for-paid-protesters-quip/ar-AA1VwlUt?ocid=BingNewsVerp"
    },
    {
      "type": "news",
      "title": "The brazen ad for rent-a-crowd protesters to attend anti-Israel rally in Melbourne",
      "date": "2026-05-27T14:23:25.433213Z",
      "sourceUrl": "https://www.msn.com/en-in/news/other/the-brazen-ad-for-rent-a-crowd-protesters-to-attend-anti-israel-rally-in-melbourne/ar-AA1WVqBb?ocid=BingNewsVerp"
    },
    {
      "type": "news",
      "title": "KFAN's Paul Allen returns after week away, reiterates apology for 'paid protesters' quip",
      "date": "2026-05-27T10:55:51.375586Z",
      "sourceUrl": "https://www.msn.com/en-us/entertainment/celebrities/kfan-s-paul-allen-returns-after-week-away-reiterates-apology-for-paid-protesters-quip/ar-AA1VwlUt?ocid=BingNewsVerp"
    },
    {
      "type": "news",
      "title": "'Astroturf': Critics speculate Tesla protests are not a grassroots movement, but carefully organized campaign",
      "date": "2026-05-27T10:55:51.375586Z",
      "sourceUrl": "https://www.foxnews.com/politics/astroturf-critics-speculate-tesla-protests-not-grassroots-movement-carefully-organized-campaign"
    },
    {
      "type": "news",
      "title": "Tesla Terror Attacks Show Americans Aren\u2019t Buying the Left\u2019s Fake \u2018Grassroots\u2019 Game Anymore",
      "date": "2026-05-27T10:55:51.375586Z",
      "sourceUrl": "https://spectator.org/tesla-attack-american-not-buying-left-fake-grassroot/"
    },
    {
      "type": "news",
      "title": "Phoenix officer accused of provoking student protesters on paid leave",
      "date": "2026-05-27T06:58:15.714889Z",
      "sourceUrl": "https://www.aol.com/articles/phoenix-officer-accused-provoking-student-015721361.html"
    },
    {
      "type": "news",
      "title": "KFAN's Paul Allen returns after week away, reiterates apology for 'paid protesters' quip",
      "date": "2026-05-27T06:58:15.714889Z",
      "sourceUrl": "https://www.msn.com/en-us/news/us/kfans-paul-allen-returns-after-week-away-reiterates-apology-for-paid-protesters-quip/ar-AA1VwlUt?ocid=BingNewsVerp"
    },
    {
      "type": "news",
      "title": "Phoenix officer accused of provoking student protesters on paid leave",
      "date": "2026-05-27T06:58:15.714889Z",
      "sourceUrl": "https://www.usatoday.com/story/news/local/phoenix/2026/04/10/phoenix-police-officer-on-paid-leave-after-confrontation-at-protest/89560182007/"
    },
    {
      "type": "news",
      "title": "Are Minneapolis protesters paid, like the Trump administration says? Here's a fact check",
      "date": "2026-05-27T02:44:48.213107Z",
      "sourceUrl": "https://www.msn.com/en-ca/news/us/are-minneapolis-protesters-paid-like-the-trump-administration-says-here-s-a-fact-check/ar-AA1W1ReG"
    },
    {
      "type": "news",
      "title": "KFAN's Paul Allen returns after week away, reiterates apology for 'paid protesters' quip",
      "date": "2026-05-27T02:44:48.213107Z",
      "sourceUrl": "https://www.yahoo.com/entertainment/tv/articles/kfans-paul-allen-returns-week-194031958.html"
    },
    {
      "type": "news",
      "title": "Kevin O'Leary says data center campus protesters were 'bused in' from out of state",
      "date": "2026-05-27T02:44:48.213107Z",
      "sourceUrl": "https://www.sltrib.com/news/2026/05/05/kevin-oleary-says-protesters/"
    },
    {
      "type": "news",
      "title": "Phoenix officer accused of provoking student protesters on paid leave",
      "date": "2026-05-26T23:03:27.191970Z",
      "sourceUrl": "https://www.usatoday.com/story/news/local/phoenix/2026/04/10/phoenix-police-officer-on-paid-leave-after-confrontation-at-protest/89560182007/"
    },
    {
      "type": "news",
      "title": "KFAN's Paul Allen returns after week away, reiterates apology for 'paid protesters' quip",
      "date": "2026-05-26T23:03:27.191970Z",
      "sourceUrl": "https://www.msn.com/en-us/entertainment/celebrities/kfan-s-paul-allen-returns-after-week-away-reiterates-apology-for-paid-protesters-quip/ar-AA1VwlUt?ocid=BingNewsVerp"
    },
    {
      "type": "news",
      "title": "The brazen ad for rent-a-crowd protesters to attend anti-Israel rally in Melbourne",
      "date": "2026-05-26T23:03:27.191970Z",
      "sourceUrl": "https://www.msn.com/en-in/news/other/the-brazen-ad-for-rent-a-crowd-protesters-to-attend-anti-israel-rally-in-melbourne/ar-AA1WVqBb?ocid=BingNewsVerp"
    },
    {
      "type": "news",
      "title": "Phoenix officer accused of provoking student protesters on paid leave",
      "date": "2026-05-26T21:51:44.651915Z",
      "sourceUrl": "https://www.usatoday.com/story/news/local/phoenix/2026/04/10/phoenix-police-officer-on-paid-leave-after-confrontation-at-protest/89560182007/"
    },
    {
      "type": "news",
      "title": "KFAN's Paul Allen returns after week away, reiterates apology for 'paid protesters' quip",
      "date": "2026-05-26T21:51:44.651915Z",
      "sourceUrl": "https://www.msn.com/en-us/entertainment/celebrities/kfan-s-paul-allen-returns-after-week-away-reiterates-apology-for-paid-protesters-quip/ar-AA1VwlUt?ocid=BingNewsVerp"
    },
    {
      "type": "news",
      "title": "The brazen ad for rent-a-crowd protesters to attend anti-Israel rally in Melbourne",
      "date": "2026-05-26T21:51:44.651915Z",
      "sourceUrl": "https://www.msn.com/en-in/news/other/the-brazen-ad-for-rent-a-crowd-protesters-to-attend-anti-israel-rally-in-melbourne/ar-AA1WVqBb?ocid=BingNewsVerp"
    },
    {
      "type": "news",
      "title": "Are Minneapolis protesters paid, like the Trump administration says? Here's a fact check",
      "date": "2026-05-26T20:00:33.216605Z",
      "sourceUrl": "https://www.msn.com/en-ca/news/us/are-minneapolis-protesters-paid-like-the-trump-administration-says-here-s-a-fact-check/ar-AA1W1ReG"
    },
    {
      "type": "news",
      "title": "KFAN's Paul Allen returns after week away, reiterates apology for 'paid protesters' quip",
      "date": "2026-05-26T20:00:33.216605Z",
      "sourceUrl": "https://www.yahoo.com/entertainment/tv/articles/kfans-paul-allen-returns-week-194031958.html"
    },
    {
      "type": "news",
      "title": "Kevin O'Leary says data center campus protesters were 'bused in' from out of state",
      "date": "2026-05-26T20:00:33.216605Z",
      "sourceUrl": "https://www.sltrib.com/news/2026/05/05/kevin-oleary-says-protesters/"
    },
    {
      "type": "news",
      "title": "Phoenix officer accused of provoking student protesters on paid leave",
      "date": "2026-05-26T17:52:56.457998Z",
      "sourceUrl": "https://www.usatoday.com/story/news/local/phoenix/2026/04/10/phoenix-police-officer-on-paid-leave-after-confrontation-at-protest/89560182007/"
    },
    {
      "type": "news",
      "title": "KFAN's Paul Allen returns after week away, reiterates apology for 'paid protesters' quip",
      "date": "2026-05-26T17:52:56.457998Z",
      "sourceUrl": "https://www.msn.com/en-us/entertainment/celebrities/kfan-s-paul-allen-returns-after-week-away-reiterates-apology-for-paid-protesters-quip/ar-AA1VwlUt?ocid=BingNewsVerp"
    },
    {
      "type": "news",
      "title": "The brazen ad for rent-a-crowd protesters to attend anti-Israel rally in Melbourne",
      "date": "2026-05-26T17:52:56.457998Z",
      "sourceUrl": "https://www.msn.com/en-in/news/other/the-brazen-ad-for-rent-a-crowd-protesters-to-attend-anti-israel-rally-in-melbourne/ar-AA1WVqBb?ocid=BingNewsVerp"
    },
    {
      "type": "news",
      "title": "Sheriff calls protesters \u2018whack-jobs\u2019 after ICE comments blocked by Greenville C...",
      "date": "2026-05-26T14:52:14.249699Z",
      "sourceUrl": "https://www.foxcarolina.com/2026/05/21/sheriff-calls-protesters-whack-jobs-after-ice-comments-blocked-by-greenville-co-council/"
    },
    {
      "type": "news",
      "title": "Are Minneapolis protesters paid, like the Trump administration says? Here's a fact check",
      "date": "2026-05-26T14:52:14.249699Z",
      "sourceUrl": "https://www.msn.com/en-us/society-culture-and-history/human-rights/are-minneapolis-protesters-paid-like-the-trump-administration-says-here-s-a-fact-check/ar-AA1W1ReG"
    },
    {
      "type": "news",
      "title": "KFAN's Paul Allen returns after week away, reiterates apology for 'paid protesters' quip",
      "date": "2026-05-26T14:52:14.249699Z",
      "sourceUrl": "https://www.yahoo.com/entertainment/tv/articles/kfans-paul-allen-returns-week-194031958.html"
    },
    {
      "type": "news",
      "title": "Are Minneapolis protesters paid, like the Trump administration says? Here's a fact check",
      "date": "2026-05-26T07:42:29.161324Z",
      "sourceUrl": "https://www.msn.com/en-us/society-culture-and-history/human-rights/are-minneapolis-protesters-paid-like-the-trump-administration-says-here-s-a-fact-check/ar-AA1W1ReG"
    },
    {
      "type": "news",
      "title": "KFAN's Paul Allen returns after week away, reiterates apology for 'paid protesters' quip",
      "date": "2026-05-26T07:42:29.161324Z",
      "sourceUrl": "https://www.yahoo.com/entertainment/tv/articles/kfans-paul-allen-returns-week-194031958.html"
    },
    {
      "type": "news",
      "title": "The brazen ad for rent-a-crowd protesters to attend anti-Israel rally in Melbourne",
      "date": "2026-05-26T07:42:29.161324Z",
      "sourceUrl": "https://www.msn.com/en-us/news/world/the-brazen-ad-for-rent-a-crowd-protesters-to-attend-anti-israel-rally-in-melbourne/ar-AA1WVqrt"
    },
    {
      "type": "news",
      "title": "KFAN's Paul Allen returns after week away, reiterates apology for 'paid protesters' quip",
      "date": "2026-05-26T03:57:10.917757Z",
      "sourceUrl": "https://www.msn.com/en-us/entertainment/celebrities/kfan-s-paul-allen-returns-after-week-away-reiterates-apology-for-paid-protesters-quip/ar-AA1VwlUt?ocid=BingNewsVerp"
    },
    {
      "type": "news",
      "title": "Phoenix officer accused of provoking student protesters on paid leave",
      "date": "2026-05-26T03:57:10.917757Z",
      "sourceUrl": "https://www.msn.com/en-us/crime/general/phoenix-officer-accused-of-provoking-student-protesters-on-paid-leave/ar-AA20Chi3?ocid=BingNewsVerp"
    },
    {
      "type": "news",
      "title": "The brazen ad for rent-a-crowd protesters to attend anti-Israel rally in Melbourne",
      "date": "2026-05-26T03:57:10.917757Z",
      "sourceUrl": "https://www.msn.com/en-in/news/other/the-brazen-ad-for-rent-a-crowd-protesters-to-attend-anti-israel-rally-in-melbourne/ar-AA1WVqBb?ocid=BingNewsVerp"
    },
    {
      "type": "news",
      "title": "Phoenix officer accused of provoking student protesters on paid leave",
      "date": "2026-05-25T23:59:25.671580Z",
      "sourceUrl": "https://www.aol.com/articles/phoenix-officer-accused-provoking-student-015721361.html"
    },
    {
      "type": "news",
      "title": "Are Minneapolis protesters paid, like the Trump administration says? Here's a fact check",
      "date": "2026-05-25T23:59:25.671580Z",
      "sourceUrl": "https://www.cbsnews.com/minnesota/news/minneapolis-are-protesters-paid-fact-check/"
    },
    {
      "type": "news",
      "title": "KFAN's Paul Allen returns after week away, reiterates apology for 'paid protesters' quip",
      "date": "2026-05-25T23:59:25.671580Z",
      "sourceUrl": "https://www.yahoo.com/entertainment/tv/articles/kfans-paul-allen-returns-week-194031958.html"
    },
    {
      "type": "news",
      "title": "Sheriff calls protesters \u2018whack-jobs\u2019 after ICE comments blocked by Greenville C...",
      "date": "2026-05-25T22:09:58.429086Z",
      "sourceUrl": "https://www.foxcarolina.com/2026/05/21/sheriff-calls-protesters-whack-jobs-after-ice-comments-blocked-by-greenville-co-council/"
    },
    {
      "type": "news",
      "title": "Phoenix officer accused of provoking student protesters on paid leave",
      "date": "2026-05-25T22:09:58.429086Z",
      "sourceUrl": "https://www.aol.com/articles/phoenix-officer-accused-provoking-student-015721361.html"
    },
    {
      "type": "news",
      "title": "KFAN's Paul Allen returns after week away, reiterates apology for 'paid protesters' quip",
      "date": "2026-05-25T22:09:58.429086Z",
      "sourceUrl": "https://www.msn.com/en-us/entertainment/celebrities/kfan-s-paul-allen-returns-after-week-away-reiterates-apology-for-paid-protesters-quip/ar-AA1VwlUt?ocid=BingNewsVerp"
    },
    {
      "type": "news",
      "title": "Are Minneapolis protesters paid, like the Trump administration says? Here's a fact check",
      "date": "2026-05-25T20:58:55.157166Z",
      "sourceUrl": "https://www.cbsnews.com/minnesota/news/minneapolis-are-protesters-paid-fact-check/"
    },
    {
      "type": "news",
      "title": "KFAN's Paul Allen returns after week away, reiterates apology for 'paid protesters' quip",
      "date": "2026-05-25T20:58:55.157166Z",
      "sourceUrl": "https://www.yahoo.com/entertainment/tv/articles/kfans-paul-allen-returns-week-194031958.html"
    },
    {
      "type": "news",
      "title": "Kevin O'Leary says data center campus protesters were 'bused in' from out of state",
      "date": "2026-05-25T20:58:55.157166Z",
      "sourceUrl": "https://www.sltrib.com/news/2026/05/05/kevin-oleary-says-protesters/"
    },
    {
      "type": "news",
      "title": "Sheriff calls protesters \u2018whack-jobs\u2019 after ICE comments blocked by Greenville C...",
      "date": "2026-05-25T19:19:10.218459Z",
      "sourceUrl": "https://www.foxcarolina.com/2026/05/21/sheriff-calls-protesters-whack-jobs-after-ice-comments-blocked-by-greenville-co-council/"
    },
    {
      "type": "news",
      "title": "Phoenix officer accused of provoking student protesters on paid leave",
      "date": "2026-05-25T19:19:10.218459Z",
      "sourceUrl": "https://www.aol.com/articles/phoenix-officer-accused-provoking-student-015721361.html"
    },
    {
      "type": "news",
      "title": "KFAN's Paul Allen returns after week away, reiterates apology for 'paid protesters' quip",
      "date": "2026-05-25T19:19:10.218459Z",
      "sourceUrl": "https://www.msn.com/en-us/entertainment/celebrities/kfan-s-paul-allen-returns-after-week-away-reiterates-apology-for-paid-protesters-quip/ar-AA1VwlUt?ocid=BingNewsVerp"
    },
    {
      "type": "news",
      "title": "Sheriff calls protesters \u2018whack-jobs\u2019 after ICE comments blocked by Greenville C...",
      "date": "2026-05-25T17:02:05.035154Z",
      "sourceUrl": "https://www.foxcarolina.com/2026/05/21/sheriff-calls-protesters-whack-jobs-after-ice-comments-blocked-by-greenville-co-council/"
    },
    {
      "type": "news",
      "title": "Homeless people on Skid Row were paid to register to vote, feds charge",
      "date": "2026-05-25T17:02:05.035154Z",
      "sourceUrl": "https://www.yahoo.com/news/articles/homeless-people-skid-row-were-184119554.html"
    },
    {
      "type": "news",
      "title": "Are Minneapolis protesters paid, like the Trump administration says? Here's a fact check",
      "date": "2026-05-25T17:02:05.035154Z",
      "sourceUrl": "https://www.cbsnews.com/minnesota/news/minneapolis-are-protesters-paid-fact-check/"
    },
    {
      "type": "news",
      "title": "Phoenix officer accused of provoking student protesters on paid leave",
      "date": "2026-05-25T14:40:19.027840Z",
      "sourceUrl": "https://www.aol.com/articles/phoenix-officer-accused-provoking-student-015721361.html"
    },
    {
      "type": "news",
      "title": "KFAN's Paul Allen returns after week away, reiterates apology for 'paid protesters' quip",
      "date": "2026-05-25T14:40:19.027840Z",
      "sourceUrl": "https://www.msn.com/en-us/entertainment/celebrities/kfan-s-paul-allen-returns-after-week-away-reiterates-apology-for-paid-protesters-quip/ar-AA1VwlUt?ocid=BingNewsVerp"
    },
    {
      "type": "news",
      "title": "Phoenix officer accused of provoking student protesters on paid leave",
      "date": "2026-05-25T14:40:19.027840Z",
      "sourceUrl": "https://www.usatoday.com/story/news/local/phoenix/2026/04/10/phoenix-police-officer-on-paid-leave-after-confrontation-at-protest/89560182007/"
    },
    {
      "type": "news",
      "title": "Sheriff calls protesters \u2018whack-jobs\u2019 after ICE comments blocked by Greenville C...",
      "date": "2026-05-25T11:46:39.072253Z",
      "sourceUrl": "https://www.foxcarolina.com/2026/05/21/sheriff-calls-protesters-whack-jobs-after-ice-comments-blocked-by-greenville-co-council/"
    },
    {
      "type": "news",
      "title": "Homeless people on Skid Row were paid to register to vote, feds charge",
      "date": "2026-05-25T11:46:39.072253Z",
      "sourceUrl": "https://www.yahoo.com/news/articles/homeless-people-skid-row-were-184119554.html"
    },
    {
      "type": "news",
      "title": "Phoenix officer accused of provoking student protesters on paid leave",
      "date": "2026-05-25T11:46:39.072253Z",
      "sourceUrl": "https://www.aol.com/articles/phoenix-officer-accused-provoking-student-015721361.html"
    },
    {
      "type": "news",
      "title": "Sheriff calls protesters \u2018whack-jobs\u2019 after ICE comments blocked by Greenville C...",
      "date": "2026-05-25T07:07:17.427927Z",
      "sourceUrl": "https://www.foxcarolina.com/2026/05/21/sheriff-calls-protesters-whack-jobs-after-ice-comments-blocked-by-greenville-co-council/"
    },
    {
      "type": "news",
      "title": "Homeless people on Skid Row were paid to register to vote, feds charge",
      "date": "2026-05-25T07:07:17.427927Z",
      "sourceUrl": "https://www.yahoo.com/news/articles/homeless-people-skid-row-were-184119554.html"
    },
    {
      "type": "news",
      "title": "Are Minneapolis protesters paid, like the Trump administration says? Here's a fact check",
      "date": "2026-05-25T07:07:17.427927Z",
      "sourceUrl": "https://www.msn.com/en-us/society-culture-and-history/human-rights/are-minneapolis-protesters-paid-like-the-trump-administration-says-here-s-a-fact-check/ar-AA1W1ReG"
    },
    {
      "type": "news",
      "title": "The brazen ad for rent-a-crowd protesters to attend anti-Israel rally in Melbourne",
      "date": "2026-05-25T02:45:45.031798Z",
      "sourceUrl": "https://www.msn.com/en-us/news/world/the-brazen-ad-for-rent-a-crowd-protesters-to-attend-anti-israel-rally-in-melbourne/ar-AA1WVqrt?ocid=BingNewsVerp"
    }
  ],
  "recentNews": [
    {
      "title": "Trump says Delaney Hall protesters are 'paid' as clashes escalate outside NJ ICE facility",
      "url": "https://www.msn.com/en-us/news/world/trump-says-delaney-hall-protesters-are-paid-as-clashes-escalate-outside-nj-ice-facility/ar-AA24dJjM",
      "snippet": "President Trump dismissed Delaney Hall protesters as fake and paid for as Democratic lawmakers alleged overcrowding and poor conditions at the ICE detention center.",
      "publisher": "Fox News",
      "source": "duckduckgo",
      "query": "paid protesters",
      "date": "2026-05-27T23:01:00+00:00",
      "relevance_score": 95,
      "collected_at": "2026-05-28T02:43:51.998349Z"
    },
    {
      "title": "Trump says Delaney Hall protesters are 'paid' as clashes escalate outside NJ ICE facility",
      "url": "https://www.msn.com/en-us/news/news/trump-says-delaney-hall-protesters-are-paid-as-clashes-escalate-outside-nj-ice-facility/ar-AA24dJjM",
      "snippet": "President Trump dismissed Delaney Hall protesters as fake and paid for as Democratic lawmakers alleged overcrowding and poor conditions at the ICE detention center.",
      "publisher": "Fox News",
      "source": "duckduckgo",
      "query": "paid protesters",
      "date": "2026-05-27T22:23:33+00:00",
      "relevance_score": 95,
      "collected_at": "2026-05-28T06:47:04.079695Z"
    },
    {
      "title": "Trump says Delaney Hall protesters are 'paid for' amid ongoing clashes outside NJ ICE facility",
      "url": "https://www.msn.com/en-us/politics/government/trump-says-delaney-hall-protesters-are-paid-for-amid-ongoing-clashes-outside-nj-ice-facility/ar-AA24feqz",
      "snippet": "NEWARK, NEW JERSEY: President Donald Trump sharply dismissed protesters outside the Delaney Hall ICE detention facility on Wednesday, May 27, calling them \"fake\" and \"paid for\" as tensions continued escalating around the controversial Newark ...",
      "publisher": "MSN",
      "source": "duckduckgo",
      "query": "paid protesters",
      "date": "2026-05-28T04:50:00+00:00",
      "relevance_score": 95,
      "collected_at": "2026-05-28T06:47:04.079721Z"
    },
    {
      "title": "Trump says Delaney Hall protesters are 'paid' as clashes escalate outside NJ ICE facility",
      "url": "https://www.aol.com/news/trump-says-delaney-hall-protesters-222333653.html",
      "snippet": "President Trump dismissed Delaney Hall protesters as fake and paid for as Democratic lawmakers alleged overcrowding and poor conditions at the ICE detention center.",
      "publisher": "AOL",
      "source": "duckduckgo",
      "query": "paid protesters",
      "date": "2026-05-28T08:28:00+00:00",
      "relevance_score": 95,
      "collected_at": "2026-05-28T10:48:46.588231Z"
    },
    {
      "title": "Trump says Delaney Hall protesters are \u2018paid\u2019 as clashes escalate outside NJ ICE...",
      "url": "https://www.yahoo.com/news/politics/articles/trump-says-delaney-hall-protesters-222333517.html",
      "snippet": "President Trump dismissed Delaney Hall protesters as fake and paid for as Democratic lawmakers...",
      "publisher": "Fox News \u00b7 via Yahoo News",
      "source": "duckduckgo",
      "query": "paid protesters",
      "date": "2026-05-28T05:08:28+00:00",
      "relevance_score": 95,
      "collected_at": "2026-05-29T05:08:28.309273Z"
    },
    {
      "type": "news",
      "source": "google_news",
      "title": "Astroturfing: Understanding and Addressing the Influence of Fake Grassroots Movements Across Diverse Domains on Social Media Platforms - springerprofessional.de",
      "url": "https://news.google.com/rss/articles/CBMisgFBVV95cUxNUGtWSVFHXzN4RFhsRE5URk1OLUk0TEVONDhKUzhpdWNLZVpuRzZaOUF6d1EwQ0s3MWxwanY3Y2lVbm1fM3RtNVBrVURLczViVUdtQmVyMVk4U2RJWWJGR0l1VXpNRXR3SW1xcER6a2J6NTJKdnVIYmdqVHktal9KM0RZV1ZYZ1V5bFgxYTNtdlJtQXJPdHlLVFNSTG15T3AzYUM4WlhzTjdsbnlXNm15Yi1B?oc=5",
      "date": "2025-08-01T11:42:20Z",
      "publisher": "springerprofessional.de",
      "query": "fake grassroots",
      "relevance_score": 90,
      "location": ""
    },
    {
      "type": "news",
      "source": "google_news",
      "title": "What political ads are Australians seeing online? Astroturfing, fake grassroots groups, and outright falsehoods - The Conversation",
      "url": "https://news.google.com/rss/articles/CBMi2wFBVV95cUxPYmhmX1ZCSFFLYkxnbUljVWpsR0EtcVNfRVdjZ2NlN0FWdnQ3YmYwTUc1WXNSLXVCUDJRN3Z6anZXV0FfNlNTNktqZ3BvbkN2bWFNdk9KX3FFSWlCNS1HVlZsQXdKeUxhM2VEQTZSMzF3SWloV3Rubk1OR3loYk9WcFRpS2FmeFF5aDlGS2pzMDB4b3JpVF9QbzlFQ3ljVHVFMjFkMTJwbVhWNGdTNktsMTUzazNqbGZSTXpHdDlNeGdBOHlBSUFCOFE3MVZueEhDY08wTDZsWWdIRjg?oc=5",
      "date": "2025-04-27T07:00:00Z",
      "publisher": "The Conversation",
      "query": "fake grassroots",
      "relevance_score": 90,
      "location": ""
    },
    {
      "title": "Kenyan authorities paid trolls to threaten Gen Z protesters, Amnesty says",
      "url": "https://www.msn.com/en-us/news/world/kenyan-authorities-paid-trolls-to-threaten-gen-z-protesters-amnesty-says/ar-AA1QK7z1?ocid=BingNewsVerp",
      "snippet": "The Kenyan authorities paid a network of trolls to threaten and intimidate young protesters during recent anti-government demonstrations, Amnesty International has said. A new report by the human ...",
      "publisher": "MSN",
      "source": "duckduckgo",
      "query": "paid protesters",
      "date": "2025-11-19T00:00:00+00:00",
      "relevance_score": 90,
      "collected_at": "2026-01-10T01:21:18.722473Z"
    },
    {
      "title": "Masked agitator tells Laura Ingraham she's 'getting paid right now' at anti-ICE protest",
      "url": "https://www.msn.com/en-us/news/us/masked-agitator-tells-laura-ingraham-she-s-getting-paid-right-now-at-anti-ice-protest/ar-AA1TUzeF",
      "snippet": "Protester says she's 'getting paid right now' during exchange with Fox News host at Minneapolis anti-ICE demonstrations after a deadly shooting involving a federal agent.",
      "publisher": "Fox News",
      "source": "duckduckgo",
      "query": "paid protesters",
      "date": "2026-01-09T20:10:00+00:00",
      "relevance_score": 90,
      "collected_at": "2026-01-10T15:13:50.667635Z"
    },
    {
      "title": "Paid protest CEO urges Congress to pass law exposing who funds demonstrations",
      "url": "https://www.msn.com/en-us/politics/government/paid-protest-ceo-urges-congress-to-pass-law-exposing-who-funds-demonstrations/ar-AA1QhM7J",
      "snippet": "(NewsNation) \u2014 The CEO of a company that provides paid protesters for events is asking members of Congress to pass a \"Transparency in Political Demonstration Act\" that would expose the groups hiring demonstrators to attend events around the U.S. Adam ...",
      "publisher": "MSN",
      "source": "duckduckgo",
      "query": "paid protesters",
      "date": "2025-11-12T12:30:00+00:00",
      "relevance_score": 90,
      "collected_at": "2026-01-10T19:11:12.300746Z"
    },
    {
      "title": "Masked agitator tells Laura Ingraham she's 'getting paid right now' at anti-ICE protest",
      "url": "https://www.foxnews.com/media/masked-agitator-tells-laura-ingraham-shes-getting-paid-right-now-during-anti-ice-protest",
      "snippet": "Protester says she's 'getting paid right now' during exchange with Fox News host at Minneapolis anti-ICE demonstrations after a deadly shooting involving a federal agent.",
      "publisher": "Fox News",
      "source": "duckduckgo",
      "query": "paid protesters",
      "date": "2026-01-09T20:10:00+00:00",
      "relevance_score": 90,
      "collected_at": "2026-01-12T09:26:09.060233Z"
    },
    {
      "title": "Paid protest CEO urges Congress to pass law exposing who funds demonstrations",
      "url": "https://www.msn.com/en-us/politics/government/paid-protest-ceo-urges-congress-to-pass-law-exposing-who-funds-demonstrations/ar-AA1QhM7J?ocid=BingNewsVerp",
      "snippet": "(NewsNation) \u2014 The CEO of a company that provides paid protesters for events is asking members of Congress to pass a \u201cTransparency in Political Demonstration Act\u201d that would expose the groups hiring ...",
      "publisher": "MSN",
      "source": "duckduckgo",
      "query": "paid protesters",
      "date": "2025-11-12T00:00:00+00:00",
      "relevance_score": 90,
      "collected_at": "2026-01-13T08:22:00.645271Z"
    },
    {
      "title": "'They Use Serious Hammers': Trump Discredits Himself When He Tries To Prove The Existence Of 'Paid' Protesters In Oval Office Rant",
      "url": "https://www.msn.com/en-us/video/weather/they-use-serious-hammers-trump-discredits-himself-when-he-tries-to-prove-the-existence-of-paid-protesters-in-oval-office-rant/vi-AA1Rgx4R?ocid=BingNewsVerp",
      "snippet": "Donald Trump signed a memorandum to deploy troops in Memphis several weeks ago from the Oval Office. During Q&A with the press, Trump tried to prove that protesters in cities are paid and part of some ...",
      "publisher": "MSN",
      "source": "duckduckgo",
      "query": "paid protesters",
      "date": "2025-11-27T00:00:00+00:00",
      "relevance_score": 90,
      "collected_at": "2026-01-13T08:22:00.645281Z"
    },
    {
      "title": "New Milford residents angry official alleged \u2018No Kings' protesters were paid",
      "url": "https://www.msn.com/en-us/politics/government/new-milford-residents-angry-official-alleged-no-kings-protesters-were-paid/ar-AA1PyAdK?ocid=BingNewsVerp",
      "snippet": "NEW MILFORD \u2013 Area residents who participated in the recent \"No Kings\" protest recently voiced their disappointment at a Town Council member's comments that claimed they were \"paid\" to protest. More ...",
      "publisher": "MSN",
      "source": "duckduckgo",
      "query": "paid protesters",
      "date": "2025-10-31T00:00:00+00:00",
      "relevance_score": 90,
      "collected_at": "2026-01-15T03:26:04.162758Z"
    },
    {
      "title": "'STOP TRUMP' Craigslist ad recruiting paid protesters isn't from January 2026",
      "url": "https://www.msn.com/en-us/news/us/stop-trump-craigslist-ad-recruiting-paid-protesters-isnt-from-january-2026/ar-AA1UhUi9",
      "snippet": "A photo circulating online authentically showed a Craigslist ad from January 2026 recruiting paid protesters to demonstrate against U.S. President Donald Trump. The alleged advertisement was offering people up to $1,",
      "publisher": "Snopes",
      "source": "duckduckgo",
      "query": "paid protesters",
      "date": "2026-01-15T16:00:00+00:00",
      "relevance_score": 90,
      "collected_at": "2026-01-15T17:27:07.212741Z"
    },
    {
      "title": "Fact Check: Is 'Stop Trump' Craigslist ad recruiting paid protesters from January 2026 real?",
      "url": "https://news.meaww.com/fact-check-is-stop-trump-craigslist-ad-recruiting-paid-protesters-from-january-2026-real",
      "snippet": "On January 10, a Facebook user posted a picture of the Craigslist ad. The caption of the post read, \"'Stop Trump' Craigslist ad recruiting paid protesters from January 2026. Let's stop pretending this is 'activism'.\"",
      "publisher": "MEAWW News",
      "source": "duckduckgo",
      "query": "paid protesters",
      "date": "2026-01-16T03:08:00+00:00",
      "relevance_score": 90,
      "collected_at": "2026-01-16T04:34:34.917186Z"
    },
    {
      "title": "'STOP TRUMP' Craigslist ad recruiting paid protesters isn't from January 2026",
      "url": "https://www.msn.com/en-us/news/us/stop-trump-craigslist-ad-recruiting-paid-protesters-isnt-from-january-2026/ar-AA1UhUi9?ocid=BingNewsVerp",
      "snippet": "A photo circulating online authentically showed a Craigslist ad from January 2026 recruiting paid protesters to demonstrate ...",
      "publisher": "Snopes on MSN",
      "source": "duckduckgo",
      "query": "paid protesters",
      "date": "2025-12-31T08:21:19+00:00",
      "relevance_score": 90,
      "collected_at": "2026-01-16T08:21:20.071897Z"
    },
    {
      "title": "'They have brand-new, beautiful printed signs': Trump discredits himself when he explains why protesters are 'paid' by Democrats",
      "url": "https://www.msn.com/en-us/video/news/they-have-brand-new-beautiful-printed-signs-trump-discredits-himself-when-he-explains-why-protesters-are-paid-by-democrats/vi-AA1TJQqT?ocid=BingNewsVerp",
      "snippet": "During his remarks to House Republicans at the Kennedy Center yesterday, Donald Trump claimed protesters against him are \"paid\" by the radical left. Why does Trump think they're \"paid people\"? Because ...",
      "publisher": "Slingshot News on MSN",
      "source": "duckduckgo",
      "query": "paid protesters",
      "date": "2026-01-08T04:36:54+00:00",
      "relevance_score": 90,
      "collected_at": "2026-01-18T04:36:54.171416Z"
    },
    {
      "title": "'They Use Serious Hammers': Trump Discredits Himself When He Tries To Prove The Existence Of 'Paid' Protesters In Oval Office Rant",
      "url": "https://www.msn.com/en-us/politics/government/they-use-serious-hammers-trump-discredits-himself-when-he-tries-to-prove-the-existence-of-paid-protesters-in-oval-office-rant/vi-AA1Rgx4R?ocid=BingNewsVerp",
      "snippet": "Donald Trump signed a memorandum to deploy troops in Memphis several weeks ago from the Oval Office. During Q&A with the press, Trump tried to prove that protesters in cities are paid and part of some ...",
      "publisher": "MSN",
      "source": "duckduckgo",
      "query": "paid protesters",
      "date": "2025-11-27T00:00:00+00:00",
      "relevance_score": 90,
      "collected_at": "2026-01-18T04:36:54.171422Z"
    },
    {
      "title": "Let\u2019s settle once and for all whether protesters are \u2018paid\u2019 | Letters",
      "url": "https://www.yahoo.com/news/articles/let-settle-once-whether-protesters-233706168.html",
      "snippet": "Let\u2019s settle once and for all whether protesters are \u2018 paid \u2019 President Donald Trump has repeatedly ca...",
      "publisher": "The Des Moines Register",
      "source": "duckduckgo",
      "query": "paid protesters",
      "date": "2026-01-17T23:15:08+00:00",
      "relevance_score": 90,
      "collected_at": "2026-01-18T07:15:08.121826Z"
    }
  ],
  "jobPostings": [
    {
      "type": "job_posting",
      "source": "adzuna",
      "title": "SEM Strategist (North America)",
      "company": "Palo Alto Networks",
      "city": "US",
      "state": "",
      "url": "https://www.adzuna.com/land/ad/5665795527?se=PmYsbxxb8RGtYNFAtJjkyA&utm_medium=api&utm_source=a70fa881&v=D6B87818C6F548A942B213C133D0C8534CD84ECF",
      "date": "2026-05-29T05:08:30.936131Z",
      "salary_min": 170542.45,
      "salary_max": 170542.45,
      "suspicion_score": 0,
      "keywords": [
        "campaign field"
      ],
      "is_monitoring_entry": false
    },
    {
      "type": "job_posting",
      "source": "adzuna",
      "title": "Marketing Administrator",
      "company": "REDSTONE RANCH LLC",
      "city": "US",
      "state": "",
      "url": "https://www.adzuna.com/land/ad/5739864616?se=PmYsbxxb8RGtYNFAtJjkyA&utm_medium=api&utm_source=a70fa881&v=94B20ED5D60DC3B52338C11B066361DA8DFF268B",
      "date": "2026-05-29T05:08:30.936157Z",
      "salary_min": 32849.81,
      "salary_max": 32849.81,
      "suspicion_score": 0,
      "keywords": [
        "campaign field"
      ],
      "is_monitoring_entry": false
    },
    {
      "type": "job_posting",
      "source": "adzuna",
      "title": "Senior Alliance Manager, AWS",
      "company": "Palo Alto Networks",
      "city": "US",
      "state": "",
      "url": "https://www.adzuna.com/land/ad/5744002320?se=PmYsbxxb8RGtYNFAtJjkyA&utm_medium=api&utm_source=a70fa881&v=77B95365C76B9F531F8F752D301143181D13DA64",
      "date": "2026-05-29T05:08:30.936208Z",
      "salary_min": 232192.9,
      "salary_max": 232192.9,
      "suspicion_score": 0,
      "keywords": [
        "campaign field"
      ],
      "is_monitoring_entry": false
    },
    {
      "type": "job_posting",
      "source": "adzuna",
      "title": "Sr Field Marketing Manager, Amazon Business",
      "company": "Amazon",
      "city": "US",
      "state": "",
      "url": "https://www.adzuna.com/land/ad/5710742715?se=PmYsbxxb8RGtYNFAtJjkyA&utm_medium=api&utm_source=a70fa881&v=6AC49758986D3841A3D8EC700603D3810741110D",
      "date": "2026-05-29T05:08:30.936231Z",
      "salary_min": 273466.97,
      "salary_max": 273466.97,
      "suspicion_score": 0,
      "keywords": [
        "campaign field"
      ],
      "is_monitoring_entry": false
    },
    {
      "type": "job_posting",
      "source": "adzuna",
      "title": "Political/Community Organizer",
      "company": "SEIU USWW",
      "city": "US",
      "state": "",
      "url": "https://www.adzuna.com/details/5647690792?utm_medium=api&utm_source=a70fa881",
      "date": "2026-05-29T05:08:31.360500Z",
      "salary_min": 84229.38,
      "salary_max": 84229.38,
      "suspicion_score": 0,
      "keywords": [
        "community organizer political"
      ],
      "is_monitoring_entry": false
    },
    {
      "type": "job_posting",
      "source": "adzuna",
      "title": "Policy Coordinator",
      "company": "CAIR San Francisco Bay Area",
      "city": "US",
      "state": "",
      "url": "https://www.adzuna.com/details/5628247845?utm_medium=api&utm_source=a70fa881",
      "date": "2026-05-29T05:08:31.360585Z",
      "salary_min": 64438,
      "salary_max": 69700,
      "suspicion_score": 0,
      "keywords": [
        "community organizer political"
      ],
      "is_monitoring_entry": false
    },
    {
      "type": "job_posting",
      "source": "adzuna",
      "title": "Shift Supervisor",
      "company": "Graham-Windham Inc.",
      "city": "US",
      "state": "",
      "url": "https://www.adzuna.com/details/5391538151?utm_medium=api&utm_source=a70fa881",
      "date": "2026-05-29T05:08:31.360646Z",
      "salary_min": 54605.57,
      "salary_max": 54605.57,
      "suspicion_score": 0,
      "keywords": [
        "community organizer political"
      ],
      "is_monitoring_entry": false
    },
    {
      "type": "job_posting",
      "source": "adzuna",
      "title": "Organizing Director, SEIU Local 221",
      "company": "Current SEIU",
      "city": "US",
      "state": "",
      "url": "https://www.adzuna.com/details/5532915397?utm_medium=api&utm_source=a70fa881",
      "date": "2026-05-29T05:08:31.360672Z",
      "salary_min": 110000,
      "salary_max": 120000,
      "suspicion_score": 0,
      "keywords": [
        "community organizer political"
      ],
      "is_monitoring_entry": false
    },
    {
      "type": "job_posting",
      "source": "adzuna",
      "title": "JTF-Gold Mobility Coordinator",
      "company": "Na Oiwi Kane",
      "city": "US",
      "state": "",
      "url": "https://www.adzuna.com/land/ad/5734643078?se=xqqgbxxb8RGMrfc9M6jWzw&utm_medium=api&utm_source=a70fa881&v=162559ECC37925BEDC00EA3E69EF7E49CEA0148A",
      "date": "2026-05-29T05:08:31.705212Z",
      "salary_min": 59802.24,
      "salary_max": 59802.24,
      "suspicion_score": 0,
      "keywords": [
        "mobilization coordinator"
      ],
      "is_monitoring_entry": false
    },
    {
      "type": "job_posting",
      "source": "adzuna",
      "title": "JTF-Gold Mobility Coordinator with Security Clearance",
      "company": "Honu Services",
      "city": "US",
      "state": "",
      "url": "https://www.adzuna.com/land/ad/5740541927?se=xqqgbxxb8RGMrfc9M6jWzw&utm_medium=api&utm_source=a70fa881&v=F3CAE7C993DB58913F5038E1DA5DFBD398417001",
      "date": "2026-05-29T05:08:31.705272Z",
      "salary_min": 97339.67,
      "salary_max": 97339.67,
      "suspicion_score": 0,
      "keywords": [
        "mobilization coordinator"
      ],
      "is_monitoring_entry": false
    },
    {
      "type": "job_posting",
      "source": "adzuna",
      "title": "Mobility Management Coordinator",
      "company": "Schaeffler",
      "city": "US",
      "state": "",
      "url": "https://www.adzuna.com/land/ad/5731959034?se=xqqgbxxb8RGMrfc9M6jWzw&utm_medium=api&utm_source=a70fa881&v=91754F9E7AB589F9A42E995A2D2EA2F616DAE520",
      "date": "2026-05-29T05:08:31.705292Z",
      "salary_min": 89360.29,
      "salary_max": 89360.29,
      "suspicion_score": 0,
      "keywords": [
        "mobilization coordinator"
      ],
      "is_monitoring_entry": false
    },
    {
      "type": "job_posting",
      "source": "adzuna",
      "title": "Mobility Program Coordinator",
      "company": "System One",
      "city": "US",
      "state": "",
      "url": "https://www.adzuna.com/land/ad/5742865605?se=xqqgbxxb8RGMrfc9M6jWzw&utm_medium=api&utm_source=a70fa881&v=ADBD75C3CBF2B4A1C74E386DD4D6DCCDF0A40272",
      "date": "2026-05-29T05:08:31.705313Z",
      "salary_min": 81649.75,
      "salary_max": 81649.75,
      "suspicion_score": 0,
      "keywords": [
        "mobilization coordinator"
      ],
      "is_monitoring_entry": false
    },
    {
      "type": "job_posting",
      "source": "adzuna",
      "title": "Air Mobility Coordinator",
      "company": "Topsarge Business Solutions",
      "city": "US",
      "state": "",
      "url": "https://www.adzuna.com/details/5431242285?utm_medium=api&utm_source=a70fa881",
      "date": "2026-05-29T05:08:31.705377Z",
      "salary_min": 90000,
      "salary_max": 95000,
      "suspicion_score": 0,
      "keywords": [
        "mobilization coordinator"
      ],
      "is_monitoring_entry": false
    },
    {
      "type": "job_posting",
      "source": "adzuna",
      "title": "Matter Mobility Coordinator",
      "company": "Davis Wright Tremaine LLP",
      "city": "US",
      "state": "",
      "url": "https://www.adzuna.com/details/5727941047?utm_medium=api&utm_source=a70fa881",
      "date": "2026-05-29T05:08:31.705398Z",
      "salary_min": 79996,
      "salary_max": 88524,
      "suspicion_score": 0,
      "keywords": [
        "mobilization coordinator"
      ],
      "is_monitoring_entry": false
    },
    {
      "type": "job_posting",
      "source": "adzuna",
      "title": "Environmental Organizer Full Time/Internship/Part Time",
      "company": "Clean Water Action",
      "city": "US",
      "state": "",
      "url": "https://www.adzuna.com/details/5729168146?utm_medium=api&utm_source=a70fa881",
      "date": "2026-05-29T09:40:35.572011Z",
      "salary_min": 40556.63,
      "salary_max": 40556.63,
      "suspicion_score": 30,
      "keywords": [
        "grassroots organizer"
      ],
      "is_monitoring_entry": false
    },
    {
      "type": "job_posting",
      "source": "adzuna",
      "title": "Canvasser - Queens",
      "company": "North Shore Strategies",
      "city": "US",
      "state": "",
      "url": "https://www.adzuna.com/details/5698464642?utm_medium=api&utm_source=a70fa881",
      "date": "2026-05-29T09:40:34.841564Z",
      "salary_min": 80513.85,
      "salary_max": 80513.85,
      "suspicion_score": 20,
      "keywords": [
        "canvasser political"
      ],
      "is_monitoring_entry": false
    },
    {
      "type": "job_posting",
      "source": "adzuna",
      "title": "Canvasser - Manhattan",
      "company": "North Shore Strategies",
      "city": "US",
      "state": "",
      "url": "https://www.adzuna.com/details/5698464649?utm_medium=api&utm_source=a70fa881",
      "date": "2026-05-29T09:40:34.841583Z",
      "salary_min": 89925.55,
      "salary_max": 89925.55,
      "suspicion_score": 20,
      "keywords": [
        "canvasser political"
      ],
      "is_monitoring_entry": false
    },
    {
      "type": "job_posting",
      "source": "adzuna",
      "title": "Canvasser - Staten Island",
      "company": "North Shore Strategies",
      "city": "US",
      "state": "",
      "url": "https://www.adzuna.com/details/5698464644?utm_medium=api&utm_source=a70fa881",
      "date": "2026-05-29T09:40:34.841633Z",
      "salary_min": 93191.55,
      "salary_max": 93191.55,
      "suspicion_score": 20,
      "keywords": [
        "canvasser political"
      ],
      "is_monitoring_entry": false
    },
    {
      "type": "job_posting",
      "source": "adzuna",
      "title": "Canvasser - Bronx",
      "company": "North Shore Strategies",
      "city": "US",
      "state": "",
      "url": "https://www.adzuna.com/details/5698464639?utm_medium=api&utm_source=a70fa881",
      "date": "2026-05-29T09:40:34.841649Z",
      "salary_min": 91626.52,
      "salary_max": 91626.52,
      "suspicion_score": 20,
      "keywords": [
        "canvasser political"
      ],
      "is_monitoring_entry": false
    },
    {
      "type": "job_posting",
      "source": "adzuna",
      "title": "Canvasser - Buffalo",
      "company": "North Shore Strategies",
      "city": "US",
      "state": "",
      "url": "https://www.adzuna.com/details/5734719229?utm_medium=api&utm_source=a70fa881",
      "date": "2026-05-29T09:40:34.841666Z",
      "salary_min": 90814.7,
      "salary_max": 90814.7,
      "suspicion_score": 20,
      "keywords": [
        "canvasser political"
      ],
      "is_monitoring_entry": false
    },
    {
      "type": "job_posting",
      "source": "adzuna",
      "title": "Canvasser - Syracuse",
      "company": "North Shore Strategies",
      "city": "US",
      "state": "",
      "url": "https://www.adzuna.com/details/5734719230?utm_medium=api&utm_source=a70fa881",
      "date": "2026-05-29T09:40:34.841681Z",
      "salary_min": 72350.02,
      "salary_max": 72350.02,
      "suspicion_score": 20,
      "keywords": [
        "canvasser political"
      ],
      "is_monitoring_entry": false
    },
    {
      "type": "job_posting",
      "source": "adzuna",
      "title": "Regional Coordinator, Coastal MS",
      "company": "Mississippi Votes",
      "city": "US",
      "state": "",
      "url": "https://www.adzuna.com/land/ad/5742337786?se=CnVbcUJb8RGrcsb7COxaHg&utm_medium=api&utm_source=a70fa881&v=6034524C3F47CC1726CDECBE5DF3B0B8976882B5",
      "date": "2026-05-29T09:40:35.571977Z",
      "salary_min": 45402.21,
      "salary_max": 45402.21,
      "suspicion_score": 20,
      "keywords": [
        "grassroots organizer"
      ],
      "is_monitoring_entry": false
    },
    {
      "type": "job_posting",
      "source": "adzuna",
      "title": "Regional Canvass Manager - Columbia",
      "company": "Civics Education Project",
      "city": "US",
      "state": "",
      "url": "https://www.adzuna.com/details/5500535138?utm_medium=api&utm_source=a70fa881",
      "date": "2026-05-29T09:40:35.572089Z",
      "salary_min": 59549.66,
      "salary_max": 59549.66,
      "suspicion_score": 20,
      "keywords": [
        "grassroots organizer"
      ],
      "is_monitoring_entry": false
    },
    {
      "type": "job_posting",
      "source": "adzuna",
      "title": "Quality Control Manager - Neighborhood Captains Program",
      "company": "Movement Labs",
      "city": "US",
      "state": "",
      "url": "https://www.adzuna.com/details/5742783465?utm_medium=api&utm_source=a70fa881",
      "date": "2026-05-29T09:40:37.186642Z",
      "salary_min": 81875,
      "salary_max": 91875,
      "suspicion_score": 20,
      "keywords": [
        "community organizer political"
      ],
      "is_monitoring_entry": false
    },
    {
      "type": "job_posting",
      "source": "adzuna",
      "title": "Paid Canvasser",
      "company": "Always United LLC",
      "city": "US",
      "state": "",
      "url": "https://www.adzuna.com/land/ad/5740393686?se=xi3xcEJb8RGrcsb7COxaHg&utm_medium=api&utm_source=a70fa881&v=3B4BC6A43E64239E29546D4046E58CF4BABBD167",
      "date": "2026-05-29T09:40:34.841526Z",
      "salary_min": 36000,
      "salary_max": 45000,
      "suspicion_score": 10,
      "keywords": [
        "canvasser political"
      ],
      "is_monitoring_entry": false
    },
    {
      "type": "job_posting",
      "source": "adzuna",
      "title": "Political Roles",
      "company": "Talarico for Texas",
      "city": "US",
      "state": "",
      "url": "https://www.adzuna.com/details/5408399336?utm_medium=api&utm_source=a70fa881",
      "date": "2026-05-29T09:40:35.571994Z",
      "salary_min": 58642.65,
      "salary_max": 58642.65,
      "suspicion_score": 10,
      "keywords": [
        "grassroots organizer"
      ],
      "is_monitoring_entry": false
    },
    {
      "type": "job_posting",
      "source": "adzuna",
      "title": "Regional Political Engagement Director",
      "company": "AIPAC",
      "city": "US",
      "state": "",
      "url": "https://www.adzuna.com/details/4950628330?utm_medium=api&utm_source=a70fa881",
      "date": "2026-05-29T09:40:36.080916Z",
      "salary_min": 125000,
      "salary_max": 165000,
      "suspicion_score": 10,
      "keywords": [
        "political activist"
      ],
      "is_monitoring_entry": false
    },
    {
      "type": "job_posting",
      "source": "adzuna",
      "title": "Coordinator (Strategic Campaign Manager)",
      "company": "Service Employees International Union",
      "city": "US",
      "state": "",
      "url": "https://www.adzuna.com/details/5639894384?utm_medium=api&utm_source=a70fa881",
      "date": "2026-05-29T09:40:37.186596Z",
      "salary_min": 113083,
      "salary_max": 118808,
      "suspicion_score": 10,
      "keywords": [
        "community organizer political"
      ],
      "is_monitoring_entry": false
    },
    {
      "type": "job_posting",
      "source": "adzuna",
      "title": "Community and Advocacy Organizer",
      "company": "Nc Association Of Ed",
      "city": "US",
      "state": "",
      "url": "https://www.adzuna.com/details/4811113387?utm_medium=api&utm_source=a70fa881",
      "date": "2026-05-29T09:40:37.186624Z",
      "salary_min": 90420.45,
      "salary_max": 90420.45,
      "suspicion_score": 10,
      "keywords": [
        "community organizer political"
      ],
      "is_monitoring_entry": false
    },
    {
      "type": "job_posting",
      "source": "adzuna",
      "title": "Advocacy Campaign Strategist, Elections and Government Program",
      "company": "Brennan Center for Justice",
      "city": "US",
      "state": "",
      "url": "https://www.adzuna.com/details/5683283119?utm_medium=api&utm_source=a70fa881",
      "date": "2026-05-29T09:40:37.979088Z",
      "salary_min": 103441.5,
      "salary_max": 103441.5,
      "suspicion_score": 10,
      "keywords": [
        "advocacy campaign"
      ],
      "is_monitoring_entry": false
    },
    {
      "type": "job_posting",
      "source": "adzuna",
      "title": "Senior Director, Campaigns & Advocacy",
      "company": "Microsoft Corporation",
      "city": "US",
      "state": "",
      "url": "https://www.adzuna.com/land/ad/5744280369?se=3mTIckJb8RGolK7N6UODIQ&utm_medium=api&utm_source=a70fa881&v=20C313DECA6DB78BE5716EE2A715C74BA4E6E98F",
      "date": "2026-05-29T09:40:37.979125Z",
      "salary_min": 168508.33,
      "salary_max": 168508.33,
      "suspicion_score": 10,
      "keywords": [
        "advocacy campaign"
      ],
      "is_monitoring_entry": false
    },
    {
      "type": "job_posting",
      "source": "adzuna",
      "title": "Senior Administrator, Policy, Advocacy & Campaigns (S3)",
      "company": "Save the Children 2022",
      "city": "US",
      "state": "",
      "url": "https://www.adzuna.com/details/5730159207?utm_medium=api&utm_source=a70fa881",
      "date": "2026-05-29T09:40:37.979162Z",
      "salary_min": 50150,
      "salary_max": 56050,
      "suspicion_score": 10,
      "keywords": [
        "advocacy campaign"
      ],
      "is_monitoring_entry": false
    },
    {
      "type": "job_posting",
      "source": "adzuna",
      "title": "Assistant Account Manager",
      "company": "TSG - The Sheridan Group",
      "city": "US",
      "state": "",
      "url": "https://www.adzuna.com/land/ad/5723038483?se=3mTIckJb8RGolK7N6UODIQ&utm_medium=api&utm_source=a70fa881&v=3A4B40538543FC75C10A8EE620BE0DBE4BD31649",
      "date": "2026-05-29T09:40:37.979180Z",
      "salary_min": 58000,
      "salary_max": 78000,
      "suspicion_score": 10,
      "keywords": [
        "advocacy campaign"
      ],
      "is_monitoring_entry": false
    },
    {
      "type": "job_posting",
      "source": "adzuna",
      "title": "Prepress Technician",
      "company": "TSG - The Sheridan Group",
      "city": "US",
      "state": "",
      "url": "https://www.adzuna.com/land/ad/5723038495?se=3mTIckJb8RGolK7N6UODIQ&utm_medium=api&utm_source=a70fa881&v=2DF697929A4A0B9E214E384C2329CC90D8AD3B0D",
      "date": "2026-05-29T09:40:37.979197Z",
      "salary_min": 56000,
      "salary_max": 71000,
      "suspicion_score": 10,
      "keywords": [
        "advocacy campaign"
      ],
      "is_monitoring_entry": false
    },
    {
      "type": "job_posting",
      "source": "adzuna",
      "title": "Political Director, SEIU Local 521",
      "company": "Current SEIU",
      "city": "US",
      "state": "",
      "url": "https://www.adzuna.com/details/5543529916?utm_medium=api&utm_source=a70fa881",
      "date": "2026-05-29T09:40:36.080995Z",
      "salary_min": 128410,
      "salary_max": 141926,
      "suspicion_score": 0,
      "keywords": [
        "political activist"
      ],
      "is_monitoring_entry": false
    },
    {
      "type": "job_posting",
      "source": "adzuna",
      "title": "Political Organizer, 1199 SEIU",
      "company": "Current SEIU",
      "city": "US",
      "state": "",
      "url": "https://www.adzuna.com/details/5684819735?utm_medium=api&utm_source=a70fa881",
      "date": "2026-05-29T09:40:36.081039Z",
      "salary_min": 37502.6,
      "salary_max": 37502.6,
      "suspicion_score": 0,
      "keywords": [
        "political activist"
      ],
      "is_monitoring_entry": false
    },
    {
      "type": "job_posting",
      "source": "adzuna",
      "title": "Operations Assistant",
      "company": "Nardello",
      "city": "US",
      "state": "",
      "url": "https://www.adzuna.com/details/5677752464?utm_medium=api&utm_source=a70fa881",
      "date": "2026-05-29T09:40:36.081103Z",
      "salary_min": 62000,
      "salary_max": 68000,
      "suspicion_score": 0,
      "keywords": [
        "political activist"
      ],
      "is_monitoring_entry": false
    },
    {
      "type": "job_posting",
      "source": "adzuna",
      "title": "Post-Doctoral Associate",
      "company": "Rutgers University",
      "city": "US",
      "state": "",
      "url": "https://www.adzuna.com/land/ad/5656508685?se=8GuhcUJb8RGrcsb7COxaHg&utm_medium=api&utm_source=a70fa881&v=16B23003DAC87B1AC6315B9C3F5B78606326244F",
      "date": "2026-05-29T09:40:36.081120Z",
      "salary_min": 52303.5,
      "salary_max": 52303.5,
      "suspicion_score": 0,
      "keywords": [
        "political activist"
      ],
      "is_monitoring_entry": false
    },
    {
      "type": "job_posting",
      "source": "adzuna",
      "title": "AI Field, Growth & Campaign Senior Marketing Manager",
      "company": "Cognizant",
      "city": "US",
      "state": "",
      "url": "https://www.adzuna.com/land/ad/5710050594?se=-gfscUJb8RGrcsb7COxaHg&utm_medium=api&utm_source=a70fa881&v=147D433F05E42C03843EA3A3D0729E8589EF6AC9",
      "date": "2026-05-29T09:40:36.615936Z",
      "salary_min": 138704.39,
      "salary_max": 138704.39,
      "suspicion_score": 0,
      "keywords": [
        "campaign field"
      ],
      "is_monitoring_entry": false
    },
    {
      "type": "job_posting",
      "source": "adzuna",
      "title": "Oceanographic Lidar Remote Sensing and Field Campaign Internship",
      "company": "Analytical Mechanics Associates",
      "city": "US",
      "state": "",
      "url": "https://www.adzuna.com/details/5715578960?utm_medium=api&utm_source=a70fa881",
      "date": "2026-05-29T09:40:36.615974Z",
      "salary_min": 115275.35,
      "salary_max": 115275.35,
      "suspicion_score": 0,
      "keywords": [
        "campaign field"
      ],
      "is_monitoring_entry": false
    },
    {
      "type": "job_posting",
      "source": "adzuna",
      "title": "SEM Strategist (North America)",
      "company": "Palo Alto Networks",
      "city": "US",
      "state": "",
      "url": "https://www.adzuna.com/land/ad/5665795527?se=-gfscUJb8RGrcsb7COxaHg&utm_medium=api&utm_source=a70fa881&v=D6B87818C6F548A942B213C133D0C8534CD84ECF",
      "date": "2026-05-29T09:40:36.616010Z",
      "salary_min": 170542.45,
      "salary_max": 170542.45,
      "suspicion_score": 0,
      "keywords": [
        "campaign field"
      ],
      "is_monitoring_entry": false
    },
    {
      "type": "job_posting",
      "source": "adzuna",
      "title": "Senior Alliance Manager, AWS",
      "company": "Palo Alto Networks",
      "city": "US",
      "state": "",
      "url": "https://www.adzuna.com/land/ad/5744002320?se=-gfscUJb8RGrcsb7COxaHg&utm_medium=api&utm_source=a70fa881&v=77B95365C76B9F531F8F752D301143181D13DA64",
      "date": "2026-05-29T09:40:36.616045Z",
      "salary_min": 232192.9,
      "salary_max": 232192.9,
      "suspicion_score": 0,
      "keywords": [
        "campaign field"
      ],
      "is_monitoring_entry": false
    },
    {
      "type": "job_posting",
      "source": "adzuna",
      "title": "Sr Field Marketing Manager, Amazon Business",
      "company": "Amazon",
      "city": "US",
      "state": "",
      "url": "https://www.adzuna.com/land/ad/5710742715?se=-gfscUJb8RGrcsb7COxaHg&utm_medium=api&utm_source=a70fa881&v=6AC49758986D3841A3D8EC700603D3810741110D",
      "date": "2026-05-29T09:40:36.616102Z",
      "salary_min": 273466.97,
      "salary_max": 273466.97,
      "suspicion_score": 0,
      "keywords": [
        "campaign field"
      ],
      "is_monitoring_entry": false
    },
    {
      "type": "job_posting",
      "source": "adzuna",
      "title": "Security Manager",
      "company": "Graham-Windham Inc.",
      "city": "US",
      "state": "",
      "url": "https://www.adzuna.com/details/5391630274?utm_medium=api&utm_source=a70fa881",
      "date": "2026-05-29T09:40:37.186512Z",
      "salary_min": 68501.32,
      "salary_max": 68501.32,
      "suspicion_score": 0,
      "keywords": [
        "community organizer political"
      ],
      "is_monitoring_entry": false
    },
    {
      "type": "job_posting",
      "source": "adzuna",
      "title": "JTF-Gold Mobility Coordinator",
      "company": "Na Oiwi Kane",
      "city": "US",
      "state": "",
      "url": "https://www.adzuna.com/land/ad/5734643078?se=hJuRckJb8RGLhOKqikEyOg&utm_medium=api&utm_source=a70fa881&v=162559ECC37925BEDC00EA3E69EF7E49CEA0148A",
      "date": "2026-05-29T09:40:37.605264Z",
      "salary_min": 59802.24,
      "salary_max": 59802.24,
      "suspicion_score": 0,
      "keywords": [
        "mobilization coordinator"
      ],
      "is_monitoring_entry": false
    },
    {
      "type": "job_posting",
      "source": "adzuna",
      "title": "JTF-Gold Mobility Coordinator with Security Clearance",
      "company": "Honu Services",
      "city": "US",
      "state": "",
      "url": "https://www.adzuna.com/land/ad/5740541927?se=hJuRckJb8RGLhOKqikEyOg&utm_medium=api&utm_source=a70fa881&v=F3CAE7C993DB58913F5038E1DA5DFBD398417001",
      "date": "2026-05-29T09:40:37.605318Z",
      "salary_min": 97339.67,
      "salary_max": 97339.67,
      "suspicion_score": 0,
      "keywords": [
        "mobilization coordinator"
      ],
      "is_monitoring_entry": false
    },
    {
      "type": "job_posting",
      "source": "adzuna",
      "title": "Mobility Management Coordinator",
      "company": "Schaeffler",
      "city": "US",
      "state": "",
      "url": "https://www.adzuna.com/land/ad/5731959034?se=hJuRckJb8RGLhOKqikEyOg&utm_medium=api&utm_source=a70fa881&v=91754F9E7AB589F9A42E995A2D2EA2F616DAE520",
      "date": "2026-05-29T09:40:37.605334Z",
      "salary_min": 89360.29,
      "salary_max": 89360.29,
      "suspicion_score": 0,
      "keywords": [
        "mobilization coordinator"
      ],
      "is_monitoring_entry": false
    },
    {
      "type": "job_posting",
      "source": "adzuna",
      "title": "Mobility Program Coordinator",
      "company": "System One",
      "city": "US",
      "state": "",
      "url": "https://www.adzuna.com/land/ad/5742865605?se=hJuRckJb8RGLhOKqikEyOg&utm_medium=api&utm_source=a70fa881&v=ADBD75C3CBF2B4A1C74E386DD4D6DCCDF0A40272",
      "date": "2026-05-29T09:40:37.605352Z",
      "salary_min": 81649.75,
      "salary_max": 81649.75,
      "suspicion_score": 0,
      "keywords": [
        "mobilization coordinator"
      ],
      "is_monitoring_entry": false
    },
    {
      "type": "job_posting",
      "source": "adzuna",
      "title": "Mobile Service Coordinator",
      "company": "Coast Counties Truck & Equipment Compan",
      "city": "US",
      "state": "",
      "url": "https://www.adzuna.com/land/ad/5744289518?se=hJuRckJb8RGLhOKqikEyOg&utm_medium=api&utm_source=a70fa881&v=BE959B7A0EF0E232FADCA21A643FF9D85839EF2B",
      "date": "2026-05-29T09:40:37.605369Z",
      "salary_min": 54159.19,
      "salary_max": 54159.19,
      "suspicion_score": 0,
      "keywords": [
        "mobilization coordinator"
      ],
      "is_monitoring_entry": false
    },
    {
      "type": "job_posting",
      "source": "adzuna",
      "title": "Mobility Coordinator",
      "company": "Lutheran Social Services of Wisconsin and Upper Michigan",
      "city": "US",
      "state": "",
      "url": "https://www.adzuna.com/details/5732142345?utm_medium=api&utm_source=a70fa881",
      "date": "2026-05-29T09:40:37.605402Z",
      "salary_min": 72823.3,
      "salary_max": 72823.3,
      "suspicion_score": 0,
      "keywords": [
        "mobilization coordinator"
      ],
      "is_monitoring_entry": false
    }
  ],
  "jobPostingPatterns": {
    "totalJobs": 50
  },
  "flaggedOrganizations": [
    {
      "type": "independent_expenditure",
      "source": "fec",
      "committee_id": "C00931774",
      "committee_name": "ARTICLE ONE PAC",
      "amount": 44000.0,
      "date": "2026-05-26",
      "state": "NJ"
    },
    {
      "type": "independent_expenditure",
      "source": "fec",
      "committee_id": "C00892653",
      "committee_name": "WORKING CLASS HEROES FUND",
      "amount": 18689.58,
      "date": "2026-05-26",
      "state": "CA"
    },
    {
      "type": "independent_expenditure",
      "source": "fec",
      "committee_id": "C00892653",
      "committee_name": "WORKING CLASS HEROES FUND",
      "amount": 37945.51,
      "date": "2026-05-26",
      "state": "CA"
    },
    {
      "type": "independent_expenditure",
      "source": "fec",
      "committee_id": "C00772244",
      "committee_name": "UPSET THE SETUP",
      "amount": 28671.34,
      "date": "2026-05-26",
      "state": "CA"
    },
    {
      "type": "independent_expenditure",
      "source": "fec",
      "committee_id": "C00901223",
      "committee_name": "LONE STAR LIBERTY PAC",
      "amount": 73054.0,
      "date": "2026-05-26",
      "state": "TX"
    },
    {
      "type": "independent_expenditure",
      "source": "fec",
      "committee_id": "C00525824",
      "committee_name": "PEACE THROUGH STRENGTH PAC",
      "amount": 1000.0,
      "date": "2026-05-26",
      "state": "CA"
    },
    {
      "type": "independent_expenditure",
      "source": "fec",
      "committee_id": "C00630665",
      "committee_name": "JUSTICE DEMOCRATS PAC",
      "amount": 11000.0,
      "date": "2026-05-26",
      "state": "NY"
    },
    {
      "type": "independent_expenditure",
      "source": "fec",
      "committee_id": "C00897926",
      "committee_name": "PROGRESSIVE PROMISE",
      "amount": 175000.0,
      "date": "2026-05-26",
      "state": "CA"
    },
    {
      "type": "independent_expenditure",
      "source": "fec",
      "committee_id": "C00630665",
      "committee_name": "JUSTICE DEMOCRATS PAC",
      "amount": 5000.0,
      "date": "2026-05-26",
      "state": "NY"
    },
    {
      "type": "independent_expenditure",
      "source": "fec",
      "committee_id": "C00630665",
      "committee_name": "JUSTICE DEMOCRATS PAC",
      "amount": 5000.0,
      "date": "2026-05-26",
      "state": "NY"
    },
    {
      "type": "independent_expenditure",
      "source": "fec",
      "committee_id": "C00630665",
      "committee_name": "JUSTICE DEMOCRATS PAC",
      "amount": 125000.0,
      "date": "2026-05-26",
      "state": "NY"
    },
    {
      "type": "independent_expenditure",
      "source": "fec",
      "committee_id": "C00630665",
      "committee_name": "JUSTICE DEMOCRATS PAC",
      "amount": 125000.0,
      "date": "2026-05-26",
      "state": "NY"
    },
    {
      "type": "independent_expenditure",
      "source": "fec",
      "committee_id": "C00751503",
      "committee_name": "NEW LEADERSHIP PAC",
      "amount": 10000.0,
      "date": "2026-05-26",
      "state": "TX"
    },
    {
      "type": "independent_expenditure",
      "source": "fec",
      "committee_id": "C00938506",
      "committee_name": "THE AFFORDABILITY INITIATIVE",
      "amount": 20000.0,
      "date": "2026-05-26",
      "state": "NJ"
    },
    {
      "type": "independent_expenditure",
      "source": "fec",
      "committee_id": "C00947275",
      "committee_name": "CALIFORNIA CONSERVATIVES PAC",
      "amount": 20272.94,
      "date": "2026-05-26",
      "state": "CA"
    },
    {
      "type": "independent_expenditure",
      "source": "fec",
      "committee_id": "C00947275",
      "committee_name": "CALIFORNIA CONSERVATIVES PAC",
      "amount": 45000.0,
      "date": "2026-05-26",
      "state": "CA"
    },
    {
      "type": "independent_expenditure",
      "source": "fec",
      "committee_id": "C00004036",
      "committee_name": "SEIU COPE (SERVICE EMPLOYEES INTERNATIONAL UNION COMMITTEE ON POLITICAL EDUCATION)",
      "amount": 48832.62,
      "date": "2026-05-26",
      "state": "CA"
    },
    {
      "type": "independent_expenditure",
      "source": "fec",
      "committee_id": "C00004036",
      "committee_name": "SEIU COPE (SERVICE EMPLOYEES INTERNATIONAL UNION COMMITTEE ON POLITICAL EDUCATION)",
      "amount": 48832.62,
      "date": "2026-05-26",
      "state": "CA"
    },
    {
      "type": "independent_expenditure",
      "source": "fec",
      "committee_id": "C00004036",
      "committee_name": "SEIU COPE (SERVICE EMPLOYEES INTERNATIONAL UNION COMMITTEE ON POLITICAL EDUCATION)",
      "amount": 48832.62,
      "date": "2026-05-26",
      "state": "CA"
    },
    {
      "type": "independent_expenditure",
      "source": "fec",
      "committee_id": "C00633248",
      "committee_name": "314 ACTION FUND",
      "amount": 54667.37,
      "date": "2026-05-26",
      "state": "CA"
    },
    {
      "type": "independent_expenditure",
      "source": "fec",
      "committee_id": "C00698936",
      "committee_name": "WFW ACTION FUND INC",
      "amount": 3298.32,
      "date": "2026-05-26",
      "state": "TX"
    },
    {
      "type": "independent_expenditure",
      "source": "fec",
      "committee_id": "C00513176",
      "committee_name": "CONGRESSIONAL PROGRESSIVE CAUCUS PAC",
      "amount": 6250.0,
      "date": "2026-05-26",
      "state": "CA"
    },
    {
      "type": "independent_expenditure",
      "source": "fec",
      "committee_id": "C00542217",
      "committee_name": "TEXANS FOR A CONSERVATIVE MAJORITY",
      "amount": 27935.08,
      "date": "2026-05-26",
      "state": "TX"
    },
    {
      "type": "independent_expenditure",
      "source": "fec",
      "committee_id": "C00375279",
      "committee_name": "ALAMEDA COUNTY DEMOCRATIC CENTRAL COMMITTEE",
      "amount": 125.0,
      "date": "2026-05-26",
      "state": "CA"
    },
    {
      "type": "independent_expenditure",
      "source": "fec",
      "committee_id": "C00375279",
      "committee_name": "ALAMEDA COUNTY DEMOCRATIC CENTRAL COMMITTEE",
      "amount": 1708.0,
      "date": "2026-05-26",
      "state": "CA"
    },
    {
      "type": "independent_expenditure",
      "source": "fec",
      "committee_id": "C00375279",
      "committee_name": "ALAMEDA COUNTY DEMOCRATIC CENTRAL COMMITTEE",
      "amount": 5485.32,
      "date": "2026-05-26",
      "state": "CA"
    },
    {
      "type": "new_committee",
      "source": "fec",
      "committee_id": "C00951806",
      "name": "MAKING CALIFORNIA FIRST",
      "committee_type": "O",
      "first_file_date": "2026-05-27",
      "state": "CA",
      "city": null
    },
    {
      "type": "new_committee",
      "source": "fec",
      "committee_id": "C00951863",
      "name": "FLORIDA CONSERVATIVES FUND",
      "committee_type": "O",
      "first_file_date": "2026-05-27",
      "state": "AL",
      "city": null
    },
    {
      "type": "new_committee",
      "source": "fec",
      "committee_id": "C00951756",
      "name": "LONG ISLAND FORWARD PAC INC",
      "committee_type": "O",
      "first_file_date": "2026-05-26",
      "state": "VA",
      "city": null
    },
    {
      "type": "new_committee",
      "source": "fec",
      "committee_id": "C00951749",
      "name": "HUDSON VALUES",
      "committee_type": "O",
      "first_file_date": "2026-05-26",
      "state": "VA",
      "city": null
    },
    {
      "type": "new_committee",
      "source": "fec",
      "committee_id": "C00951665",
      "name": "WESTERN BLUE PAC",
      "committee_type": "O",
      "first_file_date": "2026-05-26",
      "state": "CA",
      "city": null
    },
    {
      "type": "new_committee",
      "source": "fec",
      "committee_id": "C00951723",
      "name": "THE EDGE ACTION FUND",
      "committee_type": "O",
      "first_file_date": "2026-05-26",
      "state": "DC",
      "city": null
    },
    {
      "type": "new_committee",
      "source": "fec",
      "committee_id": "C00951715",
      "name": "ACTION DEMOCRATS FOR ALL",
      "committee_type": "O",
      "first_file_date": "2026-05-26",
      "state": "DC",
      "city": null
    },
    {
      "type": "new_committee",
      "source": "fec",
      "committee_id": "C00951483",
      "name": "GEORGIA VALES",
      "committee_type": "O",
      "first_file_date": "2026-05-23",
      "state": "TX",
      "city": null
    },
    {
      "type": "new_committee",
      "source": "fec",
      "committee_id": "C00951426",
      "name": "MICHIGAN VALUES PAC",
      "committee_type": "O",
      "first_file_date": "2026-05-22",
      "state": "DC",
      "city": null
    },
    {
      "type": "new_committee",
      "source": "fec",
      "committee_id": "C00951418",
      "name": "SAFER KANSAS FUND",
      "committee_type": "O",
      "first_file_date": "2026-05-22",
      "state": "DC",
      "city": null
    },
    {
      "type": "new_committee",
      "source": "fec",
      "committee_id": "C00951442",
      "name": "ASIANS FOR TALARICO",
      "committee_type": "V",
      "first_file_date": "2026-05-22",
      "state": "TN",
      "city": null
    },
    {
      "type": "new_committee",
      "source": "fec",
      "committee_id": "C00951434",
      "name": "INDIGENOUS WOMEN LEAD PAC",
      "committee_type": "O",
      "first_file_date": "2026-05-22",
      "state": "DC",
      "city": null
    },
    {
      "type": "new_committee",
      "source": "fec",
      "committee_id": "C00951459",
      "name": "JUSTICE FOR DEMOCRACY COMMITTEE",
      "committee_type": "O",
      "first_file_date": "2026-05-22",
      "state": "DC",
      "city": null
    },
    {
      "type": "new_committee",
      "source": "fec",
      "committee_id": "C00951376",
      "name": "DEMOCRATS FIGHT BACK PAC",
      "committee_type": "O",
      "first_file_date": "2026-05-21",
      "state": "DC",
      "city": null
    }
  ]
}