{
  "lastScan": "2026-02-06T10:33:02.601370Z",
  "stats": {
    "events": 100,
    "alerts": 3,
    "orgs": 40,
    "newsArticles": 20
  },
  "systemConfidence": 60,
  "confidenceFactors": [
    {
      "factor": "News Coverage",
      "score": 80,
      "detail": "11 high-relevance articles"
    },
    {
      "factor": "Organization Risk",
      "score": 35,
      "detail": "0 high-risk orgs"
    },
    {
      "factor": "Job Postings",
      "score": 30,
      "detail": "0 suspicious postings"
    }
  ],
  "agentNotes": [
    {
      "summary": "Monitoring 15 news, 14 orgs, 58 jobs. 3 alerts.",
      "timestamp": "2026-02-06T10:33:02.600706Z"
    },
    {
      "summary": "Monitoring 15 news, 14 orgs, 58 jobs. 3 alerts.",
      "timestamp": "2026-02-06T09:36:05.690850Z"
    },
    {
      "summary": "Monitoring 15 news, 14 orgs, 58 jobs. 3 alerts.",
      "timestamp": "2026-02-06T08:33:56.620902Z"
    },
    {
      "summary": "Monitoring 15 news, 14 orgs, 58 jobs. 3 alerts.",
      "timestamp": "2026-02-06T07:41:55.109695Z"
    },
    {
      "summary": "Monitoring 15 news, 14 orgs, 58 jobs. 3 alerts.",
      "timestamp": "2026-02-06T06:44:23.696611Z"
    },
    {
      "summary": "Monitoring 15 news, 14 orgs, 58 jobs. 3 alerts.",
      "timestamp": "2026-02-06T05:48:09.606965Z"
    },
    {
      "summary": "Monitoring 15 news, 14 orgs, 57 jobs. 3 alerts.",
      "timestamp": "2026-02-06T04:08:53.131832Z"
    },
    {
      "summary": "Monitoring 15 news, 14 orgs, 58 jobs. 3 alerts.",
      "timestamp": "2026-02-06T01:23:37.231446Z"
    },
    {
      "summary": "Monitoring 15 news, 14 orgs, 58 jobs. 3 alerts.",
      "timestamp": "2026-02-05T23:18:11.464878Z"
    },
    {
      "summary": "Monitoring 15 news, 14 orgs, 57 jobs. 3 alerts.",
      "timestamp": "2026-02-05T22:20:26.959643Z"
    }
  ],
  "connections": [
    {
      "type": "Naming Pattern",
      "description": "15 orgs with generic patriotic names typical of astroturf.",
      "probability": 78,
      "evidence": [
        {
          "type": "Org",
          "detail": "Citizens For Sanity"
        },
        {
          "type": "Org",
          "detail": "Citizens For Education"
        },
        {
          "type": "Org",
          "detail": "Citizens For Peace"
        }
      ]
    },
    {
      "type": "Paid Protest News",
      "description": "5 articles specifically about paid protesters.",
      "probability": 72,
      "evidence": [
        {
          "type": "News",
          "detail": "Verify: Rep. Tim Burchett claims protesters in Minneapolis are 'paid'"
        },
        {
          "type": "News",
          "detail": "KFAN's Paul Allen quiet Sunday after suggesting protest marchers were paid"
        }
      ]
    }
  ],
  "timeline": [
    {
      "type": "news",
      "title": "Verify: Rep. Tim Burchett claims protesters in Minneapolis are 'paid'",
      "date": "2026-02-06T10:33:02.601370Z",
      "sourceUrl": "https://www.msn.com/en-us/news/us/verify-rep-tim-burchett-claims-protesters-in-minneapolis-are-paid/ar-AA1V4qBW"
    },
    {
      "type": "news",
      "title": "KFAN's Paul Allen quiet Sunday after suggesting protest marchers were paid",
      "date": "2026-02-06T10:33:02.601370Z",
      "sourceUrl": "https://www.twincities.com/2026/01/25/kfans-paul-allen-quiet-sunday-after-suggesting-protest-marchers-were-paid/"
    },
    {
      "type": "news",
      "title": "Right-wing media figures are claiming, once again, that anti-ICE protesters are paid agitators",
      "date": "2026-02-06T10:33:02.601370Z",
      "sourceUrl": "https://www.mediamatters.org/immigration/right-wing-media-figures-are-claiming-once-again-anti-ice-protesters-are-paid-agitators"
    },
    {
      "type": "news",
      "title": "Verify: Rep. Tim Burchett claims protesters in Minneapolis are 'paid'",
      "date": "2026-02-06T09:36:05.691816Z",
      "sourceUrl": "https://www.msn.com/en-us/news/us/verify-rep-tim-burchett-claims-protesters-in-minneapolis-are-paid/ar-AA1V4qBW"
    },
    {
      "type": "news",
      "title": "KFAN's Paul Allen quiet Sunday after suggesting protest marchers were paid",
      "date": "2026-02-06T09:36:05.691816Z",
      "sourceUrl": "https://www.twincities.com/2026/01/25/kfans-paul-allen-quiet-sunday-after-suggesting-protest-marchers-were-paid/"
    },
    {
      "type": "news",
      "title": "Right-wing media figures are claiming, once again, that anti-ICE protesters are paid agitators",
      "date": "2026-02-06T09:36:05.691816Z",
      "sourceUrl": "https://www.mediamatters.org/immigration/right-wing-media-figures-are-claiming-once-again-anti-ice-protesters-are-paid-agitators"
    },
    {
      "type": "news",
      "title": "Verify: Rep. Tim Burchett claims protesters in Minneapolis are 'paid'",
      "date": "2026-02-06T08:33:56.621881Z",
      "sourceUrl": "https://www.msn.com/en-us/news/us/verify-rep-tim-burchett-claims-protesters-in-minneapolis-are-paid/ar-AA1V4qBW"
    },
    {
      "type": "news",
      "title": "KFAN's Paul Allen quiet Sunday after suggesting protest marchers were paid",
      "date": "2026-02-06T08:33:56.621881Z",
      "sourceUrl": "https://www.twincities.com/2026/01/25/kfans-paul-allen-quiet-sunday-after-suggesting-protest-marchers-were-paid/"
    },
    {
      "type": "news",
      "title": "Right-wing media figures are claiming, once again, that anti-ICE protesters are paid agitators",
      "date": "2026-02-06T08:33:56.621881Z",
      "sourceUrl": "https://www.mediamatters.org/immigration/right-wing-media-figures-are-claiming-once-again-anti-ice-protesters-are-paid-agitators"
    },
    {
      "type": "news",
      "title": "Verify: Rep. Tim Burchett claims protesters in Minneapolis are 'paid'",
      "date": "2026-02-06T07:41:55.110713Z",
      "sourceUrl": "https://www.msn.com/en-us/news/us/verify-rep-tim-burchett-claims-protesters-in-minneapolis-are-paid/ar-AA1V4qBW"
    },
    {
      "type": "news",
      "title": "KFAN's Paul Allen quiet Sunday after suggesting protest marchers were paid",
      "date": "2026-02-06T07:41:55.110713Z",
      "sourceUrl": "https://www.twincities.com/2026/01/25/kfans-paul-allen-quiet-sunday-after-suggesting-protest-marchers-were-paid/"
    },
    {
      "type": "news",
      "title": "Right-wing media figures are claiming, once again, that anti-ICE protesters are paid agitators",
      "date": "2026-02-06T07:41:55.110713Z",
      "sourceUrl": "https://www.mediamatters.org/immigration/right-wing-media-figures-are-claiming-once-again-anti-ice-protesters-are-paid-agitators"
    },
    {
      "type": "news",
      "title": "Critics of Minnesota anti-ICE protests falsely call protesters paid",
      "date": "2026-02-06T06:44:23.697252Z",
      "sourceUrl": "https://www.politifact.com/factchecks/2026/jan/26/donald-trump/Trump-paid-protesters-ICE-Minnesota-Minneapolis/"
    },
    {
      "type": "news",
      "title": "Vikings announcer steps away from radio show after comments about 'paid protesters'",
      "date": "2026-02-06T06:44:23.697252Z",
      "sourceUrl": "https://www.msn.com/en-us/news/us/vikings-announcer-stexpediaeps-away-from-radio-show-after-comments-about-paid-protesters/ar-AA1V5YLs?ocid=BingNewsVerp"
    },
    {
      "type": "news",
      "title": "Jimmy Kimmel Tells Trump Admin to Prove Minneapolis Protesters Are Really Paid Agitators | Video",
      "date": "2026-02-06T06:44:23.697252Z",
      "sourceUrl": "https://www.msn.com/en-us/tv/news/jimmy-kimmel-tells-trump-admin-to-prove-minneapolis-protesters-are-really-paid-agitators-video/ar-AA1Vb13J?ocid=BingNewsVerp"
    },
    {
      "type": "news",
      "title": "Verify: Rep. Tim Burchett claims protesters in Minneapolis are 'paid'",
      "date": "2026-02-06T05:48:09.607801Z",
      "sourceUrl": "https://www.msn.com/en-us/news/us/verify-rep-tim-burchett-claims-protesters-in-minneapolis-are-paid/ar-AA1V4qBW"
    },
    {
      "type": "news",
      "title": "KFAN's Paul Allen quiet Sunday after suggesting protest marchers were paid",
      "date": "2026-02-06T05:48:09.607801Z",
      "sourceUrl": "https://www.twincities.com/2026/01/25/kfans-paul-allen-quiet-sunday-after-suggesting-protest-marchers-were-paid/"
    },
    {
      "type": "news",
      "title": "Right-wing media figures are claiming, once again, that anti-ICE protesters are paid agitators",
      "date": "2026-02-06T05:48:09.607801Z",
      "sourceUrl": "https://www.mediamatters.org/immigration/right-wing-media-figures-are-claiming-once-again-anti-ice-protesters-are-paid-agitators"
    },
    {
      "type": "news",
      "title": "Critics of Minnesota anti-ICE protests falsely call protesters paid",
      "date": "2026-02-06T04:08:53.132664Z",
      "sourceUrl": "https://www.politifact.com/factchecks/2026/jan/26/donald-trump/Trump-paid-protesters-ICE-Minnesota-Minneapolis/"
    },
    {
      "type": "news",
      "title": "Jimmy Kimmel Throws Trump's 'Paid Agitators' Claim Right Back in His Face",
      "date": "2026-02-06T04:08:53.132664Z",
      "sourceUrl": "https://www.yahoo.com/entertainment/tv/articles/jimmy-kimmel-throws-trump-paid-113644842.html"
    },
    {
      "type": "news",
      "title": "KFAN airs 'paid protesters' apology from Paul Allen in middle of commercial break",
      "date": "2026-02-06T04:08:53.132664Z",
      "sourceUrl": "https://www.msn.com/en-us/entertainment/general/kfan-airs-paid-protesters-apology-from-paul-allen-in-middle-of-commercial-break/ar-AA1V1kry?ocid=BingNewsVerp"
    },
    {
      "type": "news",
      "title": "Byron Donalds blames ICE shootings on \u2018paid agitators,\u2019 echoing false claim by Trump",
      "date": "2026-02-06T01:23:37.232187Z",
      "sourceUrl": "https://thegrio.com/2026/01/27/byron-donalds-ice-paid-agitators-echoing-false-claim-by-trump/"
    },
    {
      "type": "news",
      "title": "Vikings announcer steps away from radio show after comments about 'paid protesters'",
      "date": "2026-02-06T01:23:37.232187Z",
      "sourceUrl": "https://www.msn.com/en-us/sports/football/vikings-announcer-steps-away-from-radio-show-after-comments-about-paid-protesters/ar-AA1V5YLs?ocid=BingNewsVerp"
    },
    {
      "type": "news",
      "title": "Critics of Minnesota anti-ICE protests falsely call protesters paid",
      "date": "2026-02-06T01:23:37.232187Z",
      "sourceUrl": "https://www.politifact.com/factchecks/2026/jan/26/donald-trump/Trump-paid-protesters-ICE-Minnesota-Minneapolis/"
    },
    {
      "type": "news",
      "title": "Verify: Rep. Tim Burchett claims protesters in Minneapolis are 'paid'",
      "date": "2026-02-05T23:18:11.465413Z",
      "sourceUrl": "https://www.msn.com/en-us/news/us/verify-rep-tim-burchett-claims-protesters-in-minneapolis-are-paid/ar-AA1V4qBW"
    },
    {
      "type": "news",
      "title": "KFAN's Paul Allen quiet Sunday after suggesting protest marchers were paid",
      "date": "2026-02-05T23:18:11.465413Z",
      "sourceUrl": "https://www.twincities.com/2026/01/25/kfans-paul-allen-quiet-sunday-after-suggesting-protest-marchers-were-paid/"
    },
    {
      "type": "news",
      "title": "Right-wing media figures are claiming, once again, that anti-ICE protesters are paid agitators",
      "date": "2026-02-05T23:18:11.465413Z",
      "sourceUrl": "https://www.mediamatters.org/immigration/right-wing-media-figures-are-claiming-once-again-anti-ice-protesters-are-paid-agitators"
    },
    {
      "type": "news",
      "title": "Critics of Minnesota anti-ICE protests falsely call protesters paid",
      "date": "2026-02-05T22:20:26.960698Z",
      "sourceUrl": "https://www.politifact.com/factchecks/2026/jan/26/donald-trump/Trump-paid-protesters-ICE-Minnesota-Minneapolis/"
    },
    {
      "type": "news",
      "title": "KFAN airs 'paid protesters' apology from Paul Allen in middle of commercial break",
      "date": "2026-02-05T22:20:26.960698Z",
      "sourceUrl": "https://www.msn.com/en-us/entertainment/general/kfan-airs-paid-protesters-apology-from-paul-allen-in-middle-of-commercial-break/ar-AA1V1kry?ocid=BingNewsVerp"
    },
    {
      "type": "news",
      "title": "Jimmy Kimmel Tells Trump Admin to Prove Minneapolis Protesters Are Really Paid Agitators | Video",
      "date": "2026-02-05T22:20:26.960698Z",
      "sourceUrl": "https://www.msn.com/en-us/tv/news/jimmy-kimmel-tells-trump-admin-to-prove-minneapolis-protesters-are-really-paid-agitators-video/ar-AA1Vb13J?ocid=BingNewsVerp"
    },
    {
      "type": "news",
      "title": "Critics of Minnesota anti-ICE protests falsely call protesters paid",
      "date": "2026-02-05T21:21:47.776915Z",
      "sourceUrl": "https://www.politifact.com/factchecks/2026/jan/26/donald-trump/Trump-paid-protesters-ICE-Minnesota-Minneapolis/"
    },
    {
      "type": "news",
      "title": "Byron Donalds blames ICE shootings on \u2018paid agitators,\u2019 echoing false claim by Trump",
      "date": "2026-02-05T21:21:47.776915Z",
      "sourceUrl": "https://thegrio.com/2026/01/27/byron-donalds-ice-paid-agitators-echoing-false-claim-by-trump/"
    },
    {
      "type": "news",
      "title": "Vikings announcer steps away from radio show after comments about 'paid protesters'",
      "date": "2026-02-05T21:21:47.776915Z",
      "sourceUrl": "https://www.msn.com/en-us/sports/football/vikings-announcer-steps-away-from-radio-show-after-comments-about-paid-protesters/ar-AA1V5YLs?ocid=BingNewsVerp"
    },
    {
      "type": "news",
      "title": "Critics of Minnesota anti-ICE protests falsely call protesters paid",
      "date": "2026-02-05T20:26:06.470086Z",
      "sourceUrl": "https://www.politifact.com/factchecks/2026/jan/26/donald-trump/Trump-paid-protesters-ICE-Minnesota-Minneapolis/"
    },
    {
      "type": "news",
      "title": "Byron Donalds blames ICE shootings on \u2018paid agitators,\u2019 echoing false claim by Trump",
      "date": "2026-02-05T20:26:06.470086Z",
      "sourceUrl": "https://thegrio.com/2026/01/27/byron-donalds-ice-paid-agitators-echoing-false-claim-by-trump/"
    },
    {
      "type": "news",
      "title": "KFAN airs 'paid protesters' apology from Paul Allen in middle of commercial break",
      "date": "2026-02-05T20:26:06.470086Z",
      "sourceUrl": "https://www.msn.com/en-us/entertainment/general/kfan-airs-paid-protesters-apology-from-paul-allen-in-middle-of-commercial-break/ar-AA1V1kry?ocid=BingNewsVerp"
    },
    {
      "type": "news",
      "title": "Verify: Rep. Tim Burchett claims protesters in Minneapolis are 'paid'",
      "date": "2026-02-05T19:33:39.391290Z",
      "sourceUrl": "https://www.msn.com/en-us/news/us/verify-rep-tim-burchett-claims-protesters-in-minneapolis-are-paid/ar-AA1V4qBW"
    },
    {
      "type": "news",
      "title": "KFAN's Paul Allen quiet Sunday after suggesting protest marchers were paid",
      "date": "2026-02-05T19:33:39.391290Z",
      "sourceUrl": "https://www.twincities.com/2026/01/25/kfans-paul-allen-quiet-sunday-after-suggesting-protest-marchers-were-paid/"
    },
    {
      "type": "news",
      "title": "Right-wing media figures are claiming, once again, that anti-ICE protesters are paid agitators",
      "date": "2026-02-05T19:33:39.391290Z",
      "sourceUrl": "https://www.mediamatters.org/immigration/right-wing-media-figures-are-claiming-once-again-anti-ice-protesters-are-paid-agitators"
    },
    {
      "type": "news",
      "title": "Critics of Minnesota anti-ICE protests falsely call protesters paid",
      "date": "2026-02-05T18:39:44.260561Z",
      "sourceUrl": "https://www.politifact.com/factchecks/2026/jan/26/donald-trump/Trump-paid-protesters-ICE-Minnesota-Minneapolis/"
    },
    {
      "type": "news",
      "title": "KFAN airs 'paid protesters' apology from Paul Allen in middle of commercial break",
      "date": "2026-02-05T18:39:44.260561Z",
      "sourceUrl": "https://www.msn.com/en-us/entertainment/general/kfan-airs-paid-protesters-apology-from-paul-allen-in-middle-of-commercial-break/ar-AA1V1kry?ocid=BingNewsVerp"
    },
    {
      "type": "news",
      "title": "Jimmy Kimmel Tells Trump Admin to Prove Minneapolis Protesters Are Really Paid Agitators | Video",
      "date": "2026-02-05T18:39:44.260561Z",
      "sourceUrl": "https://www.msn.com/en-us/tv/news/jimmy-kimmel-tells-trump-admin-to-prove-minneapolis-protesters-are-really-paid-agitators-video/ar-AA1Vb13J?ocid=BingNewsVerp"
    },
    {
      "type": "news",
      "title": "Critics of Minnesota anti-ICE protests falsely call protesters paid",
      "date": "2026-02-05T17:42:33.240058Z",
      "sourceUrl": "https://www.politifact.com/factchecks/2026/jan/26/donald-trump/Trump-paid-protesters-ICE-Minnesota-Minneapolis/"
    },
    {
      "type": "news",
      "title": "Byron Donalds blames ICE shootings on \u2018paid agitators,\u2019 echoing false claim by Trump",
      "date": "2026-02-05T17:42:33.240058Z",
      "sourceUrl": "https://thegrio.com/2026/01/27/byron-donalds-ice-paid-agitators-echoing-false-claim-by-trump/"
    },
    {
      "type": "news",
      "title": "Vikings announcer steps away from radio show after comments about 'paid protesters'",
      "date": "2026-02-05T17:42:33.240058Z",
      "sourceUrl": "https://www.msn.com/en-us/sports/football/vikings-announcer-steps-away-from-radio-show-after-comments-about-paid-protesters/ar-AA1V5YLs?ocid=BingNewsVerp"
    },
    {
      "type": "news",
      "title": "Verify: Rep. Tim Burchett claims protesters in Minneapolis are 'paid'",
      "date": "2026-02-05T16:39:20.490235Z",
      "sourceUrl": "https://www.msn.com/en-us/news/us/verify-rep-tim-burchett-claims-protesters-in-minneapolis-are-paid/ar-AA1V4qBW"
    },
    {
      "type": "news",
      "title": "KFAN's Paul Allen quiet Sunday after suggesting protest marchers were paid",
      "date": "2026-02-05T16:39:20.490235Z",
      "sourceUrl": "https://www.twincities.com/2026/01/25/kfans-paul-allen-quiet-sunday-after-suggesting-protest-marchers-were-paid/"
    },
    {
      "type": "news",
      "title": "Right-wing media figures are claiming, once again, that anti-ICE protesters are paid agitators",
      "date": "2026-02-05T16:39:20.490235Z",
      "sourceUrl": "https://www.mediamatters.org/immigration/right-wing-media-figures-are-claiming-once-again-anti-ice-protesters-are-paid-agitators"
    },
    {
      "type": "news",
      "title": "Verify: Rep. Tim Burchett claims protesters in Minneapolis are 'paid'",
      "date": "2026-02-05T15:35:50.831354Z",
      "sourceUrl": "https://www.msn.com/en-us/news/us/verify-rep-tim-burchett-claims-protesters-in-minneapolis-are-paid/ar-AA1V4qBW"
    },
    {
      "type": "news",
      "title": "KFAN's Paul Allen quiet Sunday after suggesting protest marchers were paid",
      "date": "2026-02-05T15:35:50.831354Z",
      "sourceUrl": "https://www.twincities.com/2026/01/25/kfans-paul-allen-quiet-sunday-after-suggesting-protest-marchers-were-paid/"
    },
    {
      "type": "news",
      "title": "Right-wing media figures are claiming, once again, that anti-ICE protesters are paid agitators",
      "date": "2026-02-05T15:35:50.831354Z",
      "sourceUrl": "https://www.mediamatters.org/immigration/right-wing-media-figures-are-claiming-once-again-anti-ice-protesters-are-paid-agitators"
    },
    {
      "type": "news",
      "title": "Minnesota Vikings announcer apologizes for on-air comments about \u2018paid protesters\u2019 \u2014 reveals he\u2019ll be stepping away for \u2018a few days\u2019",
      "date": "2026-02-05T14:01:31.091448Z",
      "sourceUrl": "https://www.msn.com/en-us/news/us/minnesota-vikings-announcer-apologizes-for-on-air-comments-about-paid-protesters-reveals-he-ll-be-stepping-away-for-a-few-days/ar-AA1V1cng?ocid=BingNewsVerp"
    },
    {
      "type": "news",
      "title": "Critics of Minnesota anti-ICE protests falsely call protesters paid",
      "date": "2026-02-05T14:01:31.091448Z",
      "sourceUrl": "https://www.politifact.com/factchecks/2026/jan/26/donald-trump/Trump-paid-protesters-ICE-Minnesota-Minneapolis/"
    },
    {
      "type": "news",
      "title": "Byron Donalds blames ICE shootings on \u2018paid agitators,\u2019 echoing false claim by Trump",
      "date": "2026-02-05T14:01:31.091448Z",
      "sourceUrl": "https://thegrio.com/2026/01/27/byron-donalds-ice-paid-agitators-echoing-false-claim-by-trump/"
    },
    {
      "type": "news",
      "title": "Critics of Minnesota anti-ICE protests falsely call protesters paid",
      "date": "2026-02-05T12:44:07.233933Z",
      "sourceUrl": "https://www.politifact.com/factchecks/2026/jan/26/donald-trump/Trump-paid-protesters-ICE-Minnesota-Minneapolis/"
    },
    {
      "type": "news",
      "title": "KFAN airs 'paid protesters' apology from Paul Allen in middle of commercial break",
      "date": "2026-02-05T12:44:07.233933Z",
      "sourceUrl": "https://www.msn.com/en-us/entertainment/general/kfan-airs-paid-protesters-apology-from-paul-allen-in-middle-of-commercial-break/ar-AA1V1kry?ocid=BingNewsVerp"
    },
    {
      "type": "news",
      "title": "Nevada Gov. Joe Lombardo says anti-Trump protesters were paid, don't want to work",
      "date": "2026-02-05T12:44:07.233933Z",
      "sourceUrl": "https://www.msn.com/en-us/news/other/nevada-gov-joe-lombardo-says-anti-trump-protesters-were-paid-don-t-want-to-work/ar-AA1CHlgC?ocid=BingNewsVerp"
    },
    {
      "type": "news",
      "title": "Verify: Rep. Tim Burchett claims protesters in Minneapolis are 'paid'",
      "date": "2026-02-05T11:30:43.996495Z",
      "sourceUrl": "https://www.msn.com/en-us/news/us/verify-rep-tim-burchett-claims-protesters-in-minneapolis-are-paid/ar-AA1V4qBW"
    },
    {
      "type": "news",
      "title": "KFAN's Paul Allen quiet Sunday after suggesting protest marchers were paid",
      "date": "2026-02-05T11:30:43.996495Z",
      "sourceUrl": "https://www.twincities.com/2026/01/25/kfans-paul-allen-quiet-sunday-after-suggesting-protest-marchers-were-paid/"
    },
    {
      "type": "news",
      "title": "Right-wing media figures are claiming, once again, that anti-ICE protesters are paid agitators",
      "date": "2026-02-05T11:30:43.996495Z",
      "sourceUrl": "https://www.mediamatters.org/immigration/right-wing-media-figures-are-claiming-once-again-anti-ice-protesters-are-paid-agitators"
    },
    {
      "type": "news",
      "title": "Critics of Minnesota anti-ICE protests falsely call protesters paid",
      "date": "2026-02-05T10:34:34.087318Z",
      "sourceUrl": "https://www.politifact.com/factchecks/2026/jan/26/donald-trump/Trump-paid-protesters-ICE-Minnesota-Minneapolis/"
    },
    {
      "type": "news",
      "title": "Verify: Rep. Tim Burchett claims protesters in Minneapolis are 'paid'",
      "date": "2026-02-05T10:34:34.087318Z",
      "sourceUrl": "https://www.msn.com/en-us/news/us/verify-rep-tim-burchett-claims-protesters-in-minneapolis-are-paid/ar-AA1V4qBW"
    },
    {
      "type": "news",
      "title": "KFAN's Paul Allen quiet Sunday after suggesting protest marchers were paid",
      "date": "2026-02-05T10:34:34.087318Z",
      "sourceUrl": "https://www.twincities.com/2026/01/25/kfans-paul-allen-quiet-sunday-after-suggesting-protest-marchers-were-paid/"
    },
    {
      "type": "news",
      "title": "Verify: Rep. Tim Burchett claims protesters in Minneapolis are 'paid'",
      "date": "2026-02-05T09:37:19.760976Z",
      "sourceUrl": "https://www.msn.com/en-us/news/us/verify-rep-tim-burchett-claims-protesters-in-minneapolis-are-paid/ar-AA1V4qBW"
    },
    {
      "type": "news",
      "title": "KFAN's Paul Allen quiet Sunday after suggesting protest marchers were paid",
      "date": "2026-02-05T09:37:19.760976Z",
      "sourceUrl": "https://www.twincities.com/2026/01/25/kfans-paul-allen-quiet-sunday-after-suggesting-protest-marchers-were-paid/"
    },
    {
      "type": "news",
      "title": "Right-wing media figures are claiming, once again, that anti-ICE protesters are paid agitators",
      "date": "2026-02-05T09:37:19.760976Z",
      "sourceUrl": "https://www.mediamatters.org/immigration/right-wing-media-figures-are-claiming-once-again-anti-ice-protesters-are-paid-agitators"
    },
    {
      "type": "news",
      "title": "Critics of Minnesota anti-ICE protests falsely call protesters paid",
      "date": "2026-02-05T08:35:24.179633Z",
      "sourceUrl": "https://www.politifact.com/factchecks/2026/jan/26/donald-trump/Trump-paid-protesters-ICE-Minnesota-Minneapolis/"
    },
    {
      "type": "news",
      "title": "Byron Donalds blames ICE shootings on 'paid agitators,' echoing false claim by Trump",
      "date": "2026-02-05T08:35:24.179633Z",
      "sourceUrl": "https://thegrio.com/2026/01/27/byron-donalds-ice-paid-agitators-echoing-false-claim-by-trump/"
    },
    {
      "type": "news",
      "title": "Jimmy Kimmel Throws Trump's 'Paid Agitators' Claim Right Back in His Face",
      "date": "2026-02-05T08:35:24.179633Z",
      "sourceUrl": "https://www.yahoo.com/entertainment/tv/articles/jimmy-kimmel-throws-trump-paid-113644842.html"
    },
    {
      "type": "news",
      "title": "Verify: Rep. Tim Burchett claims protesters in Minneapolis are 'paid'",
      "date": "2026-02-05T07:45:19.056734Z",
      "sourceUrl": "https://www.msn.com/en-us/news/us/verify-rep-tim-burchett-claims-protesters-in-minneapolis-are-paid/ar-AA1V4qBW"
    },
    {
      "type": "news",
      "title": "KFAN's Paul Allen quiet Sunday after suggesting protest marchers were paid",
      "date": "2026-02-05T07:45:19.056734Z",
      "sourceUrl": "https://www.twincities.com/2026/01/25/kfans-paul-allen-quiet-sunday-after-suggesting-protest-marchers-were-paid/"
    },
    {
      "type": "news",
      "title": "Right-wing media figures are claiming, once again, that anti-ICE protesters are paid agitators",
      "date": "2026-02-05T07:45:19.056734Z",
      "sourceUrl": "https://www.mediamatters.org/immigration/right-wing-media-figures-are-claiming-once-again-anti-ice-protesters-are-paid-agitators"
    },
    {
      "type": "news",
      "title": "Critics of Minnesota anti-ICE protests falsely call protesters paid",
      "date": "2026-02-05T06:50:28.338969Z",
      "sourceUrl": "https://www.politifact.com/factchecks/2026/jan/26/donald-trump/Trump-paid-protesters-ICE-Minnesota-Minneapolis/"
    },
    {
      "type": "news",
      "title": "Byron Donalds blames ICE shootings on 'paid agitators,' echoing false claim by Trump",
      "date": "2026-02-05T06:50:28.338969Z",
      "sourceUrl": "https://thegrio.com/2026/01/27/byron-donalds-ice-paid-agitators-echoing-false-claim-by-trump/"
    },
    {
      "type": "news",
      "title": "Verify: Rep. Tim Burchett claims protesters in Minneapolis are 'paid'",
      "date": "2026-02-05T06:50:28.338969Z",
      "sourceUrl": "https://www.msn.com/en-us/news/us/verify-rep-tim-burchett-claims-protesters-in-minneapolis-are-paid/ar-AA1V4qBW"
    },
    {
      "type": "news",
      "title": "Verify: Rep. Tim Burchett claims protesters in Minneapolis are 'paid'",
      "date": "2026-02-05T05:51:16.797118Z",
      "sourceUrl": "https://www.msn.com/en-us/news/us/verify-rep-tim-burchett-claims-protesters-in-minneapolis-are-paid/ar-AA1V4qBW"
    },
    {
      "type": "news",
      "title": "KFAN's Paul Allen quiet Sunday after suggesting protest marchers were paid",
      "date": "2026-02-05T05:51:16.797118Z",
      "sourceUrl": "https://www.twincities.com/2026/01/25/kfans-paul-allen-quiet-sunday-after-suggesting-protest-marchers-were-paid/"
    },
    {
      "type": "news",
      "title": "Right-wing media figures are claiming, once again, that anti-ICE protesters are paid agitators",
      "date": "2026-02-05T05:51:16.797118Z",
      "sourceUrl": "https://www.mediamatters.org/immigration/right-wing-media-figures-are-claiming-once-again-anti-ice-protesters-are-paid-agitators"
    },
    {
      "type": "news",
      "title": "Verify: Rep. Tim Burchett claims protesters in Minneapolis are 'paid'",
      "date": "2026-02-05T04:08:44.356713Z",
      "sourceUrl": "https://www.msn.com/en-us/news/us/verify-rep-tim-burchett-claims-protesters-in-minneapolis-are-paid/ar-AA1V4qBW"
    },
    {
      "type": "news",
      "title": "KFAN's Paul Allen quiet Sunday after suggesting protest marchers were paid",
      "date": "2026-02-05T04:08:44.356713Z",
      "sourceUrl": "https://www.twincities.com/2026/01/25/kfans-paul-allen-quiet-sunday-after-suggesting-protest-marchers-were-paid/"
    },
    {
      "type": "news",
      "title": "Right-wing media figures are claiming, once again, that anti-ICE protesters are paid agitators",
      "date": "2026-02-05T04:08:44.356713Z",
      "sourceUrl": "https://www.mediamatters.org/immigration/right-wing-media-figures-are-claiming-once-again-anti-ice-protesters-are-paid-agitators"
    },
    {
      "type": "news",
      "title": "Verify: Rep. Tim Burchett claims protesters in Minneapolis are 'paid'",
      "date": "2026-02-05T01:22:19.242313Z",
      "sourceUrl": "https://www.msn.com/en-us/news/us/verify-rep-tim-burchett-claims-protesters-in-minneapolis-are-paid/ar-AA1V4qBW"
    },
    {
      "type": "news",
      "title": "KFAN's Paul Allen quiet Sunday after suggesting protest marchers were paid",
      "date": "2026-02-05T01:22:19.242313Z",
      "sourceUrl": "https://www.twincities.com/2026/01/25/kfans-paul-allen-quiet-sunday-after-suggesting-protest-marchers-were-paid/"
    },
    {
      "type": "news",
      "title": "Right-wing media figures are claiming, once again, that anti-ICE protesters are paid agitators",
      "date": "2026-02-05T01:22:19.242313Z",
      "sourceUrl": "https://www.mediamatters.org/immigration/right-wing-media-figures-are-claiming-once-again-anti-ice-protesters-are-paid-agitators"
    },
    {
      "type": "news",
      "title": "Critics of Minnesota anti-ICE protests falsely call protesters paid",
      "date": "2026-02-04T23:20:39.489067Z",
      "sourceUrl": "https://www.politifact.com/factchecks/2026/jan/26/donald-trump/Trump-paid-protesters-ICE-Minnesota-Minneapolis/"
    },
    {
      "type": "news",
      "title": "KFAN airs 'paid protesters' apology from Paul Allen in middle of commercial break",
      "date": "2026-02-04T23:20:39.489067Z",
      "sourceUrl": "https://www.msn.com/en-us/entertainment/general/kfan-airs-paid-protesters-apology-from-paul-allen-in-middle-of-commercial-break/ar-AA1V1kry?ocid=BingNewsVerp"
    },
    {
      "type": "news",
      "title": "Jimmy Kimmel Tells Trump Admin to Prove Minneapolis Protesters Are Really Paid Agitators | Video",
      "date": "2026-02-04T23:20:39.489067Z",
      "sourceUrl": "https://www.msn.com/en-us/tv/news/jimmy-kimmel-tells-trump-admin-to-prove-minneapolis-protesters-are-really-paid-agitators-video/ar-AA1Vb13J?ocid=BingNewsVerp"
    },
    {
      "type": "news",
      "title": "Critics of Minnesota anti-ICE protests falsely call protesters paid",
      "date": "2026-02-04T22:19:52.512455Z",
      "sourceUrl": "https://www.politifact.com/factchecks/2026/jan/26/donald-trump/Trump-paid-protesters-ICE-Minnesota-Minneapolis/"
    },
    {
      "type": "news",
      "title": "Paul Allen \u2018taking a few days off\u2019 after \u2018paid protestors\u2019 claim",
      "date": "2026-02-04T22:19:52.512455Z",
      "sourceUrl": "https://nypost.com/2026/01/26/sports/kfans-paul-allen-taking-a-few-days-off-after-paid-protestors-claim/"
    },
    {
      "type": "news",
      "title": "Byron Donalds blames ICE shootings on \u2018paid agitators,\u2019 echoing false claim by Trump",
      "date": "2026-02-04T22:19:52.512455Z",
      "sourceUrl": "https://thegrio.com/2026/01/27/byron-donalds-ice-paid-agitators-echoing-false-claim-by-trump/"
    },
    {
      "type": "news",
      "title": "Verify: Rep. Tim Burchett claims protesters in Minneapolis are 'paid'",
      "date": "2026-02-04T21:27:05.538947Z",
      "sourceUrl": "https://www.msn.com/en-us/news/us/verify-rep-tim-burchett-claims-protesters-in-minneapolis-are-paid/ar-AA1V4qBW"
    },
    {
      "type": "news",
      "title": "KFAN's Paul Allen quiet Sunday after suggesting protest marchers were paid",
      "date": "2026-02-04T21:27:05.538947Z",
      "sourceUrl": "https://www.twincities.com/2026/01/25/kfans-paul-allen-quiet-sunday-after-suggesting-protest-marchers-were-paid/"
    },
    {
      "type": "news",
      "title": "Right-wing media figures are claiming, once again, that anti-ICE protesters are paid agitators",
      "date": "2026-02-04T21:27:05.538947Z",
      "sourceUrl": "https://www.mediamatters.org/immigration/right-wing-media-figures-are-claiming-once-again-anti-ice-protesters-are-paid-agitators"
    },
    {
      "type": "news",
      "title": "Critics of Minnesota anti-ICE protests falsely call protesters paid",
      "date": "2026-02-04T20:27:10.155593Z",
      "sourceUrl": "https://www.politifact.com/factchecks/2026/jan/26/donald-trump/Trump-paid-protesters-ICE-Minnesota-Minneapolis/"
    },
    {
      "type": "news",
      "title": "Paul Allen \u2018taking a few days off\u2019 after \u2018paid protestors\u2019 claim",
      "date": "2026-02-04T20:27:10.155593Z",
      "sourceUrl": "https://nypost.com/2026/01/26/sports/kfans-paul-allen-taking-a-few-days-off-after-paid-protestors-claim/"
    },
    {
      "type": "news",
      "title": "Vikings announcer steps away from radio show after comments about 'paid protesters'",
      "date": "2026-02-04T20:27:10.155593Z",
      "sourceUrl": "https://www.msn.com/en-us/sports/football/vikings-announcer-steps-away-from-radio-show-after-comments-about-paid-protesters/ar-AA1V5YLs?ocid=BingNewsVerp"
    },
    {
      "type": "news",
      "title": "Critics of Minnesota anti-ICE protests falsely call protesters paid",
      "date": "2026-02-04T19:34:53.737982Z",
      "sourceUrl": "https://www.politifact.com/factchecks/2026/jan/26/donald-trump/Trump-paid-protesters-ICE-Minnesota-Minneapolis/"
    },
    {
      "type": "news",
      "title": "Byron Donalds blames ICE shootings on \u2018paid agitators,\u2019 echoing false claim by Trump",
      "date": "2026-02-04T19:34:53.737982Z",
      "sourceUrl": "https://thegrio.com/2026/01/27/byron-donalds-ice-paid-agitators-echoing-false-claim-by-trump/"
    },
    {
      "type": "news",
      "title": "Paul Allen \u2018taking a few days off\u2019 after \u2018paid protestors\u2019 claim",
      "date": "2026-02-04T19:34:53.737982Z",
      "sourceUrl": "https://nypost.com/2026/01/26/sports/kfans-paul-allen-taking-a-few-days-off-after-paid-protestors-claim/"
    },
    {
      "type": "news",
      "title": "Critics of Minnesota anti-ICE protests falsely call protesters paid",
      "date": "2026-02-04T18:39:04.076555Z",
      "sourceUrl": "https://www.politifact.com/factchecks/2026/jan/26/donald-trump/Trump-paid-protesters-ICE-Minnesota-Minneapolis/"
    }
  ],
  "recentNews": [
    {
      "type": "news",
      "source": "google_news",
      "title": "Astroturfing: Understanding and Addressing the Influence of Fake Grassroots Movements Across Diverse Domains on Social Media Platforms - springerprofessional.de",
      "url": "https://news.google.com/rss/articles/CBMisgFBVV95cUxNUGtWSVFHXzN4RFhsRE5URk1OLUk0TEVONDhKUzhpdWNLZVpuRzZaOUF6d1EwQ0s3MWxwanY3Y2lVbm1fM3RtNVBrVURLczViVUdtQmVyMVk4U2RJWWJGR0l1VXpNRXR3SW1xcER6a2J6NTJKdnVIYmdqVHktal9KM0RZV1ZYZ1V5bFgxYTNtdlJtQXJPdHlLVFNSTG15T3AzYUM4WlhzTjdsbnlXNm15Yi1B?oc=5",
      "date": "2025-08-01T11:42:20Z",
      "publisher": "springerprofessional.de",
      "query": "fake grassroots",
      "relevance_score": 90,
      "location": ""
    },
    {
      "type": "news",
      "source": "google_news",
      "title": "What political ads are Australians seeing online? Astroturfing, fake grassroots groups, and outright falsehoods - The Conversation",
      "url": "https://news.google.com/rss/articles/CBMi2wFBVV95cUxPYmhmX1ZCSFFLYkxnbUljVWpsR0EtcVNfRVdjZ2NlN0FWdnQ3YmYwTUc1WXNSLXVCUDJRN3Z6anZXV0FfNlNTNktqZ3BvbkN2bWFNdk9KX3FFSWlCNS1HVlZsQXdKeUxhM2VEQTZSMzF3SWloV3Rubk1OR3loYk9WcFRpS2FmeFF5aDlGS2pzMDB4b3JpVF9QbzlFQ3ljVHVFMjFkMTJwbVhWNGdTNktsMTUzazNqbGZSTXpHdDlNeGdBOHlBSUFCOFE3MVZueEhDY08wTDZsWWdIRjg?oc=5",
      "date": "2025-04-27T07:00:00Z",
      "publisher": "The Conversation",
      "query": "fake grassroots",
      "relevance_score": 90,
      "location": ""
    },
    {
      "title": "Kenyan authorities paid trolls to threaten Gen Z protesters, Amnesty says",
      "url": "https://www.msn.com/en-us/news/world/kenyan-authorities-paid-trolls-to-threaten-gen-z-protesters-amnesty-says/ar-AA1QK7z1?ocid=BingNewsVerp",
      "snippet": "The Kenyan authorities paid a network of trolls to threaten and intimidate young protesters during recent anti-government demonstrations, Amnesty International has said. A new report by the human ...",
      "publisher": "MSN",
      "source": "duckduckgo",
      "query": "paid protesters",
      "date": "2025-11-19T00:00:00+00:00",
      "relevance_score": 90,
      "collected_at": "2026-01-10T01:21:18.722473Z"
    },
    {
      "title": "Masked agitator tells Laura Ingraham she's 'getting paid right now' at anti-ICE protest",
      "url": "https://www.msn.com/en-us/news/us/masked-agitator-tells-laura-ingraham-she-s-getting-paid-right-now-at-anti-ice-protest/ar-AA1TUzeF",
      "snippet": "Protester says she's 'getting paid right now' during exchange with Fox News host at Minneapolis anti-ICE demonstrations after a deadly shooting involving a federal agent.",
      "publisher": "Fox News",
      "source": "duckduckgo",
      "query": "paid protesters",
      "date": "2026-01-09T20:10:00+00:00",
      "relevance_score": 90,
      "collected_at": "2026-01-10T15:13:50.667635Z"
    },
    {
      "title": "Paid protest CEO urges Congress to pass law exposing who funds demonstrations",
      "url": "https://www.msn.com/en-us/politics/government/paid-protest-ceo-urges-congress-to-pass-law-exposing-who-funds-demonstrations/ar-AA1QhM7J",
      "snippet": "(NewsNation) \u2014 The CEO of a company that provides paid protesters for events is asking members of Congress to pass a \"Transparency in Political Demonstration Act\" that would expose the groups hiring demonstrators to attend events around the U.S. Adam ...",
      "publisher": "MSN",
      "source": "duckduckgo",
      "query": "paid protesters",
      "date": "2025-11-12T12:30:00+00:00",
      "relevance_score": 90,
      "collected_at": "2026-01-10T19:11:12.300746Z"
    },
    {
      "title": "Masked agitator tells Laura Ingraham she's 'getting paid right now' at anti-ICE protest",
      "url": "https://www.foxnews.com/media/masked-agitator-tells-laura-ingraham-shes-getting-paid-right-now-during-anti-ice-protest",
      "snippet": "Protester says she's 'getting paid right now' during exchange with Fox News host at Minneapolis anti-ICE demonstrations after a deadly shooting involving a federal agent.",
      "publisher": "Fox News",
      "source": "duckduckgo",
      "query": "paid protesters",
      "date": "2026-01-09T20:10:00+00:00",
      "relevance_score": 90,
      "collected_at": "2026-01-12T09:26:09.060233Z"
    },
    {
      "title": "Paid protest CEO urges Congress to pass law exposing who funds demonstrations",
      "url": "https://www.msn.com/en-us/politics/government/paid-protest-ceo-urges-congress-to-pass-law-exposing-who-funds-demonstrations/ar-AA1QhM7J?ocid=BingNewsVerp",
      "snippet": "(NewsNation) \u2014 The CEO of a company that provides paid protesters for events is asking members of Congress to pass a \u201cTransparency in Political Demonstration Act\u201d that would expose the groups hiring ...",
      "publisher": "MSN",
      "source": "duckduckgo",
      "query": "paid protesters",
      "date": "2025-11-12T00:00:00+00:00",
      "relevance_score": 90,
      "collected_at": "2026-01-13T08:22:00.645271Z"
    },
    {
      "title": "'They Use Serious Hammers': Trump Discredits Himself When He Tries To Prove The Existence Of 'Paid' Protesters In Oval Office Rant",
      "url": "https://www.msn.com/en-us/video/weather/they-use-serious-hammers-trump-discredits-himself-when-he-tries-to-prove-the-existence-of-paid-protesters-in-oval-office-rant/vi-AA1Rgx4R?ocid=BingNewsVerp",
      "snippet": "Donald Trump signed a memorandum to deploy troops in Memphis several weeks ago from the Oval Office. During Q&A with the press, Trump tried to prove that protesters in cities are paid and part of some ...",
      "publisher": "MSN",
      "source": "duckduckgo",
      "query": "paid protesters",
      "date": "2025-11-27T00:00:00+00:00",
      "relevance_score": 90,
      "collected_at": "2026-01-13T08:22:00.645281Z"
    },
    {
      "title": "New Milford residents angry official alleged \u2018No Kings' protesters were paid",
      "url": "https://www.msn.com/en-us/politics/government/new-milford-residents-angry-official-alleged-no-kings-protesters-were-paid/ar-AA1PyAdK?ocid=BingNewsVerp",
      "snippet": "NEW MILFORD \u2013 Area residents who participated in the recent \"No Kings\" protest recently voiced their disappointment at a Town Council member's comments that claimed they were \"paid\" to protest. More ...",
      "publisher": "MSN",
      "source": "duckduckgo",
      "query": "paid protesters",
      "date": "2025-10-31T00:00:00+00:00",
      "relevance_score": 90,
      "collected_at": "2026-01-15T03:26:04.162758Z"
    },
    {
      "title": "'STOP TRUMP' Craigslist ad recruiting paid protesters isn't from January 2026",
      "url": "https://www.msn.com/en-us/news/us/stop-trump-craigslist-ad-recruiting-paid-protesters-isnt-from-january-2026/ar-AA1UhUi9",
      "snippet": "A photo circulating online authentically showed a Craigslist ad from January 2026 recruiting paid protesters to demonstrate against U.S. President Donald Trump. The alleged advertisement was offering people up to $1,",
      "publisher": "Snopes",
      "source": "duckduckgo",
      "query": "paid protesters",
      "date": "2026-01-15T16:00:00+00:00",
      "relevance_score": 90,
      "collected_at": "2026-01-15T17:27:07.212741Z"
    },
    {
      "title": "Fact Check: Is 'Stop Trump' Craigslist ad recruiting paid protesters from January 2026 real?",
      "url": "https://news.meaww.com/fact-check-is-stop-trump-craigslist-ad-recruiting-paid-protesters-from-january-2026-real",
      "snippet": "On January 10, a Facebook user posted a picture of the Craigslist ad. The caption of the post read, \"'Stop Trump' Craigslist ad recruiting paid protesters from January 2026. Let's stop pretending this is 'activism'.\"",
      "publisher": "MEAWW News",
      "source": "duckduckgo",
      "query": "paid protesters",
      "date": "2026-01-16T03:08:00+00:00",
      "relevance_score": 90,
      "collected_at": "2026-01-16T04:34:34.917186Z"
    },
    {
      "title": "'STOP TRUMP' Craigslist ad recruiting paid protesters isn't from January 2026",
      "url": "https://www.msn.com/en-us/news/us/stop-trump-craigslist-ad-recruiting-paid-protesters-isnt-from-january-2026/ar-AA1UhUi9?ocid=BingNewsVerp",
      "snippet": "A photo circulating online authentically showed a Craigslist ad from January 2026 recruiting paid protesters to demonstrate ...",
      "publisher": "Snopes on MSN",
      "source": "duckduckgo",
      "query": "paid protesters",
      "date": "2025-12-31T08:21:19+00:00",
      "relevance_score": 90,
      "collected_at": "2026-01-16T08:21:20.071897Z"
    },
    {
      "title": "'They have brand-new, beautiful printed signs': Trump discredits himself when he explains why protesters are 'paid' by Democrats",
      "url": "https://www.msn.com/en-us/video/news/they-have-brand-new-beautiful-printed-signs-trump-discredits-himself-when-he-explains-why-protesters-are-paid-by-democrats/vi-AA1TJQqT?ocid=BingNewsVerp",
      "snippet": "During his remarks to House Republicans at the Kennedy Center yesterday, Donald Trump claimed protesters against him are \"paid\" by the radical left. Why does Trump think they're \"paid people\"? Because ...",
      "publisher": "Slingshot News on MSN",
      "source": "duckduckgo",
      "query": "paid protesters",
      "date": "2026-01-08T04:36:54+00:00",
      "relevance_score": 90,
      "collected_at": "2026-01-18T04:36:54.171416Z"
    },
    {
      "title": "'They Use Serious Hammers': Trump Discredits Himself When He Tries To Prove The Existence Of 'Paid' Protesters In Oval Office Rant",
      "url": "https://www.msn.com/en-us/politics/government/they-use-serious-hammers-trump-discredits-himself-when-he-tries-to-prove-the-existence-of-paid-protesters-in-oval-office-rant/vi-AA1Rgx4R?ocid=BingNewsVerp",
      "snippet": "Donald Trump signed a memorandum to deploy troops in Memphis several weeks ago from the Oval Office. During Q&A with the press, Trump tried to prove that protesters in cities are paid and part of some ...",
      "publisher": "MSN",
      "source": "duckduckgo",
      "query": "paid protesters",
      "date": "2025-11-27T00:00:00+00:00",
      "relevance_score": 90,
      "collected_at": "2026-01-18T04:36:54.171422Z"
    },
    {
      "title": "Let\u2019s settle once and for all whether protesters are \u2018paid\u2019 | Letters",
      "url": "https://www.yahoo.com/news/articles/let-settle-once-whether-protesters-233706168.html",
      "snippet": "Let\u2019s settle once and for all whether protesters are \u2018 paid \u2019 President Donald Trump has repeatedly ca...",
      "publisher": "The Des Moines Register",
      "source": "duckduckgo",
      "query": "paid protesters",
      "date": "2026-01-17T23:15:08+00:00",
      "relevance_score": 90,
      "collected_at": "2026-01-18T07:15:08.121826Z"
    },
    {
      "title": "'They use serious hammers': Trump discredits himself, tries to prove the existence of 'paid' protesters in rambling remarks",
      "url": "https://www.msn.com/en-us/video/money/they-use-serious-hammers-trump-discredits-himself-tries-to-prove-the-existence-of-paid-protesters-in-rambling-remarks/vi-AA1SXXnR?ocid=BingNewsVerp",
      "snippet": "Donald Trump signed a memorandum to deploy troops in Memphis several weeks ago in September. During Q&A with the press, Trump rambled on and on in an attempt to prove that protesters are \"paid.\" ...",
      "publisher": "MSN",
      "source": "duckduckgo",
      "query": "paid protesters",
      "date": "2025-12-24T00:00:00+00:00",
      "relevance_score": 90,
      "collected_at": "2026-01-18T10:15:18.305937Z"
    },
    {
      "title": "'They use serious hammers': Trump discredits himself, tries to prove the existence of 'paid' protesters in rambling remarks",
      "url": "https://www.msn.com/en-us/news/news/they-use-serious-hammers-trump-discredits-himself-tries-to-prove-the-existence-of-paid-protesters-in-rambling-remarks/vi-AA1SXXnR?ocid=BingNewsVerp",
      "snippet": "Donald Trump signed a memorandum to deploy troops in Memphis several weeks ago in September. During Q&A with the press, Trump rambled on and on in an attempt to prove that protesters are \"paid.\" So ...",
      "publisher": "MSN",
      "source": "duckduckgo",
      "query": "paid protesters",
      "date": "2025-12-24T00:00:00+00:00",
      "relevance_score": 90,
      "collected_at": "2026-01-18T11:12:02.926301Z"
    },
    {
      "title": "Paid Protestors Who Got Within Feet Of Trump Disrupt Scott Bessent\u2019s Dinner",
      "url": "https://ijr.com/paid-protestors-who-got-within-feet-of-trump-disrupt-scott-bessents-dinner/",
      "snippet": "A paid protestor employed by a Chinese Communist Party-linked activist group heckled Treasury Scott Bessent during a night out in Washington, D.C. on Wednesday. Bessent was dining at the wine bar ...",
      "publisher": "IJR",
      "source": "duckduckgo",
      "query": "paid protesters",
      "date": "2025-12-18T00:00:00+00:00",
      "relevance_score": 90,
      "collected_at": "2026-01-19T10:21:39.576656Z"
    },
    {
      "title": "Republicans' 'paid protesters' nonsense takes an ugly turn in Minnesota",
      "url": "https://www.yahoo.com/news/articles/republicans-paid-protesters-nonsense-takes-191357223.html",
      "snippet": "It might make Republicans feel better to think Minnesotans are secretly being paid to protest, but reality is stubborn",
      "publisher": "Yahoo",
      "source": "duckduckgo",
      "query": "paid protesters",
      "date": "2026-01-19T19:48:00+00:00",
      "relevance_score": 90,
      "collected_at": "2026-01-19T21:14:13.379058Z"
    },
    {
      "title": "'They Use Serious Hammers': Trump Discredits Himself When He Tries To Prove The Existence Of 'Paid' Protesters In Oval Office Rant",
      "url": "https://www.msn.com/en-us/video/news/they-use-serious-hammers-trump-discredits-himself-when-he-tries-to-prove-the-existence-of-paid-protesters-in-oval-office-rant/vi-AA1Rgx4R?ocid=BingNewsVerp",
      "snippet": "Donald Trump signed a memorandum to deploy troops in Memphis several weeks ago from the Oval Office. During Q&A with the press, Trump tried to prove that protesters in cities are paid and part of some ...",
      "publisher": "MSN",
      "source": "duckduckgo",
      "query": "paid protesters",
      "date": "2025-11-27T00:00:00+00:00",
      "relevance_score": 90,
      "collected_at": "2026-01-24T14:14:05.071326Z"
    }
  ],
  "jobPostings": [
    {
      "type": "job_posting",
      "source": "adzuna",
      "title": "Regional Canvass Manager - Bel Air",
      "company": "Civics Education Project",
      "city": "US",
      "state": "",
      "url": "https://www.adzuna.com/details/5498170678?utm_medium=api&utm_source=a70fa881",
      "date": "2026-02-06T09:35:58.935266Z",
      "salary_min": 62705.09,
      "salary_max": 62705.09,
      "suspicion_score": 20,
      "keywords": [
        "grassroots organizer"
      ],
      "is_monitoring_entry": false
    },
    {
      "type": "job_posting",
      "source": "adzuna",
      "title": "Political Roles",
      "company": "Talarico for Texas",
      "city": "US",
      "state": "",
      "url": "https://www.adzuna.com/details/5408399336?utm_medium=api&utm_source=a70fa881",
      "date": "2026-02-06T09:35:58.935155Z",
      "salary_min": 58642.65,
      "salary_max": 58642.65,
      "suspicion_score": 10,
      "keywords": [
        "grassroots organizer"
      ],
      "is_monitoring_entry": false
    },
    {
      "type": "job_posting",
      "source": "adzuna",
      "title": "Community Organizer",
      "company": "Dakota Rural Action",
      "city": "US",
      "state": "",
      "url": "https://www.adzuna.com/details/5615156872?utm_medium=api&utm_source=a70fa881",
      "date": "2026-02-06T09:35:58.935313Z",
      "salary_min": 105432.62,
      "salary_max": 105432.62,
      "suspicion_score": 10,
      "keywords": [
        "grassroots organizer"
      ],
      "is_monitoring_entry": false
    },
    {
      "type": "job_posting",
      "source": "adzuna",
      "title": "Regional Political Engagement Director",
      "company": "AIPAC",
      "city": "US",
      "state": "",
      "url": "https://www.adzuna.com/details/4950628330?utm_medium=api&utm_source=a70fa881",
      "date": "2026-02-06T09:35:59.189700Z",
      "salary_min": 115000,
      "salary_max": 137000,
      "suspicion_score": 10,
      "keywords": [
        "political activist"
      ],
      "is_monitoring_entry": false
    },
    {
      "type": "job_posting",
      "source": "adzuna",
      "title": "Financial Controller",
      "company": "Sourced.",
      "city": "US",
      "state": "",
      "url": "https://www.adzuna.com/details/5510963729?utm_medium=api&utm_source=a70fa881",
      "date": "2026-02-06T09:35:59.189798Z",
      "salary_min": 90000,
      "salary_max": 110000,
      "suspicion_score": 10,
      "keywords": [
        "political activist"
      ],
      "is_monitoring_entry": false
    },
    {
      "type": "job_posting",
      "source": "adzuna",
      "title": "Political Organizer, SEIU Local 1199",
      "company": "Current SEIU",
      "city": "US",
      "state": "",
      "url": "https://www.adzuna.com/details/5561467572?utm_medium=api&utm_source=a70fa881",
      "date": "2026-02-06T09:35:59.189867Z",
      "salary_min": 46556.62,
      "salary_max": 46556.62,
      "suspicion_score": 10,
      "keywords": [
        "political activist"
      ],
      "is_monitoring_entry": false
    },
    {
      "type": "job_posting",
      "source": "adzuna",
      "title": "Field Organizer",
      "company": "Adrian Garcia for Harris County Commissioners Court, Pct 2",
      "city": "US",
      "state": "",
      "url": "https://www.adzuna.com/land/ad/5617028004?se=Pq6VPj8D8RGW1If7Fy4iGg&utm_medium=api&utm_source=a70fa881&v=B10D10D10F9437A971CBF4DB4EEAC158E29D235F",
      "date": "2026-02-06T09:35:59.473659Z",
      "salary_min": 71935.22,
      "salary_max": 71935.22,
      "suspicion_score": 10,
      "keywords": [
        "campaign field"
      ],
      "is_monitoring_entry": false
    },
    {
      "type": "job_posting",
      "source": "adzuna",
      "title": "Manager, Advocacy & Student Programs",
      "company": "Planned Parenthood Hudson Peconic",
      "city": "US",
      "state": "",
      "url": "https://www.adzuna.com/land/ad/5606807113?se=5MTEPj8D8RGVOpq5rPuaVQ&utm_medium=api&utm_source=a70fa881&v=7C9FF2AFB50E816412D705FC8A5BF6090A701976",
      "date": "2026-02-06T09:35:59.783032Z",
      "salary_min": 65000,
      "salary_max": 75000,
      "suspicion_score": 10,
      "keywords": [
        "community organizer political"
      ],
      "is_monitoring_entry": false
    },
    {
      "type": "job_posting",
      "source": "adzuna",
      "title": "Senior Director of Campaigns and Advocacy Initiatives",
      "company": "Unknown",
      "city": "US",
      "state": "",
      "url": "https://www.adzuna.com/details/5610910936?utm_medium=api&utm_source=a70fa881",
      "date": "2026-02-06T09:36:00.451379Z",
      "salary_min": 130658.09,
      "salary_max": 130658.09,
      "suspicion_score": 10,
      "keywords": [
        "advocacy campaign"
      ],
      "is_monitoring_entry": false
    },
    {
      "type": "job_posting",
      "source": "adzuna",
      "title": "Regional Manager of State & Local Government Relations - West Region",
      "company": "JPMorgan Chase",
      "city": "US",
      "state": "",
      "url": "https://www.adzuna.com/land/ad/5568776536?se=5sQmPz8D8RGW1If7Fy4iGg&utm_medium=api&utm_source=a70fa881&v=D45BC38453437DEDF4FBAD1EBA38DCEA0925536B",
      "date": "2026-02-06T09:36:00.451401Z",
      "salary_min": 177870.98,
      "salary_max": 177870.98,
      "suspicion_score": 10,
      "keywords": [
        "advocacy campaign"
      ],
      "is_monitoring_entry": false
    },
    {
      "type": "job_posting",
      "source": "adzuna",
      "title": "Social Media Specialist",
      "company": "Glove House",
      "city": "US",
      "state": "",
      "url": "https://www.adzuna.com/details/5574756200?utm_medium=api&utm_source=a70fa881",
      "date": "2026-02-06T09:36:00.451442Z",
      "salary_min": 46395.82,
      "salary_max": 46395.82,
      "suspicion_score": 10,
      "keywords": [
        "advocacy campaign"
      ],
      "is_monitoring_entry": false
    },
    {
      "type": "job_posting",
      "source": "adzuna",
      "title": "Manager, Public Affairs & Advocacy",
      "company": "AAA Mountain West Group",
      "city": "US",
      "state": "",
      "url": "https://www.adzuna.com/details/5576229887?utm_medium=api&utm_source=a70fa881",
      "date": "2026-02-06T09:36:00.451462Z",
      "salary_min": 85575.55,
      "salary_max": 85575.55,
      "suspicion_score": 10,
      "keywords": [
        "advocacy campaign"
      ],
      "is_monitoring_entry": false
    },
    {
      "type": "job_posting",
      "source": "adzuna",
      "title": "Field Marketing Manager",
      "company": "Erie Home",
      "city": "US",
      "state": "",
      "url": "https://www.adzuna.com/details/5569290265?utm_medium=api&utm_source=a70fa881",
      "date": "2026-02-06T09:35:58.290602Z",
      "salary_min": 124351.01,
      "salary_max": 124351.01,
      "suspicion_score": 0,
      "keywords": [
        "canvasser political"
      ],
      "is_monitoring_entry": false
    },
    {
      "type": "job_posting",
      "source": "adzuna",
      "title": "Director, Political Engagement",
      "company": "AIPAC",
      "city": "US",
      "state": "",
      "url": "https://www.adzuna.com/details/5576815197?utm_medium=api&utm_source=a70fa881",
      "date": "2026-02-06T09:35:59.189744Z",
      "salary_min": 125000,
      "salary_max": 165000,
      "suspicion_score": 0,
      "keywords": [
        "political activist"
      ],
      "is_monitoring_entry": false
    },
    {
      "type": "job_posting",
      "source": "adzuna",
      "title": "Director of IT, Security, & Compliance",
      "company": "Perfected Claims",
      "city": "US",
      "state": "",
      "url": "https://www.adzuna.com/details/5614734565?utm_medium=api&utm_source=a70fa881",
      "date": "2026-02-06T09:35:59.473768Z",
      "salary_min": 125996.93,
      "salary_max": 125996.93,
      "suspicion_score": 0,
      "keywords": [
        "campaign field"
      ],
      "is_monitoring_entry": false
    },
    {
      "type": "job_posting",
      "source": "adzuna",
      "title": "Shift Supervisor",
      "company": "Graham-Windham Inc.",
      "city": "US",
      "state": "",
      "url": "https://www.adzuna.com/details/5391538151?utm_medium=api&utm_source=a70fa881",
      "date": "2026-02-06T09:35:59.782987Z",
      "salary_min": 54605.57,
      "salary_max": 54605.57,
      "suspicion_score": 0,
      "keywords": [
        "community organizer political"
      ],
      "is_monitoring_entry": false
    },
    {
      "type": "job_posting",
      "source": "adzuna",
      "title": "Assistant Campaign Manager",
      "company": "BIBLER FOR PROGRESS INC",
      "city": "US",
      "state": "",
      "url": "https://www.adzuna.com/land/ad/5584387274?se=5MTEPj8D8RGVOpq5rPuaVQ&utm_medium=api&utm_source=a70fa881&v=4FDC94E4C808E96C4F91898B98C0CBD5B404686E",
      "date": "2026-02-06T09:35:59.783006Z",
      "salary_min": 29734.16,
      "salary_max": 29734.16,
      "suspicion_score": 0,
      "keywords": [
        "community organizer political"
      ],
      "is_monitoring_entry": false
    },
    {
      "type": "job_posting",
      "source": "adzuna",
      "title": "Organizing Director, SEIU Local 221",
      "company": "Current SEIU",
      "city": "US",
      "state": "",
      "url": "https://www.adzuna.com/details/5532915397?utm_medium=api&utm_source=a70fa881",
      "date": "2026-02-06T09:35:59.783096Z",
      "salary_min": 110000,
      "salary_max": 120000,
      "suspicion_score": 0,
      "keywords": [
        "community organizer political"
      ],
      "is_monitoring_entry": false
    },
    {
      "type": "job_posting",
      "source": "adzuna",
      "title": "Mobility Coordinator",
      "company": "GE Vernova",
      "city": "US",
      "state": "",
      "url": "https://www.adzuna.com/land/ad/5566637040?se=8InzPj8D8RGsyd5-fAc_gA&utm_medium=api&utm_source=a70fa881&v=D705923391B470A4D6BA85E0204CBDC3DEE31852",
      "date": "2026-02-06T09:36:00.155098Z",
      "salary_min": 84624.15,
      "salary_max": 84624.15,
      "suspicion_score": 0,
      "keywords": [
        "mobilization coordinator"
      ],
      "is_monitoring_entry": false
    },
    {
      "type": "job_posting",
      "source": "adzuna",
      "title": "Mobile Clinic Coordinator",
      "company": "International Community Health Services",
      "city": "US",
      "state": "",
      "url": "https://www.adzuna.com/land/ad/5616773055?se=8InzPj8D8RGsyd5-fAc_gA&utm_medium=api&utm_source=a70fa881&v=E7A9EEE5C967542A461D6E58D28C76E09AE87E7A",
      "date": "2026-02-06T09:36:00.155135Z",
      "salary_min": 76835.35,
      "salary_max": 76835.35,
      "suspicion_score": 0,
      "keywords": [
        "mobilization coordinator"
      ],
      "is_monitoring_entry": false
    },
    {
      "type": "job_posting",
      "source": "adzuna",
      "title": "Mobile Service Coordinator",
      "company": "Stivers Automotive Group",
      "city": "US",
      "state": "",
      "url": "https://www.adzuna.com/land/ad/5609894333?se=8InzPj8D8RGsyd5-fAc_gA&utm_medium=api&utm_source=a70fa881&v=35E464229EEE000C8A69068C74114E7827C34057",
      "date": "2026-02-06T09:36:00.155156Z",
      "salary_min": 51044.55,
      "salary_max": 51044.55,
      "suspicion_score": 0,
      "keywords": [
        "mobilization coordinator"
      ],
      "is_monitoring_entry": false
    },
    {
      "type": "job_posting",
      "source": "adzuna",
      "title": "Mobile Outreach Coordinator",
      "company": "Oak Orchard Community Health Center",
      "city": "US",
      "state": "",
      "url": "https://www.adzuna.com/land/ad/5607492725?se=8InzPj8D8RGsyd5-fAc_gA&utm_medium=api&utm_source=a70fa881&v=344BDC99BE5F9EEE1B918428C8EE73A2968887FB",
      "date": "2026-02-06T09:36:00.155257Z",
      "salary_min": 52000,
      "salary_max": 64480,
      "suspicion_score": 0,
      "keywords": [
        "mobilization coordinator"
      ],
      "is_monitoring_entry": false
    },
    {
      "type": "job_posting",
      "source": "adzuna",
      "title": "Mobile Events Coordinator",
      "company": "Puzzle Solutions Holdings LLC",
      "city": "US",
      "state": "",
      "url": "https://www.adzuna.com/details/5584488000?utm_medium=api&utm_source=a70fa881",
      "date": "2026-02-06T09:36:00.155276Z",
      "salary_min": 55000,
      "salary_max": 62000,
      "suspicion_score": 0,
      "keywords": [
        "mobilization coordinator"
      ],
      "is_monitoring_entry": false
    },
    {
      "type": "job_posting",
      "source": "adzuna",
      "title": "Government Corporate Relations Advisor",
      "company": "United Global Technologies",
      "city": "US",
      "state": "",
      "url": "https://www.adzuna.com/land/ad/5593901685?se=5sQmPz8D8RGW1If7Fy4iGg&utm_medium=api&utm_source=a70fa881&v=966968C202F3B977735D9B0B957AA5FFB90E4B8E",
      "date": "2026-02-06T09:36:00.451422Z",
      "salary_min": 94134.36,
      "salary_max": 94134.36,
      "suspicion_score": 0,
      "keywords": [
        "advocacy campaign"
      ],
      "is_monitoring_entry": false
    },
    {
      "type": "job_posting",
      "source": "adzuna",
      "title": "Political Canvasser",
      "company": "Nuevo Field Campaigns",
      "city": "US",
      "state": "",
      "url": "https://www.adzuna.com/details/5599108842?utm_medium=api&utm_source=a70fa881",
      "date": "2026-02-06T10:32:57.974844Z",
      "salary_min": 41600,
      "salary_max": 47840,
      "suspicion_score": 25,
      "keywords": [
        "canvasser political"
      ],
      "is_monitoring_entry": false
    },
    {
      "type": "job_posting",
      "source": "adzuna",
      "title": "NYWFP Petition Canvasser",
      "company": "Working Families Party",
      "city": "US",
      "state": "",
      "url": "https://www.adzuna.com/details/5615723394?utm_medium=api&utm_source=a70fa881",
      "date": "2026-02-06T10:32:58.195991Z",
      "salary_min": 68815.02,
      "salary_max": 68815.02,
      "suspicion_score": 20,
      "keywords": [
        "petition signature"
      ],
      "is_monitoring_entry": false
    },
    {
      "type": "job_posting",
      "source": "adzuna",
      "title": "Regional Canvass Manager - Columbia",
      "company": "Civics Education Project",
      "city": "US",
      "state": "",
      "url": "https://www.adzuna.com/details/5500535138?utm_medium=api&utm_source=a70fa881",
      "date": "2026-02-06T10:32:58.412042Z",
      "salary_min": 59549.66,
      "salary_max": 59549.66,
      "suspicion_score": 20,
      "keywords": [
        "grassroots organizer"
      ],
      "is_monitoring_entry": false
    },
    {
      "type": "job_posting",
      "source": "adzuna",
      "title": "Regional Canvass Manager",
      "company": "Civics Education Project",
      "city": "US",
      "state": "",
      "url": "https://www.adzuna.com/details/5500324696?utm_medium=api&utm_source=a70fa881",
      "date": "2026-02-06T10:32:58.412069Z",
      "salary_min": 64787.31,
      "salary_max": 64787.31,
      "suspicion_score": 20,
      "keywords": [
        "grassroots organizer"
      ],
      "is_monitoring_entry": false
    },
    {
      "type": "job_posting",
      "source": "adzuna",
      "title": "Regional Canvass Manager - Annapolis",
      "company": "Civics Education Project",
      "city": "US",
      "state": "",
      "url": "https://www.adzuna.com/details/5499148722?utm_medium=api&utm_source=a70fa881",
      "date": "2026-02-06T10:32:58.412130Z",
      "salary_min": 71909.36,
      "salary_max": 71909.36,
      "suspicion_score": 20,
      "keywords": [
        "grassroots organizer"
      ],
      "is_monitoring_entry": false
    },
    {
      "type": "job_posting",
      "source": "adzuna",
      "title": "Federal Campaigns Lead Climate Policy & Advocacy (Washington)",
      "company": "The Public Interest Network",
      "city": "US",
      "state": "",
      "url": "https://www.adzuna.com/details/5605641552?utm_medium=api&utm_source=a70fa881",
      "date": "2026-02-06T10:32:58.412150Z",
      "salary_min": 88063.86,
      "salary_max": 88063.86,
      "suspicion_score": 20,
      "keywords": [
        "grassroots organizer"
      ],
      "is_monitoring_entry": false
    },
    {
      "type": "job_posting",
      "source": "adzuna",
      "title": "Field Canvass Management - Environment/Democracy Advocacy",
      "company": "Clean Water Action",
      "city": "US",
      "state": "",
      "url": "https://www.adzuna.com/details/5606958245?utm_medium=api&utm_source=a70fa881",
      "date": "2026-02-06T10:32:59.753078Z",
      "salary_min": 73471.28,
      "salary_max": 73471.28,
      "suspicion_score": 20,
      "keywords": [
        "advocacy campaign"
      ],
      "is_monitoring_entry": false
    },
    {
      "type": "job_posting",
      "source": "adzuna",
      "title": "Political Organizer",
      "company": "Nuevo Field Campaigns",
      "city": "US",
      "state": "",
      "url": "https://www.adzuna.com/details/5612023566?utm_medium=api&utm_source=a70fa881",
      "date": "2026-02-06T10:32:58.195855Z",
      "salary_min": 62400,
      "salary_max": 62400,
      "suspicion_score": 15,
      "keywords": [
        "petition signature"
      ],
      "is_monitoring_entry": false
    },
    {
      "type": "job_posting",
      "source": "adzuna",
      "title": "Community Canvassers",
      "company": "The Outreach Team",
      "city": "US",
      "state": "",
      "url": "https://www.adzuna.com/details/5611268896?utm_medium=api&utm_source=a70fa881",
      "date": "2026-02-06T10:32:58.196010Z",
      "salary_min": 64651.71,
      "salary_max": 64651.71,
      "suspicion_score": 15,
      "keywords": [
        "petition signature"
      ],
      "is_monitoring_entry": false
    },
    {
      "type": "job_posting",
      "source": "adzuna",
      "title": "Field Organizer",
      "company": "Adrian Garcia for Harris County Commissioners Court, Pct 2",
      "city": "US",
      "state": "",
      "url": "https://www.adzuna.com/land/ad/5617028004?se=6NDFNEcD8RGVOpq5rPuaVQ&utm_medium=api&utm_source=a70fa881&v=B10D10D10F9437A971CBF4DB4EEAC158E29D235F",
      "date": "2026-02-06T10:32:58.926010Z",
      "salary_min": 71935.22,
      "salary_max": 71935.22,
      "suspicion_score": 10,
      "keywords": [
        "campaign field"
      ],
      "is_monitoring_entry": false
    },
    {
      "type": "job_posting",
      "source": "adzuna",
      "title": "Manager, Advocacy & Student Programs",
      "company": "Planned Parenthood Hudson Peconic",
      "city": "US",
      "state": "",
      "url": "https://www.adzuna.com/land/ad/5606807113?se=OITqNEcD8RGW1If7Fy4iGg&utm_medium=api&utm_source=a70fa881&v=7C9FF2AFB50E816412D705FC8A5BF6090A701976",
      "date": "2026-02-06T10:32:59.235098Z",
      "salary_min": 65000,
      "salary_max": 75000,
      "suspicion_score": 10,
      "keywords": [
        "community organizer political"
      ],
      "is_monitoring_entry": false
    },
    {
      "type": "job_posting",
      "source": "adzuna",
      "title": "Regional Manager of State & Local Government Relations - West Region",
      "company": "JPMorgan Chase",
      "city": "US",
      "state": "",
      "url": "https://www.adzuna.com/land/ad/5568776536?se=RDtANUcD8RGVOpq5rPuaVQ&utm_medium=api&utm_source=a70fa881&v=D45BC38453437DEDF4FBAD1EBA38DCEA0925536B",
      "date": "2026-02-06T10:32:59.752993Z",
      "salary_min": 177870.98,
      "salary_max": 177870.98,
      "suspicion_score": 10,
      "keywords": [
        "advocacy campaign"
      ],
      "is_monitoring_entry": false
    },
    {
      "type": "job_posting",
      "source": "adzuna",
      "title": "Global Mobility Coordinator",
      "company": "Cloudflare",
      "city": "US",
      "state": "",
      "url": "https://www.adzuna.com/details/5586150084?utm_medium=api&utm_source=a70fa881",
      "date": "2026-02-06T10:32:59.509067Z",
      "salary_min": 90700.27,
      "salary_max": 90700.27,
      "suspicion_score": 5,
      "keywords": [
        "mobilization coordinator"
      ],
      "is_monitoring_entry": false
    },
    {
      "type": "job_posting",
      "source": "adzuna",
      "title": "State Affiliate Political Organizer (SAPO)",
      "company": "TEXAS AFT",
      "city": "US",
      "state": "",
      "url": "https://www.adzuna.com/details/5487431097?utm_medium=api&utm_source=a70fa881",
      "date": "2026-02-06T10:32:58.699755Z",
      "salary_min": 65128.34,
      "salary_max": 65128.34,
      "suspicion_score": 0,
      "keywords": [
        "political activist"
      ],
      "is_monitoring_entry": false
    },
    {
      "type": "job_posting",
      "source": "adzuna",
      "title": "Political Director, SEIU Local 521",
      "company": "Current SEIU",
      "city": "US",
      "state": "",
      "url": "https://www.adzuna.com/details/5543529916?utm_medium=api&utm_source=a70fa881",
      "date": "2026-02-06T10:32:58.699810Z",
      "salary_min": 128410,
      "salary_max": 141926,
      "suspicion_score": 0,
      "keywords": [
        "political activist"
      ],
      "is_monitoring_entry": false
    },
    {
      "type": "job_posting",
      "source": "adzuna",
      "title": "Field Campaign Marketing Specialist, U.S.",
      "company": "Torq",
      "city": "US",
      "state": "",
      "url": "https://www.adzuna.com/details/5587841694?utm_medium=api&utm_source=a70fa881",
      "date": "2026-02-06T10:32:58.926048Z",
      "salary_min": 80121.38,
      "salary_max": 80121.38,
      "suspicion_score": 0,
      "keywords": [
        "campaign field"
      ],
      "is_monitoring_entry": false
    },
    {
      "type": "job_posting",
      "source": "adzuna",
      "title": "Director of Community Outreach",
      "company": "Fathers & Families Support Center",
      "city": "US",
      "state": "",
      "url": "https://www.adzuna.com/details/5078232766?utm_medium=api&utm_source=a70fa881",
      "date": "2026-02-06T10:32:59.235020Z",
      "salary_min": 78390.19,
      "salary_max": 78390.19,
      "suspicion_score": 0,
      "keywords": [
        "community organizer political"
      ],
      "is_monitoring_entry": false
    },
    {
      "type": "job_posting",
      "source": "adzuna",
      "title": "Security Manager",
      "company": "Graham-Windham Inc.",
      "city": "US",
      "state": "",
      "url": "https://www.adzuna.com/details/5391630274?utm_medium=api&utm_source=a70fa881",
      "date": "2026-02-06T10:32:59.235042Z",
      "salary_min": 68501.32,
      "salary_max": 68501.32,
      "suspicion_score": 0,
      "keywords": [
        "community organizer political"
      ],
      "is_monitoring_entry": false
    },
    {
      "type": "job_posting",
      "source": "adzuna",
      "title": "Assistant Campaign Manager",
      "company": "BIBLER FOR PROGRESS INC",
      "city": "US",
      "state": "",
      "url": "https://www.adzuna.com/land/ad/5584387274?se=OITqNEcD8RGW1If7Fy4iGg&utm_medium=api&utm_source=a70fa881&v=4FDC94E4C808E96C4F91898B98C0CBD5B404686E",
      "date": "2026-02-06T10:32:59.235078Z",
      "salary_min": 29734.16,
      "salary_max": 29734.16,
      "suspicion_score": 0,
      "keywords": [
        "community organizer political"
      ],
      "is_monitoring_entry": false
    },
    {
      "type": "job_posting",
      "source": "adzuna",
      "title": "Mobility Coordinator",
      "company": "GE Vernova",
      "city": "US",
      "state": "",
      "url": "https://www.adzuna.com/land/ad/5566637040?se=lEMaNUcD8RGsyd5-fAc_gA&utm_medium=api&utm_source=a70fa881&v=D705923391B470A4D6BA85E0204CBDC3DEE31852",
      "date": "2026-02-06T10:32:59.508917Z",
      "salary_min": 84624.15,
      "salary_max": 84624.15,
      "suspicion_score": 0,
      "keywords": [
        "mobilization coordinator"
      ],
      "is_monitoring_entry": false
    },
    {
      "type": "job_posting",
      "source": "adzuna",
      "title": "Mobile Clinic Coordinator",
      "company": "International Community Health Services",
      "city": "US",
      "state": "",
      "url": "https://www.adzuna.com/land/ad/5616773055?se=lEMaNUcD8RGsyd5-fAc_gA&utm_medium=api&utm_source=a70fa881&v=E7A9EEE5C967542A461D6E58D28C76E09AE87E7A",
      "date": "2026-02-06T10:32:59.508956Z",
      "salary_min": 76835.35,
      "salary_max": 76835.35,
      "suspicion_score": 0,
      "keywords": [
        "mobilization coordinator"
      ],
      "is_monitoring_entry": false
    },
    {
      "type": "job_posting",
      "source": "adzuna",
      "title": "Mobile Service Coordinator",
      "company": "Stivers Automotive Group",
      "city": "US",
      "state": "",
      "url": "https://www.adzuna.com/land/ad/5609894333?se=lEMaNUcD8RGsyd5-fAc_gA&utm_medium=api&utm_source=a70fa881&v=35E464229EEE000C8A69068C74114E7827C34057",
      "date": "2026-02-06T10:32:59.508985Z",
      "salary_min": 51044.55,
      "salary_max": 51044.55,
      "suspicion_score": 0,
      "keywords": [
        "mobilization coordinator"
      ],
      "is_monitoring_entry": false
    },
    {
      "type": "job_posting",
      "source": "adzuna",
      "title": "Air Mobility Coordinator",
      "company": "Topsarge Business Solutions",
      "city": "US",
      "state": "",
      "url": "https://www.adzuna.com/details/5431242285?utm_medium=api&utm_source=a70fa881",
      "date": "2026-02-06T10:32:59.509012Z",
      "salary_min": 90000,
      "salary_max": 95000,
      "suspicion_score": 0,
      "keywords": [
        "mobilization coordinator"
      ],
      "is_monitoring_entry": false
    },
    {
      "type": "job_posting",
      "source": "adzuna",
      "title": "Economic Mobility Coordinator",
      "company": "National Community Renaissance",
      "city": "US",
      "state": "",
      "url": "https://www.adzuna.com/details/5596318741?utm_medium=api&utm_source=a70fa881",
      "date": "2026-02-06T10:32:59.509040Z",
      "salary_min": 43680,
      "salary_max": 47840,
      "suspicion_score": 0,
      "keywords": [
        "mobilization coordinator"
      ],
      "is_monitoring_entry": false
    },
    {
      "type": "job_posting",
      "source": "adzuna",
      "title": "Mobile Outreach Coordinator",
      "company": "Oak Orchard Community Health Center",
      "city": "US",
      "state": "",
      "url": "https://www.adzuna.com/land/ad/5607492725?se=lEMaNUcD8RGsyd5-fAc_gA&utm_medium=api&utm_source=a70fa881&v=344BDC99BE5F9EEE1B918428C8EE73A2968887FB",
      "date": "2026-02-06T10:32:59.509120Z",
      "salary_min": 52000,
      "salary_max": 64480,
      "suspicion_score": 0,
      "keywords": [
        "mobilization coordinator"
      ],
      "is_monitoring_entry": false
    },
    {
      "type": "job_posting",
      "source": "adzuna",
      "title": "Government Corporate Relations Advisor",
      "company": "United Global Technologies",
      "city": "US",
      "state": "",
      "url": "https://www.adzuna.com/land/ad/5593901685?se=RDtANUcD8RGVOpq5rPuaVQ&utm_medium=api&utm_source=a70fa881&v=966968C202F3B977735D9B0B957AA5FFB90E4B8E",
      "date": "2026-02-06T10:32:59.753015Z",
      "salary_min": 94134.36,
      "salary_max": 94134.36,
      "suspicion_score": 0,
      "keywords": [
        "advocacy campaign"
      ],
      "is_monitoring_entry": false
    }
  ],
  "jobPostingPatterns": {
    "totalJobs": 50
  },
  "flaggedOrganizations": [
    {
      "type": "independent_expenditure",
      "source": "fec",
      "committee_id": "C00687103",
      "committee_name": "AMERICANS FOR PROSPERITY ACTION, INC. (AFP ACTION) DBA CVA ACTION AND DBA LIBRE ACTION",
      "amount": 250000.0,
      "date": "2026-02-02",
      "state": "NH"
    },
    {
      "type": "independent_expenditure",
      "source": "fec",
      "committee_id": "C00687103",
      "committee_name": "AMERICANS FOR PROSPERITY ACTION, INC. (AFP ACTION) DBA CVA ACTION AND DBA LIBRE ACTION",
      "amount": 500000.0,
      "date": "2026-02-02",
      "state": "MI"
    },
    {
      "type": "independent_expenditure",
      "source": "fec",
      "committee_id": "C00932707",
      "committee_name": "CONSERVATIVE TEXANS PAC",
      "amount": 9000.0,
      "date": "2026-02-02",
      "state": "TX"
    },
    {
      "type": "independent_expenditure",
      "source": "fec",
      "committee_id": "C00932707",
      "committee_name": "CONSERVATIVE TEXANS PAC",
      "amount": 774251.0,
      "date": "2026-02-02",
      "state": "TX"
    },
    {
      "type": "independent_expenditure",
      "source": "fec",
      "committee_id": "C00633248",
      "committee_name": "314 ACTION FUND",
      "amount": 73097.98,
      "date": "2026-02-02",
      "state": "IL"
    },
    {
      "type": "independent_expenditure",
      "source": "fec",
      "committee_id": "C00523241",
      "committee_name": "SPECIAL OPERATIONS FOR AMERICA",
      "amount": 25000.0,
      "date": "2026-02-02",
      "state": "NC"
    },
    {
      "type": "independent_expenditure",
      "source": "fec",
      "committee_id": "C00937094",
      "committee_name": "STRONG PAC",
      "amount": 9412.0,
      "date": "2026-02-02",
      "state": "TX"
    },
    {
      "type": "independent_expenditure",
      "source": "fec",
      "committee_id": "C00937094",
      "committee_name": "STRONG PAC",
      "amount": 1750.0,
      "date": "2026-02-02",
      "state": "TX"
    },
    {
      "type": "independent_expenditure",
      "source": "fec",
      "committee_id": "C00937094",
      "committee_name": "STRONG PAC",
      "amount": 2000.0,
      "date": "2026-02-02",
      "state": "TX"
    },
    {
      "type": "independent_expenditure",
      "source": "fec",
      "committee_id": "C00448696",
      "committee_name": "SENATE CONSERVATIVES FUND",
      "amount": 9022.58,
      "date": "2026-02-02",
      "state": "KY"
    },
    {
      "type": "independent_expenditure",
      "source": "fec",
      "committee_id": "C00448696",
      "committee_name": "SENATE CONSERVATIVES FUND",
      "amount": 9022.57,
      "date": "2026-02-02",
      "state": "FL"
    },
    {
      "type": "independent_expenditure",
      "source": "fec",
      "committee_id": "C00448696",
      "committee_name": "SENATE CONSERVATIVES FUND",
      "amount": 9022.57,
      "date": "2026-02-02",
      "state": "TN"
    },
    {
      "type": "independent_expenditure",
      "source": "fec",
      "committee_id": "C00844613",
      "committee_name": "WIN IT BACK PAC",
      "amount": 24139.65,
      "date": "2026-02-02",
      "state": "TX"
    },
    {
      "type": "independent_expenditure",
      "source": "fec",
      "committee_id": "C00687103",
      "committee_name": "AMERICANS FOR PROSPERITY ACTION, INC. (AFP ACTION) DBA CVA ACTION AND DBA LIBRE ACTION",
      "amount": 23862.0,
      "date": "2026-02-02",
      "state": "MI"
    },
    {
      "type": "independent_expenditure",
      "source": "fec",
      "committee_id": "C00799031",
      "committee_name": "UNITED DEMOCRACY PROJECT ('UDP')",
      "amount": 43493.05,
      "date": "2026-02-02",
      "state": "NJ"
    },
    {
      "type": "independent_expenditure",
      "source": "fec",
      "committee_id": "C00513176",
      "committee_name": "CONGRESSIONAL PROGRESSIVE CAUCUS PAC",
      "amount": 50000.0,
      "date": "2026-02-02",
      "state": "NJ"
    },
    {
      "type": "new_committee",
      "source": "fec",
      "committee_id": "C00937433",
      "name": "GLOVES OFF AMERICA",
      "committee_type": "O",
      "first_file_date": "2026-02-02",
      "state": "MN",
      "city": null
    },
    {
      "type": "new_committee",
      "source": "fec",
      "committee_id": "C00937367",
      "name": "SOCIAL CONTRACT ACTION COMMITTEE",
      "committee_type": "O",
      "first_file_date": "2026-02-02",
      "state": "KS",
      "city": null
    },
    {
      "type": "new_committee",
      "source": "fec",
      "committee_id": "C00937094",
      "name": "STRONG PAC",
      "committee_type": "O",
      "first_file_date": "2026-01-29",
      "state": "WI",
      "city": null
    },
    {
      "type": "new_committee",
      "source": "fec",
      "committee_id": "C00937029",
      "name": "AMERICAN POWER PAC",
      "committee_type": "O",
      "first_file_date": "2026-01-29",
      "state": "TX",
      "city": null
    },
    {
      "type": "new_committee",
      "source": "fec",
      "committee_id": "C00936997",
      "name": "INVEST IN TOMORROW COALITION PAC",
      "committee_type": "O",
      "first_file_date": "2026-01-29",
      "state": "CA",
      "city": null
    },
    {
      "type": "new_committee",
      "source": "fec",
      "committee_id": "C00937110",
      "name": "NO PUNCHING DOWN ACTION FUND",
      "committee_type": "O",
      "first_file_date": "2026-01-29",
      "state": "AR",
      "city": null
    },
    {
      "type": "new_committee",
      "source": "fec",
      "committee_id": "C00936690",
      "name": "SULLIVAN COUNTY FIRST PAC",
      "committee_type": "O",
      "first_file_date": "2026-01-27",
      "state": "TN",
      "city": null
    },
    {
      "type": "new_committee",
      "source": "fec",
      "committee_id": "C00936724",
      "name": "ELECT CHICAGO WOMEN AKA ECW",
      "committee_type": "O",
      "first_file_date": "2026-01-27",
      "state": "IL",
      "city": null
    },
    {
      "type": "new_committee",
      "source": "fec",
      "committee_id": "C00936591",
      "name": "FIGHTING FOR NEW YORK PAC",
      "committee_type": "O",
      "first_file_date": "2026-01-27",
      "state": "DC",
      "city": null
    },
    {
      "type": "new_committee",
      "source": "fec",
      "committee_id": "C00936609",
      "name": "WE DESERVE BETTER",
      "committee_type": "O",
      "first_file_date": "2026-01-27",
      "state": "CT",
      "city": null
    },
    {
      "type": "new_committee",
      "source": "fec",
      "committee_id": "C00936716",
      "name": "LEADERS FOR AMERICAN SUPER PAC",
      "committee_type": "O",
      "first_file_date": "2026-01-27",
      "state": "WA",
      "city": null
    },
    {
      "type": "new_committee",
      "source": "fec",
      "committee_id": "C00936518",
      "name": "ACCOUNTABILITY FOR ALL FUND INC.",
      "committee_type": "O",
      "first_file_date": "2026-01-26",
      "state": "DE",
      "city": null
    },
    {
      "type": "new_committee",
      "source": "fec",
      "committee_id": "C00936377",
      "name": "STUDENTS THE FREE PAC",
      "committee_type": "O",
      "first_file_date": "2026-01-26",
      "state": "TN",
      "city": null
    },
    {
      "type": "new_committee",
      "source": "fec",
      "committee_id": "C00935395",
      "name": "FOR OUR CHILDREN FLORIDA PAC",
      "committee_type": "O",
      "first_file_date": "2026-01-20",
      "state": "FL",
      "city": null
    },
    {
      "type": "new_committee",
      "source": "fec",
      "committee_id": "C00935536",
      "name": "NORTH GEORGIANS FOR OUR CONSERVATIVE FUTURE PAC",
      "committee_type": "O",
      "first_file_date": "2026-01-20",
      "state": "GA",
      "city": null
    },
    {
      "type": "new_committee",
      "source": "fec",
      "committee_id": "C00935593",
      "name": "JASON BARNES FOR PRESIDENT",
      "committee_type": "U",
      "first_file_date": "2026-01-20",
      "state": "TX",
      "city": null
    },
    {
      "type": "new_committee",
      "source": "fec",
      "committee_id": "C00935312",
      "name": "GEM CITY GOOD TROUBLE",
      "committee_type": "O",
      "first_file_date": "2026-01-19",
      "state": "OH",
      "city": null
    },
    {
      "type": "new_committee",
      "source": "fec",
      "committee_id": "C00934877",
      "name": "STOP COMMUNISM PAC",
      "committee_type": "V",
      "first_file_date": "2026-01-15",
      "state": "AL",
      "city": null
    },
    {
      "type": "new_committee",
      "source": "fec",
      "committee_id": "C00934885",
      "name": "DEFUND SIERRA CLUB PAC",
      "committee_type": "O",
      "first_file_date": "2026-01-15",
      "state": "MA",
      "city": null
    },
    {
      "type": "new_committee",
      "source": "fec",
      "committee_id": "C00934729",
      "name": "MAIN STREET VALUES PAC",
      "committee_type": "O",
      "first_file_date": "2026-01-15",
      "state": "OH",
      "city": null
    },
    {
      "type": "new_committee",
      "source": "fec",
      "committee_id": "C00934570",
      "name": "ARIZONA PATRIOTS SUPER PAC",
      "committee_type": "O",
      "first_file_date": "2026-01-14",
      "state": "AZ",
      "city": null
    },
    {
      "type": "new_committee",
      "source": "fec",
      "committee_id": "C00934463",
      "name": "RED BAYOU PAC",
      "committee_type": "O",
      "first_file_date": "2026-01-14",
      "state": "TX",
      "city": null
    },
    {
      "type": "new_committee",
      "source": "fec",
      "committee_id": "C00934596",
      "name": "WIRE TO WIRE FOR KENTUCKY",
      "committee_type": "O",
      "first_file_date": "2026-01-14",
      "state": "DC",
      "city": null
    },
    {
      "type": "new_committee",
      "source": "fec",
      "committee_id": "C00934653",
      "name": "STW PAC, INC.",
      "committee_type": "O",
      "first_file_date": "2026-01-14",
      "state": "VA",
      "city": null
    }
  ]
}