{
  "lastScan": "2026-04-08T18:01:50.426396Z",
  "stats": {
    "events": 100,
    "alerts": 3,
    "orgs": 40,
    "newsArticles": 20
  },
  "systemConfidence": 60,
  "confidenceFactors": [
    {
      "factor": "News Coverage",
      "score": 80,
      "detail": "10 high-relevance articles"
    },
    {
      "factor": "Organization Risk",
      "score": 35,
      "detail": "0 high-risk orgs"
    },
    {
      "factor": "Job Postings",
      "score": 30,
      "detail": "0 suspicious postings"
    }
  ],
  "agentNotes": [
    {
      "summary": "Monitoring 15 news, 15 orgs, 57 jobs. 3 alerts.",
      "timestamp": "2026-04-08T18:01:50.425282Z"
    },
    {
      "summary": "Monitoring 15 news, 15 orgs, 57 jobs. 3 alerts.",
      "timestamp": "2026-04-08T16:54:10.777077Z"
    },
    {
      "summary": "Monitoring 6 news, 15 orgs, 57 jobs. 3 alerts.",
      "timestamp": "2026-04-08T15:03:53.998681Z"
    },
    {
      "summary": "Monitoring 7 news, 15 orgs, 57 jobs. 3 alerts.",
      "timestamp": "2026-04-08T13:06:25.430670Z"
    },
    {
      "summary": "Monitoring 15 news, 15 orgs, 57 jobs. 2 alerts.",
      "timestamp": "2026-04-08T11:48:24.592200Z"
    },
    {
      "summary": "Monitoring 15 news, 15 orgs, 57 jobs. 2 alerts.",
      "timestamp": "2026-04-08T10:02:16.064600Z"
    },
    {
      "summary": "Monitoring 4 news, 15 orgs, 57 jobs. 1 alerts.",
      "timestamp": "2026-04-08T08:08:32.041950Z"
    },
    {
      "summary": "Monitoring 15 news, 15 orgs, 58 jobs. 2 alerts.",
      "timestamp": "2026-04-08T06:17:45.172944Z"
    },
    {
      "summary": "Monitoring 15 news, 15 orgs, 59 jobs. 2 alerts.",
      "timestamp": "2026-04-08T04:32:04.683776Z"
    },
    {
      "summary": "Monitoring 15 news, 15 orgs, 59 jobs. 3 alerts.",
      "timestamp": "2026-04-08T01:50:13.600806Z"
    }
  ],
  "connections": [
    {
      "type": "Naming Pattern",
      "description": "18 orgs with generic patriotic names typical of astroturf.",
      "probability": 78,
      "evidence": [
        {
          "type": "Org",
          "detail": "Citizens For Sanity"
        },
        {
          "type": "Org",
          "detail": "Citizens For Education"
        },
        {
          "type": "Org",
          "detail": "Citizens For Peace"
        }
      ]
    },
    {
      "type": "Paid Protest News",
      "description": "5 articles specifically about paid protesters.",
      "probability": 72,
      "evidence": [
        {
          "type": "News",
          "detail": "Fact Check: Post Does NOT Prove 'No Kings' Rallies Participants Were Paid To Join Protests on March "
        },
        {
          "type": "News",
          "detail": "Joe Rogan Raises Eyebrows for Claiming ICE Protests Are 'Paid for and Organized' as Famous Podcaster"
        }
      ]
    }
  ],
  "timeline": [
    {
      "type": "news",
      "title": "Fact Check: Post Does NOT Prove 'No Kings' Rallies Participants Were Paid To Join Protests on March 28, 2026",
      "date": "2026-04-08T18:01:50.426396Z",
      "sourceUrl": "https://www.yahoo.com/news/articles/fact-check-post-does-not-013540503.html"
    },
    {
      "type": "news",
      "title": "Joe Rogan Raises Eyebrows for Claiming ICE Protests Are 'Paid for and Organized' as Famous Podcaster Confronts RFK Jr. Over 'Very Disturbing' Raids",
      "date": "2026-04-08T18:01:50.426396Z",
      "sourceUrl": "https://www.aol.com/joe-rogan-raises-eyebrows-claiming-184500387.html"
    },
    {
      "type": "news",
      "title": "Buying or organizing? That is the 'paid protestors' question",
      "date": "2026-04-08T18:01:50.426396Z",
      "sourceUrl": "https://www.times-georgian.com/news/local/buying-or-organizing-that-is-the-paid-protestors-question/article_f94ed7e7-b005-5f56-bf5b-55b234877b2d.html"
    },
    {
      "type": "news",
      "title": "Joe Rogan Raises Eyebrows for Claiming ICE Protests Are 'Paid for and Organized' as Famous Podcaster Confronts RFK Jr. Over 'Very Disturbing' Raids",
      "date": "2026-04-08T16:54:10.777965Z",
      "sourceUrl": "https://www.aol.com/joe-rogan-raises-eyebrows-claiming-184500387.html"
    },
    {
      "type": "news",
      "title": "'Beautiful printed signs': Trump tries to use protest signs as evidence that protesters are 'paid people' in unconvincing remarks",
      "date": "2026-04-08T16:54:10.777965Z",
      "sourceUrl": "https://www.msn.com/en-us/news/opinion/beautiful-printed-signs-trump-tries-to-use-protest-signs-as-evidence-that-protesters-are-paid-people-in-unconvincing-remarks/vi-AA1ZR6ko"
    },
    {
      "type": "news",
      "title": "Protesters demand ICE agents leave Philadelphia International Airport: \"The solution is to pay TSA\"",
      "date": "2026-04-08T16:54:10.777965Z",
      "sourceUrl": "https://www.cbsnews.com/philadelphia/news/philadelphia-international-airport-ice-agents/"
    },
    {
      "type": "news",
      "title": "Fact Check: Post Does NOT Prove 'No Kings' Rallies Participants Were Paid To Join Protests on March 28, 2026",
      "date": "2026-04-08T15:03:53.999299Z",
      "sourceUrl": "https://www.yahoo.com/news/articles/fact-check-post-does-not-013540503.html"
    },
    {
      "type": "news",
      "title": "Nevada Gov. Joe Lombardo says anti-Trump protesters were paid, don't want to work",
      "date": "2026-04-08T15:03:53.999299Z",
      "sourceUrl": "https://www.msn.com/en-us/news/other/nevada-gov-joe-lombardo-says-anti-trump-protesters-were-paid-don-t-want-to-work/ar-AA1CHlgC"
    },
    {
      "type": "news",
      "title": "Ad appears to seek 'paid' protesters for No Kings demonstration",
      "date": "2026-04-08T15:03:53.999299Z",
      "sourceUrl": "https://www.msn.com/en-us/news/us/ad-appears-to-seek-paid-protesters-for-no-kings-demonstration/vi-AA1ZC3dg"
    },
    {
      "type": "news",
      "title": "Joe Rogan Raises Eyebrows for Claiming ICE Protests Are 'Paid for and Organized' as Famous Podcaster Confronts RFK Jr. Over 'Very Disturbing' Raids",
      "date": "2026-04-08T13:06:25.431578Z",
      "sourceUrl": "https://www.aol.com/joe-rogan-raises-eyebrows-claiming-184500387.html"
    },
    {
      "type": "news",
      "title": "'Beautiful printed signs': Trump tries to use protest signs as evidence that protesters are 'paid people' in unconvincing remarks",
      "date": "2026-04-08T13:06:25.431578Z",
      "sourceUrl": "https://www.msn.com/en-us/news/opinion/beautiful-printed-signs-trump-tries-to-use-protest-signs-as-evidence-that-protesters-are-paid-people-in-unconvincing-remarks/vi-AA1ZR6ko"
    },
    {
      "type": "news",
      "title": "Joe Rogan Raises Eyebrows for Claiming ICE Protests Are 'Paid for and Organized' as Famous Podcaster Confronts RFK Jr. Over 'Very Disturbing' Raids",
      "date": "2026-04-08T13:06:25.431578Z",
      "sourceUrl": "https://www.aol.com/entertainment/joe-rogan-raises-eyebrows-claiming-184500387.html"
    },
    {
      "type": "news",
      "title": "Joe Rogan Raises Eyebrows for Claiming ICE Protests Are 'Paid for and Organized' as Famous Podcaster Confronts RFK Jr. Over 'Very Disturbing' Raids",
      "date": "2026-04-08T11:48:24.593122Z",
      "sourceUrl": "https://www.aol.com/entertainment/joe-rogan-raises-eyebrows-claiming-184500387.html"
    },
    {
      "type": "news",
      "title": "The brazen ad for rent-a-crowd protesters to attend anti-Israel rally in Melbourne",
      "date": "2026-04-08T11:48:24.593122Z",
      "sourceUrl": "https://www.msn.com/en-in/news/other/the-brazen-ad-for-rent-a-crowd-protesters-to-attend-anti-israel-rally-in-melbourne/ar-AA1WVqBb?ocid=BingNewsVerp"
    },
    {
      "type": "news",
      "title": "Is TSA back to normal? LGA, JFK, EWR TSA wait times today",
      "date": "2026-04-08T11:48:24.593122Z",
      "sourceUrl": "https://www.yahoo.com/news/articles/tsa-back-normal-lga-jfk-162125129.html"
    },
    {
      "type": "news",
      "title": "Joe Rogan Raises Eyebrows for Claiming ICE Protests Are 'Paid for and Organized' as Famous Podcaster Confronts RFK Jr. Over 'Very Disturbing' Raids",
      "date": "2026-04-08T10:02:16.065630Z",
      "sourceUrl": "https://www.aol.com/entertainment/joe-rogan-raises-eyebrows-claiming-184500387.html"
    },
    {
      "type": "news",
      "title": "The brazen ad for rent-a-crowd protesters to attend anti-Israel rally in Melbourne",
      "date": "2026-04-08T10:02:16.065630Z",
      "sourceUrl": "https://www.msn.com/en-in/news/other/the-brazen-ad-for-rent-a-crowd-protesters-to-attend-anti-israel-rally-in-melbourne/ar-AA1WVqBb?ocid=BingNewsVerp"
    },
    {
      "type": "news",
      "title": "Is TSA back to normal? LGA, JFK, EWR TSA wait times today",
      "date": "2026-04-08T10:02:16.065630Z",
      "sourceUrl": "https://www.yahoo.com/news/articles/tsa-back-normal-lga-jfk-162125129.html"
    },
    {
      "type": "news",
      "title": "Joe Rogan Raises Eyebrows for Claiming ICE Protests Are 'Paid for and Organized' as Famous Podcaster Confronts RFK Jr. Over 'Very Disturbing' Raids",
      "date": "2026-04-08T08:08:32.042754Z",
      "sourceUrl": "https://www.aol.com/entertainment/joe-rogan-raises-eyebrows-claiming-184500387.html"
    },
    {
      "type": "news",
      "title": "The brazen ad for rent-a-crowd protesters to attend anti-Israel rally in Melbourne",
      "date": "2026-04-08T08:08:32.042754Z",
      "sourceUrl": "https://www.msn.com/en-my/politics/government/the-brazen-ad-for-rent-a-crowd-protesters-to-attend-anti-israel-rally-in-melbourne/ar-AA1WVEmH?ocid=BingNewsVerp"
    },
    {
      "type": "news",
      "title": "Quiet GOP 'Astroturf' campaign convinced liberal firebrand to run for US Senate, source says",
      "date": "2026-04-08T08:08:32.042754Z",
      "sourceUrl": "https://www.aol.com/news/quiet-gop-astroturf-campaign-convinced-180028572.html"
    },
    {
      "type": "news",
      "title": "Joe Rogan Raises Eyebrows for Claiming ICE Protests Are 'Paid for and Organized' as Famous Podcaster Confronts RFK Jr. Over 'Very Disturbing' Raids",
      "date": "2026-04-08T06:17:45.173960Z",
      "sourceUrl": "https://www.aol.com/joe-rogan-raises-eyebrows-claiming-184500387.html"
    },
    {
      "type": "news",
      "title": "Ad appears to seek 'paid' protesters for No Kings demonstration",
      "date": "2026-04-08T06:17:45.173960Z",
      "sourceUrl": "https://www.msn.com/en-us/news/us/ad-appears-to-seek-paid-protesters-for-no-kings-demonstration/vi-AA1ZC3dg"
    },
    {
      "type": "news",
      "title": "Kurdish groups reject Trump claim they kept US guns meant for Iran protesters",
      "date": "2026-04-08T06:17:45.173960Z",
      "sourceUrl": "https://www.newsweek.com/kurds-deny-trump-claim-kept-us-guns-iran-protesters-11789392"
    },
    {
      "type": "news",
      "title": "Joe Rogan Raises Eyebrows for Claiming ICE Protests Are 'Paid for and Organized' as Famous Podcaster Confronts RFK Jr. Over 'Very Disturbing' Raids",
      "date": "2026-04-08T04:32:04.684967Z",
      "sourceUrl": "https://www.aol.com/entertainment/joe-rogan-raises-eyebrows-claiming-184500387.html"
    },
    {
      "type": "news",
      "title": "The brazen ad for rent-a-crowd protesters to attend anti-Israel rally in Melbourne",
      "date": "2026-04-08T04:32:04.684967Z",
      "sourceUrl": "https://www.msn.com/en-my/politics/government/the-brazen-ad-for-rent-a-crowd-protesters-to-attend-anti-israel-rally-in-melbourne/ar-AA1WVEmH?ocid=BingNewsVerp"
    },
    {
      "type": "news",
      "title": "Kurdish groups reject Trump claim they kept US guns meant for Iran protesters",
      "date": "2026-04-08T04:32:04.684967Z",
      "sourceUrl": "https://www.newsweek.com/kurds-deny-trump-claim-kept-us-guns-iran-protesters-11789392"
    },
    {
      "type": "news",
      "title": "Fact Check: Post Does NOT Prove 'No Kings' Rallies Participants Were Paid To Join Protests on March 28, 2026",
      "date": "2026-04-08T01:50:13.601749Z",
      "sourceUrl": "https://www.yahoo.com/news/articles/fact-check-post-does-not-013540503.html"
    },
    {
      "type": "news",
      "title": "Joe Rogan Raises Eyebrows for Claiming ICE Protests Are 'Paid for and Organized' as Famous Podcaster Confronts RFK Jr. Over 'Very Disturbing' Raids",
      "date": "2026-04-08T01:50:13.601749Z",
      "sourceUrl": "https://www.aol.com/joe-rogan-raises-eyebrows-claiming-184500387.html"
    },
    {
      "type": "news",
      "title": "'Beautiful printed signs': Trump tries to use protest signs as evidence that protesters are 'paid people' in unconvincing remarks",
      "date": "2026-04-08T01:50:13.601749Z",
      "sourceUrl": "https://www.msn.com/en-us/news/opinion/beautiful-printed-signs-trump-tries-to-use-protest-signs-as-evidence-that-protesters-are-paid-people-in-unconvincing-remarks/vi-AA1ZR6ko"
    },
    {
      "type": "news",
      "title": "Fact Check: Post Does NOT Prove 'No Kings' Rallies Participants Were Paid To Join Protests on March 28, 2026",
      "date": "2026-04-07T23:31:32.746675Z",
      "sourceUrl": "https://www.yahoo.com/news/articles/fact-check-post-does-not-013540503.html"
    },
    {
      "type": "news",
      "title": "Joe Rogan Raises Eyebrows for Claiming ICE Protests Are 'Paid for and Organized' as Famous Podcaster Confronts RFK Jr. Over 'Very Disturbing' Raids",
      "date": "2026-04-07T23:31:32.746675Z",
      "sourceUrl": "https://www.aol.com/joe-rogan-raises-eyebrows-claiming-184500387.html"
    },
    {
      "type": "news",
      "title": "Joe Rogan Raises Eyebrows for Claiming ICE Protests Are 'Paid for and Organized' as Famous Podcaster Confronts RFK Jr. Over 'Very Disturbing' Raids",
      "date": "2026-04-07T23:31:32.746675Z",
      "sourceUrl": "https://www.aol.com/entertainment/joe-rogan-raises-eyebrows-claiming-184500387.html"
    },
    {
      "type": "news",
      "title": "Joe Rogan Raises Eyebrows for Claiming ICE Protests Are 'Paid for and Organized' as Famous Podcaster Confronts RFK Jr. Over 'Very Disturbing' Raids",
      "date": "2026-04-07T22:31:42.516152Z",
      "sourceUrl": "https://www.aol.com/entertainment/joe-rogan-raises-eyebrows-claiming-184500387.html"
    },
    {
      "type": "news",
      "title": "The brazen ad for rent-a-crowd protesters to attend anti-Israel rally in Melbourne",
      "date": "2026-04-07T22:31:42.516152Z",
      "sourceUrl": "https://www.msn.com/en-my/politics/government/the-brazen-ad-for-rent-a-crowd-protesters-to-attend-anti-israel-rally-in-melbourne/ar-AA1WVEmH?ocid=BingNewsVerp"
    },
    {
      "type": "news",
      "title": "Fact Check: Post Does NOT Prove 'No Kings' Rallies Participants Were Paid To Join Protests on March 28, 2026",
      "date": "2026-04-07T22:31:42.516152Z",
      "sourceUrl": "https://www.yahoo.com/news/articles/fact-check-post-does-not-013540503.html"
    },
    {
      "type": "news",
      "title": "Fact Check: Post Does NOT Prove 'No Kings' Rallies Participants Were Paid To Join Protests on March 28, 2026",
      "date": "2026-04-07T21:36:59.936072Z",
      "sourceUrl": "https://www.yahoo.com/news/articles/fact-check-post-does-not-013540503.html"
    },
    {
      "type": "news",
      "title": "Joe Rogan Raises Eyebrows for Claiming ICE Protests Are 'Paid for and Organized' as Famous Podcaster Confronts RFK Jr. Over 'Very Disturbing' Raids",
      "date": "2026-04-07T21:36:59.936072Z",
      "sourceUrl": "https://www.aol.com/joe-rogan-raises-eyebrows-claiming-184500387.html"
    },
    {
      "type": "news",
      "title": "'Beautiful printed signs': Trump tries to use protest signs as evidence that protesters are 'paid people' in unconvincing remarks",
      "date": "2026-04-07T21:36:59.936072Z",
      "sourceUrl": "https://www.msn.com/en-us/news/opinion/beautiful-printed-signs-trump-tries-to-use-protest-signs-as-evidence-that-protesters-are-paid-people-in-unconvincing-remarks/vi-AA1ZR6ko"
    },
    {
      "type": "news",
      "title": "Joe Rogan Raises Eyebrows for Claiming ICE Protests Are 'Paid for and Organized' as Famous Podcaster Confronts RFK Jr. Over 'Very Disturbing' Raids",
      "date": "2026-04-07T20:39:43.956705Z",
      "sourceUrl": "https://www.aol.com/entertainment/joe-rogan-raises-eyebrows-claiming-184500387.html"
    },
    {
      "type": "news",
      "title": "The brazen ad for rent-a-crowd protesters to attend anti-Israel rally in Melbourne",
      "date": "2026-04-07T20:39:43.956705Z",
      "sourceUrl": "https://www.msn.com/en-us/news/other/the-brazen-ad-for-rent-a-crowd-protesters-to-attend-anti-israel-rally-in-melbourne/ar-AA1WVqrt?ocid=BingNewsVerp"
    },
    {
      "type": "news",
      "title": "AstroTurf Brings Young Baseball Fans to 2025 World Series Through Community Initiative",
      "date": "2026-04-07T20:39:43.956705Z",
      "sourceUrl": "https://signalscv.com/2025/11/astroturf-brings-young-baseball-fans-to-2025-world-series-through-community-initiative/"
    },
    {
      "type": "news",
      "title": "The brazen ad for rent-a-crowd protesters to attend anti-Israel rally in Melbourne",
      "date": "2026-04-07T19:53:40.551620Z",
      "sourceUrl": "https://www.msn.com/en-my/politics/government/the-brazen-ad-for-rent-a-crowd-protesters-to-attend-anti-israel-rally-in-melbourne/ar-AA1WVEmH?ocid=BingNewsVerp"
    },
    {
      "type": "news",
      "title": "Ad appears to seek 'paid' protesters for No Kings demonstration",
      "date": "2026-04-07T19:53:40.551620Z",
      "sourceUrl": "https://www.msn.com/en-us/news/other/ad-appears-to-seek-paid-protesters-for-no-kings-demonstration/vi-AA1ZC3dg?ocid=BingNewsVerp"
    },
    {
      "type": "news",
      "title": "Quiet GOP 'Astroturf' campaign convinced liberal firebrand to run for US Senate, source says",
      "date": "2026-04-07T19:53:40.551620Z",
      "sourceUrl": "https://www.aol.com/news/quiet-gop-astroturf-campaign-convinced-180028572.html"
    },
    {
      "type": "news",
      "title": "Joe Rogan Raises Eyebrows for Claiming ICE Protests Are 'Paid for and Organized' as Famous Podcaster Confronts RFK Jr. Over 'Very Disturbing' Raids",
      "date": "2026-04-07T18:54:37.150662Z",
      "sourceUrl": "https://www.aol.com/joe-rogan-raises-eyebrows-claiming-184500387.html"
    },
    {
      "type": "news",
      "title": "The brazen ad for rent-a-crowd protesters to attend anti-Israel rally in Melbourne",
      "date": "2026-04-07T18:54:37.150662Z",
      "sourceUrl": "https://www.msn.com/en-in/news/other/the-brazen-ad-for-rent-a-crowd-protesters-to-attend-anti-israel-rally-in-melbourne/ar-AA1WVqBb?ocid=BingNewsVerp"
    },
    {
      "type": "news",
      "title": "Ad appears to seek 'paid' protesters for No Kings demonstration",
      "date": "2026-04-07T18:54:37.150662Z",
      "sourceUrl": "https://www.msn.com/en-us/news/us/ad-appears-to-seek-paid-protesters-for-no-kings-demonstration/vi-AA1ZC3dg"
    },
    {
      "type": "news",
      "title": "Joe Rogan Raises Eyebrows for Claiming ICE Protests Are 'Paid for and Organized' as Famous Podcaster Confronts RFK Jr. Over 'Very Disturbing' Raids",
      "date": "2026-04-07T17:53:02.919882Z",
      "sourceUrl": "https://www.aol.com/entertainment/joe-rogan-raises-eyebrows-claiming-184500387.html"
    },
    {
      "type": "news",
      "title": "The brazen ad for rent-a-crowd protesters to attend anti-Israel rally in Melbourne",
      "date": "2026-04-07T17:53:02.919882Z",
      "sourceUrl": "https://www.msn.com/en-us/news/other/the-brazen-ad-for-rent-a-crowd-protesters-to-attend-anti-israel-rally-in-melbourne/ar-AA1WVqrt?ocid=BingNewsVerp"
    },
    {
      "type": "news",
      "title": "Quiet GOP 'Astroturf' campaign convinced liberal firebrand to run for US Senate, source says",
      "date": "2026-04-07T17:53:02.919882Z",
      "sourceUrl": "https://www.aol.com/news/quiet-gop-astroturf-campaign-convinced-180028572.html"
    },
    {
      "type": "news",
      "title": "The brazen ad for rent-a-crowd protesters to attend anti-Israel rally in Melbourne",
      "date": "2026-04-07T16:49:08.236004Z",
      "sourceUrl": "https://www.msn.com/en-in/news/other/the-brazen-ad-for-rent-a-crowd-protesters-to-attend-anti-israel-rally-in-melbourne/ar-AA1WVqBb?ocid=BingNewsVerp"
    },
    {
      "type": "news",
      "title": "Ad appears to seek 'paid' protesters for No Kings demonstration",
      "date": "2026-04-07T16:49:08.236004Z",
      "sourceUrl": "https://www.msn.com/en-us/news/other/ad-appears-to-seek-paid-protesters-for-no-kings-demonstration/vi-AA1ZC3dg?ocid=BingNewsVerp"
    },
    {
      "type": "news",
      "title": "Quiet GOP 'Astroturf' campaign convinced liberal firebrand to run for US Senate, source says",
      "date": "2026-04-07T16:49:08.236004Z",
      "sourceUrl": "https://www.aol.com/news/quiet-gop-astroturf-campaign-convinced-180028572.html"
    },
    {
      "type": "news",
      "title": "The brazen ad for rent-a-crowd protesters to attend anti-Israel rally in Melbourne",
      "date": "2026-04-07T15:01:48.784462Z",
      "sourceUrl": "https://www.msn.com/en-my/politics/government/the-brazen-ad-for-rent-a-crowd-protesters-to-attend-anti-israel-rally-in-melbourne/ar-AA1WVEmH?ocid=BingNewsVerp"
    },
    {
      "type": "news",
      "title": "Joe Rogan Raises Eyebrows for Claiming ICE Protests Are 'Paid for and Organized' as Famous Podcaster Confronts RFK Jr. Over 'Very Disturbing' Raids",
      "date": "2026-04-07T15:01:48.784462Z",
      "sourceUrl": "https://www.aol.com/joe-rogan-raises-eyebrows-claiming-184500387.html"
    },
    {
      "type": "news",
      "title": "'Beautiful printed signs': Trump tries to use protest signs as evidence that protesters are 'paid people' in unconvincing remarks",
      "date": "2026-04-07T15:01:48.784462Z",
      "sourceUrl": "https://www.msn.com/en-us/news/opinion/beautiful-printed-signs-trump-tries-to-use-protest-signs-as-evidence-that-protesters-are-paid-people-in-unconvincing-remarks/vi-AA1ZR6ko"
    },
    {
      "type": "news",
      "title": "Nevada Gov. Joe Lombardo says anti-Trump protesters were paid, don't want to work",
      "date": "2026-04-07T13:05:09.602827Z",
      "sourceUrl": "https://www.msn.com/en-us/news/politics/nevada-gov-joe-lombardo-says-anti-trump-protesters-were-paid-dont-want-to-work/ar-AA1CHlgC"
    },
    {
      "type": "news",
      "title": "Joe Rogan Raises Eyebrows for Claiming ICE Protests Are 'Paid for and Organized' as Famous Podcaster Confronts RFK Jr. Over 'Very Disturbing' Raids",
      "date": "2026-04-07T13:05:09.602827Z",
      "sourceUrl": "https://www.aol.com/joe-rogan-raises-eyebrows-claiming-184500387.html"
    },
    {
      "type": "news",
      "title": "Ad appears to seek 'paid' protesters for No Kings demonstration",
      "date": "2026-04-07T13:05:09.602827Z",
      "sourceUrl": "https://www.msn.com/en-us/news/us/ad-appears-to-seek-paid-protesters-for-no-kings-demonstration/vi-AA1ZC3dg"
    },
    {
      "type": "news",
      "title": "Joe Rogan Raises Eyebrows for Claiming ICE Protests Are 'Paid for and Organized' as Famous Podcaster Confronts RFK Jr. Over 'Very Disturbing' Raids",
      "date": "2026-04-07T11:47:20.127812Z",
      "sourceUrl": "https://www.aol.com/entertainment/joe-rogan-raises-eyebrows-claiming-184500387.html"
    },
    {
      "type": "news",
      "title": "The brazen ad for rent-a-crowd protesters to attend anti-Israel rally in Melbourne",
      "date": "2026-04-07T11:47:20.127812Z",
      "sourceUrl": "https://www.msn.com/en-my/politics/government/the-brazen-ad-for-rent-a-crowd-protesters-to-attend-anti-israel-rally-in-melbourne/ar-AA1WVEmH?ocid=BingNewsVerp"
    },
    {
      "type": "news",
      "title": "Nevada Gov. Joe Lombardo says anti-Trump protesters were paid, don't want to work",
      "date": "2026-04-07T11:47:20.127812Z",
      "sourceUrl": "https://www.msn.com/en-us/news/politics/nevada-gov-joe-lombardo-says-anti-trump-protesters-were-paid-dont-want-to-work/ar-AA1CHlgC"
    },
    {
      "type": "news",
      "title": "Fact Check: Post Does NOT Prove 'No Kings' Rallies Participants Were Paid To Join Protests on March 28, 2026",
      "date": "2026-04-07T10:02:29.314891Z",
      "sourceUrl": "https://www.yahoo.com/news/articles/fact-check-post-does-not-013540503.html"
    },
    {
      "type": "news",
      "title": "'Beautiful printed signs': Trump tries to use protest signs as evidence that protesters are 'paid people' in unconvincing remarks",
      "date": "2026-04-07T10:02:29.314891Z",
      "sourceUrl": "https://www.msn.com/en-us/news/opinion/beautiful-printed-signs-trump-tries-to-use-protest-signs-as-evidence-that-protesters-are-paid-people-in-unconvincing-remarks/vi-AA1ZR6ko"
    },
    {
      "type": "news",
      "title": "The brazen ad for rent-a-crowd protesters to attend anti-Israel rally in Melbourne",
      "date": "2026-04-07T10:02:29.314891Z",
      "sourceUrl": "https://www.msn.com/en-us/news/other/the-brazen-ad-for-rent-a-crowd-protesters-to-attend-anti-israel-rally-in-melbourne/ar-AA1WVqrt?ocid=BingNewsVerp"
    },
    {
      "type": "news",
      "title": "Fact Check: Post Does NOT Prove 'No Kings' Rallies Participants Were Paid To Join Protests on March 28, 2026",
      "date": "2026-04-07T08:07:50.702902Z",
      "sourceUrl": "https://www.yahoo.com/news/articles/fact-check-post-does-not-013540503.html"
    },
    {
      "type": "news",
      "title": "Joe Rogan Raises Eyebrows for Claiming ICE Protests Are 'Paid for and Organized' as Famous Podcaster Confronts RFK Jr. Over 'Very Disturbing' Raids",
      "date": "2026-04-07T08:07:50.702902Z",
      "sourceUrl": "https://www.aol.com/joe-rogan-raises-eyebrows-claiming-184500387.html"
    },
    {
      "type": "news",
      "title": "'Beautiful printed signs': Trump tries to use protest signs as evidence that protesters are 'paid people' in unconvincing remarks",
      "date": "2026-04-07T08:07:50.702902Z",
      "sourceUrl": "https://www.msn.com/en-us/news/opinion/beautiful-printed-signs-trump-tries-to-use-protest-signs-as-evidence-that-protesters-are-paid-people-in-unconvincing-remarks/vi-AA1ZR6ko"
    },
    {
      "type": "news",
      "title": "Joe Rogan Raises Eyebrows for Claiming ICE Protests Are 'Paid for and Organized' as Famous Podcaster Confronts RFK Jr. Over 'Very Disturbing' Raids",
      "date": "2026-04-07T06:15:46.325028Z",
      "sourceUrl": "https://www.aol.com/entertainment/joe-rogan-raises-eyebrows-claiming-184500387.html"
    },
    {
      "type": "news",
      "title": "The brazen ad for rent-a-crowd protesters to attend anti-Israel rally in Melbourne",
      "date": "2026-04-07T06:15:46.325028Z",
      "sourceUrl": "https://www.msn.com/en-my/politics/government/the-brazen-ad-for-rent-a-crowd-protesters-to-attend-anti-israel-rally-in-melbourne/ar-AA1WVEmH?ocid=BingNewsVerp"
    },
    {
      "type": "news",
      "title": "Kurdish groups reject Trump claim they kept US guns meant for Iran protesters",
      "date": "2026-04-07T06:15:46.325028Z",
      "sourceUrl": "https://www.newsweek.com/kurds-deny-trump-claim-kept-us-guns-iran-protesters-11789392"
    },
    {
      "type": "news",
      "title": "The brazen ad for rent-a-crowd protesters to attend anti-Israel rally in Melbourne",
      "date": "2026-04-07T04:28:53.630851Z",
      "sourceUrl": "https://www.msn.com/en-us/news/other/the-brazen-ad-for-rent-a-crowd-protesters-to-attend-anti-israel-rally-in-melbourne/ar-AA1WVqrt?ocid=BingNewsVerp"
    },
    {
      "type": "news",
      "title": "Joe Rogan Raises Eyebrows for Claiming ICE Protests Are 'Paid for and Organized' as Famous Podcaster Confronts RFK Jr. Over 'Very Disturbing' Raids",
      "date": "2026-04-07T04:28:53.630851Z",
      "sourceUrl": "https://www.aol.com/entertainment/joe-rogan-raises-eyebrows-claiming-184500387.html"
    },
    {
      "type": "news",
      "title": "AOC enjoys Yankees game from suite as thousands of federal workers go unpaid due to shutdown",
      "date": "2026-04-07T04:28:53.630851Z",
      "sourceUrl": "https://nypost.com/2026/04/06/us-news/aoc-enjoys-yankees-game-from-suite-during-shutdown/"
    },
    {
      "type": "news",
      "title": "Verify: Rep. Tim Burchett claims protesters in Minneapolis are 'paid'",
      "date": "2026-04-07T01:49:50.706664Z",
      "sourceUrl": "https://www.msn.com/en-us/politics/government/verify-rep-tim-burchett-claims-protesters-in-minneapolis-are-paid/ar-AA1V4qBW?ocid=BingNewsVerp"
    },
    {
      "type": "news",
      "title": "The brazen ad for rent-a-crowd protesters to attend anti-Israel rally in Melbourne",
      "date": "2026-04-07T01:49:50.706664Z",
      "sourceUrl": "https://www.msn.com/en-us/news/other/the-brazen-ad-for-rent-a-crowd-protesters-to-attend-anti-israel-rally-in-melbourne/ar-AA1WVqrt?ocid=BingNewsVerp"
    },
    {
      "type": "news",
      "title": "Joe Rogan Raises Eyebrows for Claiming ICE Protests Are 'Paid for and Organized' as Famous Podcaster Confronts RFK Jr. Over 'Very Disturbing' Raids",
      "date": "2026-04-07T01:49:50.706664Z",
      "sourceUrl": "https://www.aol.com/entertainment/joe-rogan-raises-eyebrows-claiming-184500387.html"
    },
    {
      "type": "news",
      "title": "Verify: Rep. Tim Burchett claims protesters in Minneapolis are 'paid'",
      "date": "2026-04-06T23:28:59.450734Z",
      "sourceUrl": "https://www.msn.com/en-us/politics/government/verify-rep-tim-burchett-claims-protesters-in-minneapolis-are-paid/ar-AA1V4qBW?ocid=BingNewsVerp"
    },
    {
      "type": "news",
      "title": "The brazen ad for rent-a-crowd protesters to attend anti-Israel rally in Melbourne",
      "date": "2026-04-06T23:28:59.450734Z",
      "sourceUrl": "https://www.msn.com/en-us/news/other/the-brazen-ad-for-rent-a-crowd-protesters-to-attend-anti-israel-rally-in-melbourne/ar-AA1WVqrt?ocid=BingNewsVerp"
    },
    {
      "type": "news",
      "title": "Joe Rogan Raises Eyebrows for Claiming ICE Protests Are 'Paid for and Organized' as Famous Podcaster Confronts RFK Jr. Over 'Very Disturbing' Raids",
      "date": "2026-04-06T23:28:59.450734Z",
      "sourceUrl": "https://www.aol.com/entertainment/joe-rogan-raises-eyebrows-claiming-184500387.html"
    },
    {
      "type": "news",
      "title": "Joe Rogan Raises Eyebrows for Claiming ICE Protests Are 'Paid for and Organized' as Famous Podcaster Confronts RFK Jr. Over 'Very Disturbing' Raids",
      "date": "2026-04-06T22:29:03.726077Z",
      "sourceUrl": "https://www.aol.com/joe-rogan-raises-eyebrows-claiming-184500387.html"
    },
    {
      "type": "news",
      "title": "'Beautiful printed signs': Trump tries to use protest signs as evidence that protesters are 'paid people' in unconvincing remarks",
      "date": "2026-04-06T22:29:03.726077Z",
      "sourceUrl": "https://www.msn.com/en-us/news/opinion/beautiful-printed-signs-trump-tries-to-use-protest-signs-as-evidence-that-protesters-are-paid-people-in-unconvincing-remarks/vi-AA1ZR6ko"
    },
    {
      "type": "news",
      "title": "Ad appears to seek 'paid' protesters for No Kings demonstration",
      "date": "2026-04-06T22:29:03.726077Z",
      "sourceUrl": "https://www.msn.com/en-us/news/us/ad-appears-to-seek-paid-protesters-for-no-kings-demonstration/vi-AA1ZC3dg"
    },
    {
      "type": "news",
      "title": "Fact Check: Post Does NOT Prove 'No Kings' Rallies Participants Were Paid To Join Protests on March 28, 2026",
      "date": "2026-04-06T21:32:10.454621Z",
      "sourceUrl": "https://www.yahoo.com/news/articles/fact-check-post-does-not-013540503.html"
    },
    {
      "type": "news",
      "title": "Joe Rogan Raises Eyebrows for Claiming ICE Protests Are 'Paid for and Organized' as Famous Podcaster Confronts RFK Jr. Over 'Very Disturbing' Raids",
      "date": "2026-04-06T21:32:10.454621Z",
      "sourceUrl": "https://www.aol.com/joe-rogan-raises-eyebrows-claiming-184500387.html"
    },
    {
      "type": "news",
      "title": "'No Kings' protests draw massive crowds across US; some protesters detained in LA",
      "date": "2026-04-06T21:32:10.454621Z",
      "sourceUrl": "https://www.dispatch.com/story/news/nation/2026/03/28/no-kings-protest-live-updates--live/89186293007/"
    },
    {
      "type": "news",
      "title": "Fact Check: Post Does NOT Prove 'No Kings' Rallies Participants Were Paid To Join Protests on March 28, 2026",
      "date": "2026-04-06T20:31:46.140818Z",
      "sourceUrl": "https://www.yahoo.com/news/articles/fact-check-post-does-not-013540503.html"
    },
    {
      "type": "news",
      "title": "'No Kings' protests draw massive crowds across US; some protesters detained in LA",
      "date": "2026-04-06T20:31:46.140818Z",
      "sourceUrl": "https://www.dispatch.com/story/news/nation/2026/03/28/no-kings-protest-live-updates--live/89186293007/"
    },
    {
      "type": "news",
      "title": "'Beautiful printed signs': Trump tries to use protest signs as evidence that protesters are 'paid people' in unconvincing remarks",
      "date": "2026-04-06T20:31:46.140818Z",
      "sourceUrl": "https://www.msn.com/en-us/news/opinion/beautiful-printed-signs-trump-tries-to-use-protest-signs-as-evidence-that-protesters-are-paid-people-in-unconvincing-remarks/vi-AA1ZR6ko"
    },
    {
      "type": "news",
      "title": "Fact Check: Post Does NOT Prove 'No Kings' Rallies Participants Were Paid To Join Protests on March...",
      "date": "2026-04-06T19:47:45.984449Z",
      "sourceUrl": "https://www.yahoo.com/news/articles/fact-check-post-does-not-013540503.html"
    },
    {
      "type": "news",
      "title": "Verify: Rep. Tim Burchett claims protesters in Minneapolis are 'paid'",
      "date": "2026-04-06T19:47:45.984449Z",
      "sourceUrl": "https://www.msn.com/en-us/politics/government/verify-rep-tim-burchett-claims-protesters-in-minneapolis-are-paid/ar-AA1V4qBW?ocid=BingNewsVerp"
    },
    {
      "type": "news",
      "title": "The brazen ad for rent-a-crowd protesters to attend anti-Israel rally in Melbourne",
      "date": "2026-04-06T19:47:45.984449Z",
      "sourceUrl": "https://www.msn.com/en-us/news/other/the-brazen-ad-for-rent-a-crowd-protesters-to-attend-anti-israel-rally-in-melbourne/ar-AA1WVqrt?ocid=BingNewsVerp"
    },
    {
      "type": "news",
      "title": "Fact Check: Post Does NOT Prove 'No Kings' Rallies Participants Were Paid To Join Protests on March 28, 2026",
      "date": "2026-04-06T18:47:30.425256Z",
      "sourceUrl": "https://www.yahoo.com/news/articles/fact-check-post-does-not-013540503.html"
    },
    {
      "type": "news",
      "title": "Joe Rogan Raises Eyebrows for Claiming ICE Protests Are 'Paid for and Organized' as Famous Podcaster Confronts RFK Jr. Over 'Very Disturbing' Raids",
      "date": "2026-04-06T18:47:30.425256Z",
      "sourceUrl": "https://www.aol.com/joe-rogan-raises-eyebrows-claiming-184500387.html"
    },
    {
      "type": "news",
      "title": "'Beautiful printed signs': Trump tries to use protest signs as evidence that protesters are 'paid people' in unconvincing remarks",
      "date": "2026-04-06T18:47:30.425256Z",
      "sourceUrl": "https://www.msn.com/en-us/news/opinion/beautiful-printed-signs-trump-tries-to-use-protest-signs-as-evidence-that-protesters-are-paid-people-in-unconvincing-remarks/vi-AA1ZR6ko"
    },
    {
      "type": "news",
      "title": "The brazen ad for rent-a-crowd protesters to attend anti-Israel rally in Melbourne",
      "date": "2026-04-06T17:38:55.227854Z",
      "sourceUrl": "https://www.msn.com/en-us/news/other/the-brazen-ad-for-rent-a-crowd-protesters-to-attend-anti-israel-rally-in-melbourne/ar-AA1WVqrt?ocid=BingNewsVerp"
    },
    {
      "type": "news",
      "title": "Joe Rogan Raises Eyebrows for Claiming ICE Protests Are 'Paid for and Organized' as Famous Podcaster Confronts RFK Jr. Over 'Very Disturbing' Raids",
      "date": "2026-04-06T17:38:55.227854Z",
      "sourceUrl": "https://www.aol.com/entertainment/joe-rogan-raises-eyebrows-claiming-184500387.html"
    },
    {
      "type": "news",
      "title": "Fact Check: Post Does NOT Prove 'No Kings' Rallies Participants Were Paid To Join Protests on March...",
      "date": "2026-04-06T17:38:55.227854Z",
      "sourceUrl": "https://www.yahoo.com/news/articles/fact-check-post-does-not-013540503.html"
    },
    {
      "type": "news",
      "title": "Fact Check: Post Does NOT Prove 'No Kings' Rallies Participants Were Paid To Join Protests on March...",
      "date": "2026-04-06T16:39:02.575971Z",
      "sourceUrl": "https://www.yahoo.com/news/articles/fact-check-post-does-not-013540503.html"
    }
  ],
  "recentNews": [
    {
      "type": "news",
      "source": "google_news",
      "title": "Astroturfing: Understanding and Addressing the Influence of Fake Grassroots Movements Across Diverse Domains on Social Media Platforms - springerprofessional.de",
      "url": "https://news.google.com/rss/articles/CBMisgFBVV95cUxNUGtWSVFHXzN4RFhsRE5URk1OLUk0TEVONDhKUzhpdWNLZVpuRzZaOUF6d1EwQ0s3MWxwanY3Y2lVbm1fM3RtNVBrVURLczViVUdtQmVyMVk4U2RJWWJGR0l1VXpNRXR3SW1xcER6a2J6NTJKdnVIYmdqVHktal9KM0RZV1ZYZ1V5bFgxYTNtdlJtQXJPdHlLVFNSTG15T3AzYUM4WlhzTjdsbnlXNm15Yi1B?oc=5",
      "date": "2025-08-01T11:42:20Z",
      "publisher": "springerprofessional.de",
      "query": "fake grassroots",
      "relevance_score": 90,
      "location": ""
    },
    {
      "type": "news",
      "source": "google_news",
      "title": "What political ads are Australians seeing online? Astroturfing, fake grassroots groups, and outright falsehoods - The Conversation",
      "url": "https://news.google.com/rss/articles/CBMi2wFBVV95cUxPYmhmX1ZCSFFLYkxnbUljVWpsR0EtcVNfRVdjZ2NlN0FWdnQ3YmYwTUc1WXNSLXVCUDJRN3Z6anZXV0FfNlNTNktqZ3BvbkN2bWFNdk9KX3FFSWlCNS1HVlZsQXdKeUxhM2VEQTZSMzF3SWloV3Rubk1OR3loYk9WcFRpS2FmeFF5aDlGS2pzMDB4b3JpVF9QbzlFQ3ljVHVFMjFkMTJwbVhWNGdTNktsMTUzazNqbGZSTXpHdDlNeGdBOHlBSUFCOFE3MVZueEhDY08wTDZsWWdIRjg?oc=5",
      "date": "2025-04-27T07:00:00Z",
      "publisher": "The Conversation",
      "query": "fake grassroots",
      "relevance_score": 90,
      "location": ""
    },
    {
      "title": "Kenyan authorities paid trolls to threaten Gen Z protesters, Amnesty says",
      "url": "https://www.msn.com/en-us/news/world/kenyan-authorities-paid-trolls-to-threaten-gen-z-protesters-amnesty-says/ar-AA1QK7z1?ocid=BingNewsVerp",
      "snippet": "The Kenyan authorities paid a network of trolls to threaten and intimidate young protesters during recent anti-government demonstrations, Amnesty International has said. A new report by the human ...",
      "publisher": "MSN",
      "source": "duckduckgo",
      "query": "paid protesters",
      "date": "2025-11-19T00:00:00+00:00",
      "relevance_score": 90,
      "collected_at": "2026-01-10T01:21:18.722473Z"
    },
    {
      "title": "Masked agitator tells Laura Ingraham she's 'getting paid right now' at anti-ICE protest",
      "url": "https://www.msn.com/en-us/news/us/masked-agitator-tells-laura-ingraham-she-s-getting-paid-right-now-at-anti-ice-protest/ar-AA1TUzeF",
      "snippet": "Protester says she's 'getting paid right now' during exchange with Fox News host at Minneapolis anti-ICE demonstrations after a deadly shooting involving a federal agent.",
      "publisher": "Fox News",
      "source": "duckduckgo",
      "query": "paid protesters",
      "date": "2026-01-09T20:10:00+00:00",
      "relevance_score": 90,
      "collected_at": "2026-01-10T15:13:50.667635Z"
    },
    {
      "title": "Paid protest CEO urges Congress to pass law exposing who funds demonstrations",
      "url": "https://www.msn.com/en-us/politics/government/paid-protest-ceo-urges-congress-to-pass-law-exposing-who-funds-demonstrations/ar-AA1QhM7J",
      "snippet": "(NewsNation) \u2014 The CEO of a company that provides paid protesters for events is asking members of Congress to pass a \"Transparency in Political Demonstration Act\" that would expose the groups hiring demonstrators to attend events around the U.S. Adam ...",
      "publisher": "MSN",
      "source": "duckduckgo",
      "query": "paid protesters",
      "date": "2025-11-12T12:30:00+00:00",
      "relevance_score": 90,
      "collected_at": "2026-01-10T19:11:12.300746Z"
    },
    {
      "title": "Masked agitator tells Laura Ingraham she's 'getting paid right now' at anti-ICE protest",
      "url": "https://www.foxnews.com/media/masked-agitator-tells-laura-ingraham-shes-getting-paid-right-now-during-anti-ice-protest",
      "snippet": "Protester says she's 'getting paid right now' during exchange with Fox News host at Minneapolis anti-ICE demonstrations after a deadly shooting involving a federal agent.",
      "publisher": "Fox News",
      "source": "duckduckgo",
      "query": "paid protesters",
      "date": "2026-01-09T20:10:00+00:00",
      "relevance_score": 90,
      "collected_at": "2026-01-12T09:26:09.060233Z"
    },
    {
      "title": "Paid protest CEO urges Congress to pass law exposing who funds demonstrations",
      "url": "https://www.msn.com/en-us/politics/government/paid-protest-ceo-urges-congress-to-pass-law-exposing-who-funds-demonstrations/ar-AA1QhM7J?ocid=BingNewsVerp",
      "snippet": "(NewsNation) \u2014 The CEO of a company that provides paid protesters for events is asking members of Congress to pass a \u201cTransparency in Political Demonstration Act\u201d that would expose the groups hiring ...",
      "publisher": "MSN",
      "source": "duckduckgo",
      "query": "paid protesters",
      "date": "2025-11-12T00:00:00+00:00",
      "relevance_score": 90,
      "collected_at": "2026-01-13T08:22:00.645271Z"
    },
    {
      "title": "'They Use Serious Hammers': Trump Discredits Himself When He Tries To Prove The Existence Of 'Paid' Protesters In Oval Office Rant",
      "url": "https://www.msn.com/en-us/video/weather/they-use-serious-hammers-trump-discredits-himself-when-he-tries-to-prove-the-existence-of-paid-protesters-in-oval-office-rant/vi-AA1Rgx4R?ocid=BingNewsVerp",
      "snippet": "Donald Trump signed a memorandum to deploy troops in Memphis several weeks ago from the Oval Office. During Q&A with the press, Trump tried to prove that protesters in cities are paid and part of some ...",
      "publisher": "MSN",
      "source": "duckduckgo",
      "query": "paid protesters",
      "date": "2025-11-27T00:00:00+00:00",
      "relevance_score": 90,
      "collected_at": "2026-01-13T08:22:00.645281Z"
    },
    {
      "title": "New Milford residents angry official alleged \u2018No Kings' protesters were paid",
      "url": "https://www.msn.com/en-us/politics/government/new-milford-residents-angry-official-alleged-no-kings-protesters-were-paid/ar-AA1PyAdK?ocid=BingNewsVerp",
      "snippet": "NEW MILFORD \u2013 Area residents who participated in the recent \"No Kings\" protest recently voiced their disappointment at a Town Council member's comments that claimed they were \"paid\" to protest. More ...",
      "publisher": "MSN",
      "source": "duckduckgo",
      "query": "paid protesters",
      "date": "2025-10-31T00:00:00+00:00",
      "relevance_score": 90,
      "collected_at": "2026-01-15T03:26:04.162758Z"
    },
    {
      "title": "'STOP TRUMP' Craigslist ad recruiting paid protesters isn't from January 2026",
      "url": "https://www.msn.com/en-us/news/us/stop-trump-craigslist-ad-recruiting-paid-protesters-isnt-from-january-2026/ar-AA1UhUi9",
      "snippet": "A photo circulating online authentically showed a Craigslist ad from January 2026 recruiting paid protesters to demonstrate against U.S. President Donald Trump. The alleged advertisement was offering people up to $1,",
      "publisher": "Snopes",
      "source": "duckduckgo",
      "query": "paid protesters",
      "date": "2026-01-15T16:00:00+00:00",
      "relevance_score": 90,
      "collected_at": "2026-01-15T17:27:07.212741Z"
    },
    {
      "title": "Fact Check: Is 'Stop Trump' Craigslist ad recruiting paid protesters from January 2026 real?",
      "url": "https://news.meaww.com/fact-check-is-stop-trump-craigslist-ad-recruiting-paid-protesters-from-january-2026-real",
      "snippet": "On January 10, a Facebook user posted a picture of the Craigslist ad. The caption of the post read, \"'Stop Trump' Craigslist ad recruiting paid protesters from January 2026. Let's stop pretending this is 'activism'.\"",
      "publisher": "MEAWW News",
      "source": "duckduckgo",
      "query": "paid protesters",
      "date": "2026-01-16T03:08:00+00:00",
      "relevance_score": 90,
      "collected_at": "2026-01-16T04:34:34.917186Z"
    },
    {
      "title": "'STOP TRUMP' Craigslist ad recruiting paid protesters isn't from January 2026",
      "url": "https://www.msn.com/en-us/news/us/stop-trump-craigslist-ad-recruiting-paid-protesters-isnt-from-january-2026/ar-AA1UhUi9?ocid=BingNewsVerp",
      "snippet": "A photo circulating online authentically showed a Craigslist ad from January 2026 recruiting paid protesters to demonstrate ...",
      "publisher": "Snopes on MSN",
      "source": "duckduckgo",
      "query": "paid protesters",
      "date": "2025-12-31T08:21:19+00:00",
      "relevance_score": 90,
      "collected_at": "2026-01-16T08:21:20.071897Z"
    },
    {
      "title": "'They have brand-new, beautiful printed signs': Trump discredits himself when he explains why protesters are 'paid' by Democrats",
      "url": "https://www.msn.com/en-us/video/news/they-have-brand-new-beautiful-printed-signs-trump-discredits-himself-when-he-explains-why-protesters-are-paid-by-democrats/vi-AA1TJQqT?ocid=BingNewsVerp",
      "snippet": "During his remarks to House Republicans at the Kennedy Center yesterday, Donald Trump claimed protesters against him are \"paid\" by the radical left. Why does Trump think they're \"paid people\"? Because ...",
      "publisher": "Slingshot News on MSN",
      "source": "duckduckgo",
      "query": "paid protesters",
      "date": "2026-01-08T04:36:54+00:00",
      "relevance_score": 90,
      "collected_at": "2026-01-18T04:36:54.171416Z"
    },
    {
      "title": "'They Use Serious Hammers': Trump Discredits Himself When He Tries To Prove The Existence Of 'Paid' Protesters In Oval Office Rant",
      "url": "https://www.msn.com/en-us/politics/government/they-use-serious-hammers-trump-discredits-himself-when-he-tries-to-prove-the-existence-of-paid-protesters-in-oval-office-rant/vi-AA1Rgx4R?ocid=BingNewsVerp",
      "snippet": "Donald Trump signed a memorandum to deploy troops in Memphis several weeks ago from the Oval Office. During Q&A with the press, Trump tried to prove that protesters in cities are paid and part of some ...",
      "publisher": "MSN",
      "source": "duckduckgo",
      "query": "paid protesters",
      "date": "2025-11-27T00:00:00+00:00",
      "relevance_score": 90,
      "collected_at": "2026-01-18T04:36:54.171422Z"
    },
    {
      "title": "Let\u2019s settle once and for all whether protesters are \u2018paid\u2019 | Letters",
      "url": "https://www.yahoo.com/news/articles/let-settle-once-whether-protesters-233706168.html",
      "snippet": "Let\u2019s settle once and for all whether protesters are \u2018 paid \u2019 President Donald Trump has repeatedly ca...",
      "publisher": "The Des Moines Register",
      "source": "duckduckgo",
      "query": "paid protesters",
      "date": "2026-01-17T23:15:08+00:00",
      "relevance_score": 90,
      "collected_at": "2026-01-18T07:15:08.121826Z"
    },
    {
      "title": "'They use serious hammers': Trump discredits himself, tries to prove the existence of 'paid' protesters in rambling remarks",
      "url": "https://www.msn.com/en-us/video/money/they-use-serious-hammers-trump-discredits-himself-tries-to-prove-the-existence-of-paid-protesters-in-rambling-remarks/vi-AA1SXXnR?ocid=BingNewsVerp",
      "snippet": "Donald Trump signed a memorandum to deploy troops in Memphis several weeks ago in September. During Q&A with the press, Trump rambled on and on in an attempt to prove that protesters are \"paid.\" ...",
      "publisher": "MSN",
      "source": "duckduckgo",
      "query": "paid protesters",
      "date": "2025-12-24T00:00:00+00:00",
      "relevance_score": 90,
      "collected_at": "2026-01-18T10:15:18.305937Z"
    },
    {
      "title": "'They use serious hammers': Trump discredits himself, tries to prove the existence of 'paid' protesters in rambling remarks",
      "url": "https://www.msn.com/en-us/news/news/they-use-serious-hammers-trump-discredits-himself-tries-to-prove-the-existence-of-paid-protesters-in-rambling-remarks/vi-AA1SXXnR?ocid=BingNewsVerp",
      "snippet": "Donald Trump signed a memorandum to deploy troops in Memphis several weeks ago in September. During Q&A with the press, Trump rambled on and on in an attempt to prove that protesters are \"paid.\" So ...",
      "publisher": "MSN",
      "source": "duckduckgo",
      "query": "paid protesters",
      "date": "2025-12-24T00:00:00+00:00",
      "relevance_score": 90,
      "collected_at": "2026-01-18T11:12:02.926301Z"
    },
    {
      "title": "Paid Protestors Who Got Within Feet Of Trump Disrupt Scott Bessent\u2019s Dinner",
      "url": "https://ijr.com/paid-protestors-who-got-within-feet-of-trump-disrupt-scott-bessents-dinner/",
      "snippet": "A paid protestor employed by a Chinese Communist Party-linked activist group heckled Treasury Scott Bessent during a night out in Washington, D.C. on Wednesday. Bessent was dining at the wine bar ...",
      "publisher": "IJR",
      "source": "duckduckgo",
      "query": "paid protesters",
      "date": "2025-12-18T00:00:00+00:00",
      "relevance_score": 90,
      "collected_at": "2026-01-19T10:21:39.576656Z"
    },
    {
      "title": "Republicans' 'paid protesters' nonsense takes an ugly turn in Minnesota",
      "url": "https://www.yahoo.com/news/articles/republicans-paid-protesters-nonsense-takes-191357223.html",
      "snippet": "It might make Republicans feel better to think Minnesotans are secretly being paid to protest, but reality is stubborn",
      "publisher": "Yahoo",
      "source": "duckduckgo",
      "query": "paid protesters",
      "date": "2026-01-19T19:48:00+00:00",
      "relevance_score": 90,
      "collected_at": "2026-01-19T21:14:13.379058Z"
    },
    {
      "title": "'They Use Serious Hammers': Trump Discredits Himself When He Tries To Prove The Existence Of 'Paid' Protesters In Oval Office Rant",
      "url": "https://www.msn.com/en-us/video/news/they-use-serious-hammers-trump-discredits-himself-when-he-tries-to-prove-the-existence-of-paid-protesters-in-oval-office-rant/vi-AA1Rgx4R?ocid=BingNewsVerp",
      "snippet": "Donald Trump signed a memorandum to deploy troops in Memphis several weeks ago from the Oval Office. During Q&A with the press, Trump tried to prove that protesters in cities are paid and part of some ...",
      "publisher": "MSN",
      "source": "duckduckgo",
      "query": "paid protesters",
      "date": "2025-11-27T00:00:00+00:00",
      "relevance_score": 90,
      "collected_at": "2026-01-24T14:14:05.071326Z"
    }
  ],
  "jobPostings": [
    {
      "type": "job_posting",
      "source": "adzuna",
      "title": "Manager, Advocacy & Student Programs",
      "company": "Planned Parenthood Hudson Peconic",
      "city": "US",
      "state": "",
      "url": "https://www.adzuna.com/land/ad/5606807113?se=4gJpjmsz8RGeXOBckQe1UA&utm_medium=api&utm_source=a70fa881&v=7C9FF2AFB50E816412D705FC8A5BF6090A701976",
      "date": "2026-04-08T16:54:07.075127Z",
      "salary_min": 65000,
      "salary_max": 75000,
      "suspicion_score": 10,
      "keywords": [
        "community organizer political"
      ],
      "is_monitoring_entry": false
    },
    {
      "type": "job_posting",
      "source": "adzuna",
      "title": "Advocacy Campaign Strategist, Elections and Government Program",
      "company": "Brennan Center for Justice",
      "city": "US",
      "state": "",
      "url": "https://www.adzuna.com/details/5683283119?utm_medium=api&utm_source=a70fa881",
      "date": "2026-04-08T16:54:07.673515Z",
      "salary_min": 103441.5,
      "salary_max": 103441.5,
      "suspicion_score": 10,
      "keywords": [
        "advocacy campaign"
      ],
      "is_monitoring_entry": false
    },
    {
      "type": "job_posting",
      "source": "adzuna",
      "title": "Project Manager, Advocacy Campaigns & Electoral Creative",
      "company": "Planned Parenthood Federation of America",
      "city": "US",
      "state": "",
      "url": "https://www.adzuna.com/details/5645829983?utm_medium=api&utm_source=a70fa881",
      "date": "2026-04-08T16:54:07.673583Z",
      "salary_min": 122038.57,
      "salary_max": 122038.57,
      "suspicion_score": 10,
      "keywords": [
        "advocacy campaign"
      ],
      "is_monitoring_entry": false
    },
    {
      "type": "job_posting",
      "source": "adzuna",
      "title": "Director of Advocacy and Campaign Strategy",
      "company": "The Chamber Of Commerce For Greater Philadelphia",
      "city": "US",
      "state": "",
      "url": "https://www.adzuna.com/details/5686831539?utm_medium=api&utm_source=a70fa881",
      "date": "2026-04-08T16:54:07.673607Z",
      "salary_min": 90000,
      "salary_max": 100000,
      "suspicion_score": 10,
      "keywords": [
        "advocacy campaign"
      ],
      "is_monitoring_entry": false
    },
    {
      "type": "job_posting",
      "source": "adzuna",
      "title": "Regional Manager of State & Local Government Relations - West Region",
      "company": "JPMorgan Chase",
      "city": "US",
      "state": "",
      "url": "https://www.adzuna.com/land/ad/5568776536?se=LqzDjmsz8RGvrL3U9cJsgw&utm_medium=api&utm_source=a70fa881&v=D45BC38453437DEDF4FBAD1EBA38DCEA0925536B",
      "date": "2026-04-08T16:54:07.673674Z",
      "salary_min": 177870.98,
      "salary_max": 177870.98,
      "suspicion_score": 10,
      "keywords": [
        "advocacy campaign"
      ],
      "is_monitoring_entry": false
    },
    {
      "type": "job_posting",
      "source": "adzuna",
      "title": "Travel Certified Occupational Therapist Assistant (COTA) - $1,680 to $1,800 per week in Humansville, MO",
      "company": "AlliedTravelCareers",
      "city": "US",
      "state": "",
      "url": "https://www.adzuna.com/land/ad/5693275390?se=kKKYjmsz8RGvrL3U9cJsgw&utm_medium=api&utm_source=a70fa881&v=06BAE42024B773F0C92626B06CB148D93724CFFA",
      "date": "2026-04-08T16:54:07.402418Z",
      "salary_min": 87360,
      "salary_max": 93600,
      "suspicion_score": 5,
      "keywords": [
        "mobilization coordinator"
      ],
      "is_monitoring_entry": false
    },
    {
      "type": "job_posting",
      "source": "adzuna",
      "title": "Travel Occupational Therapist (OT) - $2,100 to $2,350 per week in Camarillo, CA",
      "company": "AlliedTravelCareers",
      "city": "US",
      "state": "",
      "url": "https://www.adzuna.com/land/ad/5693268838?se=kKKYjmsz8RGvrL3U9cJsgw&utm_medium=api&utm_source=a70fa881&v=796FC151F0B398F85D59184E9B4CCD0E8B266F36",
      "date": "2026-04-08T16:54:07.402442Z",
      "salary_min": 109200,
      "salary_max": 122200,
      "suspicion_score": 5,
      "keywords": [
        "mobilization coordinator"
      ],
      "is_monitoring_entry": false
    },
    {
      "type": "job_posting",
      "source": "adzuna",
      "title": "Field Marketing Manager",
      "company": "Erie Home",
      "city": "US",
      "state": "",
      "url": "https://www.adzuna.com/land/ad/5691565465?se=LEyfjWsz8RGeXOBckQe1UA&utm_medium=api&utm_source=a70fa881&v=478FCE892EB29C0185665C7035FD68597C260B8D",
      "date": "2026-04-08T16:54:05.776118Z",
      "salary_min": 106249.91,
      "salary_max": 106249.91,
      "suspicion_score": 0,
      "keywords": [
        "canvasser political"
      ],
      "is_monitoring_entry": false
    },
    {
      "type": "job_posting",
      "source": "adzuna",
      "title": "Political Director",
      "company": "SEIU 521",
      "city": "US",
      "state": "",
      "url": "https://www.adzuna.com/details/5540489070?utm_medium=api&utm_source=a70fa881",
      "date": "2026-04-08T16:54:06.527459Z",
      "salary_min": 128410,
      "salary_max": 141926,
      "suspicion_score": 0,
      "keywords": [
        "political activist"
      ],
      "is_monitoring_entry": false
    },
    {
      "type": "job_posting",
      "source": "adzuna",
      "title": "Political Director, SEIU Local 521",
      "company": "Current SEIU",
      "city": "US",
      "state": "",
      "url": "https://www.adzuna.com/details/5543529916?utm_medium=api&utm_source=a70fa881",
      "date": "2026-04-08T16:54:06.527480Z",
      "salary_min": 128410,
      "salary_max": 141926,
      "suspicion_score": 0,
      "keywords": [
        "political activist"
      ],
      "is_monitoring_entry": false
    },
    {
      "type": "job_posting",
      "source": "adzuna",
      "title": "Political Organizer, 1199 SEIU",
      "company": "Current SEIU",
      "city": "US",
      "state": "",
      "url": "https://www.adzuna.com/details/5684819735?utm_medium=api&utm_source=a70fa881",
      "date": "2026-04-08T16:54:06.527538Z",
      "salary_min": 37502.6,
      "salary_max": 37502.6,
      "suspicion_score": 0,
      "keywords": [
        "political activist"
      ],
      "is_monitoring_entry": false
    },
    {
      "type": "job_posting",
      "source": "adzuna",
      "title": "Fellow- Junior Researcher",
      "company": "European Institute of Policy Research and Human Rights AISBL",
      "city": "US",
      "state": "",
      "url": "https://www.adzuna.com/details/5655997384?utm_medium=api&utm_source=a70fa881",
      "date": "2026-04-08T16:54:06.527559Z",
      "salary_min": 81973.46,
      "salary_max": 81973.46,
      "suspicion_score": 0,
      "keywords": [
        "political activist"
      ],
      "is_monitoring_entry": false
    },
    {
      "type": "job_posting",
      "source": "adzuna",
      "title": "Campaign Management - International, Quality & Field Actions",
      "company": "Stellantis",
      "city": "US",
      "state": "",
      "url": "https://www.adzuna.com/land/ad/5666176058?se=XKxAjmsz8RG4_oxdqTiYHg&utm_medium=api&utm_source=a70fa881&v=92AACA05D9DDDDBF9AEB81DFCB6E48C7B434E3F5",
      "date": "2026-04-08T16:54:06.766717Z",
      "salary_min": 54693.76,
      "salary_max": 54693.76,
      "suspicion_score": 0,
      "keywords": [
        "campaign field"
      ],
      "is_monitoring_entry": false
    },
    {
      "type": "job_posting",
      "source": "adzuna",
      "title": "Field Marketing Lead",
      "company": "Cinch Home Services, Inc.",
      "city": "US",
      "state": "",
      "url": "https://www.adzuna.com/land/ad/5692780530?se=XKxAjmsz8RG4_oxdqTiYHg&utm_medium=api&utm_source=a70fa881&v=1487B4F7367B6E91333D54944B5F3FAF5E2D0505",
      "date": "2026-04-08T16:54:06.766761Z",
      "salary_min": 78736.55,
      "salary_max": 78736.55,
      "suspicion_score": 0,
      "keywords": [
        "campaign field"
      ],
      "is_monitoring_entry": false
    },
    {
      "type": "job_posting",
      "source": "adzuna",
      "title": "SEM Strategist (North America)",
      "company": "Palo Alto Networks",
      "city": "US",
      "state": "",
      "url": "https://www.adzuna.com/land/ad/5665795527?se=XKxAjmsz8RG4_oxdqTiYHg&utm_medium=api&utm_source=a70fa881&v=D6B87818C6F548A942B213C133D0C8534CD84ECF",
      "date": "2026-04-08T16:54:06.766785Z",
      "salary_min": 170542.45,
      "salary_max": 170542.45,
      "suspicion_score": 0,
      "keywords": [
        "campaign field"
      ],
      "is_monitoring_entry": false
    },
    {
      "type": "job_posting",
      "source": "adzuna",
      "title": "Security Manager",
      "company": "Graham-Windham Inc.",
      "city": "US",
      "state": "",
      "url": "https://www.adzuna.com/details/5391630274?utm_medium=api&utm_source=a70fa881",
      "date": "2026-04-08T16:54:07.075063Z",
      "salary_min": 68501.32,
      "salary_max": 68501.32,
      "suspicion_score": 0,
      "keywords": [
        "community organizer political"
      ],
      "is_monitoring_entry": false
    },
    {
      "type": "job_posting",
      "source": "adzuna",
      "title": "Policy Coordinator",
      "company": "CAIR San Francisco Bay Area",
      "city": "US",
      "state": "",
      "url": "https://www.adzuna.com/details/5628247845?utm_medium=api&utm_source=a70fa881",
      "date": "2026-04-08T16:54:07.075087Z",
      "salary_min": 64438,
      "salary_max": 69700,
      "suspicion_score": 0,
      "keywords": [
        "community organizer political"
      ],
      "is_monitoring_entry": false
    },
    {
      "type": "job_posting",
      "source": "adzuna",
      "title": "Mobility Coordinator",
      "company": "GE Vernova",
      "city": "US",
      "state": "",
      "url": "https://www.adzuna.com/land/ad/5566637040?se=kKKYjmsz8RGvrL3U9cJsgw&utm_medium=api&utm_source=a70fa881&v=D705923391B470A4D6BA85E0204CBDC3DEE31852",
      "date": "2026-04-08T16:54:07.402350Z",
      "salary_min": 84624.15,
      "salary_max": 84624.15,
      "suspicion_score": 0,
      "keywords": [
        "mobilization coordinator"
      ],
      "is_monitoring_entry": false
    },
    {
      "type": "job_posting",
      "source": "adzuna",
      "title": "Global Mobility Coordinator",
      "company": "Lowe's",
      "city": "US",
      "state": "",
      "url": "https://www.adzuna.com/land/ad/5657069612?se=kKKYjmsz8RGvrL3U9cJsgw&utm_medium=api&utm_source=a70fa881&v=F8B22C466856F2CD29307BB6FD4FBECF87B02D10",
      "date": "2026-04-08T16:54:07.402394Z",
      "salary_min": 62981.98,
      "salary_max": 62981.98,
      "suspicion_score": 0,
      "keywords": [
        "mobilization coordinator"
      ],
      "is_monitoring_entry": false
    },
    {
      "type": "job_posting",
      "source": "adzuna",
      "title": "Mobility Coordinator - Volunteer Transportation",
      "company": "Hopelink",
      "city": "US",
      "state": "",
      "url": "https://www.adzuna.com/details/5656407180?utm_medium=api&utm_source=a70fa881",
      "date": "2026-04-08T16:54:07.402548Z",
      "salary_min": 0,
      "salary_max": 52000,
      "suspicion_score": 0,
      "keywords": [
        "mobilization coordinator"
      ],
      "is_monitoring_entry": false
    },
    {
      "type": "job_posting",
      "source": "adzuna",
      "title": "Co-Responding Mobile Coordinator - Per Diem",
      "company": "North Suffolk Community Services Inc",
      "city": "US",
      "state": "",
      "url": "https://www.adzuna.com/details/5668862019?utm_medium=api&utm_source=a70fa881",
      "date": "2026-04-08T16:54:07.402570Z",
      "salary_min": 83200,
      "salary_max": 93600,
      "suspicion_score": 0,
      "keywords": [
        "mobilization coordinator"
      ],
      "is_monitoring_entry": false
    },
    {
      "type": "job_posting",
      "source": "adzuna",
      "title": "Field Canvasser",
      "company": "Mobilize Michigan",
      "city": "US",
      "state": "",
      "url": "https://www.adzuna.com/details/5632260612?utm_medium=api&utm_source=a70fa881",
      "date": "2026-04-08T18:01:44.378389Z",
      "salary_min": 59036.12,
      "salary_max": 59036.12,
      "suspicion_score": 30,
      "keywords": [
        "grassroots organizer"
      ],
      "is_monitoring_entry": false
    },
    {
      "type": "job_posting",
      "source": "adzuna",
      "title": "NYWFP Petition Canvasser",
      "company": "Working Families Party",
      "city": "US",
      "state": "",
      "url": "https://www.adzuna.com/details/5615723394?utm_medium=api&utm_source=a70fa881",
      "date": "2026-04-08T18:01:43.613752Z",
      "salary_min": 68815.02,
      "salary_max": 68815.02,
      "suspicion_score": 20,
      "keywords": [
        "petition signature"
      ],
      "is_monitoring_entry": false
    },
    {
      "type": "job_posting",
      "source": "adzuna",
      "title": "Lead Associate, Grassroots Organizer, New Hampshire (P2)",
      "company": "Save the Children 2022",
      "city": "US",
      "state": "",
      "url": "https://www.adzuna.com/details/5679056599?utm_medium=api&utm_source=a70fa881",
      "date": "2026-04-08T18:01:44.378213Z",
      "salary_min": 59500,
      "salary_max": 66500,
      "suspicion_score": 20,
      "keywords": [
        "grassroots organizer"
      ],
      "is_monitoring_entry": false
    },
    {
      "type": "job_posting",
      "source": "adzuna",
      "title": "Regional Canvass Manager",
      "company": "Civics Education Project",
      "city": "US",
      "state": "",
      "url": "https://www.adzuna.com/details/5500324696?utm_medium=api&utm_source=a70fa881",
      "date": "2026-04-08T18:01:44.378326Z",
      "salary_min": 64787.31,
      "salary_max": 64787.31,
      "suspicion_score": 20,
      "keywords": [
        "grassroots organizer"
      ],
      "is_monitoring_entry": false
    },
    {
      "type": "job_posting",
      "source": "adzuna",
      "title": "Regional Canvass Manager - Baltimore",
      "company": "Civics Education Project",
      "city": "US",
      "state": "",
      "url": "https://www.adzuna.com/details/5499148725?utm_medium=api&utm_source=a70fa881",
      "date": "2026-04-08T18:01:44.378343Z",
      "salary_min": 53852.02,
      "salary_max": 53852.02,
      "suspicion_score": 20,
      "keywords": [
        "grassroots organizer"
      ],
      "is_monitoring_entry": false
    },
    {
      "type": "job_posting",
      "source": "adzuna",
      "title": "Regional Canvass Manager - Bel Air",
      "company": "Civics Education Project",
      "city": "US",
      "state": "",
      "url": "https://www.adzuna.com/details/5498170678?utm_medium=api&utm_source=a70fa881",
      "date": "2026-04-08T18:01:44.378358Z",
      "salary_min": 62705.09,
      "salary_max": 62705.09,
      "suspicion_score": 20,
      "keywords": [
        "grassroots organizer"
      ],
      "is_monitoring_entry": false
    },
    {
      "type": "job_posting",
      "source": "adzuna",
      "title": "Community Canvassers - For Better Roads and Safe Streets",
      "company": "The Outreach Team",
      "city": "US",
      "state": "",
      "url": "https://www.adzuna.com/details/5664513250?utm_medium=api&utm_source=a70fa881",
      "date": "2026-04-08T18:01:43.613899Z",
      "salary_min": 44165.31,
      "salary_max": 44165.31,
      "suspicion_score": 15,
      "keywords": [
        "petition signature"
      ],
      "is_monitoring_entry": false
    },
    {
      "type": "job_posting",
      "source": "adzuna",
      "title": "Canvassers - Higher Wages Lower Rent Alliance",
      "company": "The Outreach Team",
      "city": "US",
      "state": "",
      "url": "https://www.adzuna.com/details/5663117465?utm_medium=api&utm_source=a70fa881",
      "date": "2026-04-08T18:01:43.613922Z",
      "salary_min": 47739.29,
      "salary_max": 47739.29,
      "suspicion_score": 15,
      "keywords": [
        "petition signature"
      ],
      "is_monitoring_entry": false
    },
    {
      "type": "job_posting",
      "source": "adzuna",
      "title": "Grassroots Associate",
      "company": "Americans for prosperity- Minnesota",
      "city": "US",
      "state": "",
      "url": "https://www.adzuna.com/land/ad/5693390125?se=7jiIAHUz8RG4_oxdqTiYHg&utm_medium=api&utm_source=a70fa881&v=AA8F710D4352466F14610311E4266C24E78E69F3",
      "date": "2026-04-08T18:01:44.378257Z",
      "salary_min": 47840,
      "salary_max": 47840,
      "suspicion_score": 10,
      "keywords": [
        "grassroots organizer"
      ],
      "is_monitoring_entry": false
    },
    {
      "type": "job_posting",
      "source": "adzuna",
      "title": "General Support Coordinator",
      "company": "Lawyers' Committee for Civil Rights Under Law",
      "city": "US",
      "state": "",
      "url": "https://www.adzuna.com/details/5597487798?utm_medium=api&utm_source=a70fa881",
      "date": "2026-04-08T18:01:45.584634Z",
      "salary_min": 61570.19,
      "salary_max": 61570.19,
      "suspicion_score": 10,
      "keywords": [
        "campaign field"
      ],
      "is_monitoring_entry": false
    },
    {
      "type": "job_posting",
      "source": "adzuna",
      "title": "Manager, Advocacy & Student Programs",
      "company": "Planned Parenthood Hudson Peconic",
      "city": "US",
      "state": "",
      "url": "https://www.adzuna.com/land/ad/5606807113?se=Kny3AXUz8RG4_oxdqTiYHg&utm_medium=api&utm_source=a70fa881&v=7C9FF2AFB50E816412D705FC8A5BF6090A701976",
      "date": "2026-04-08T18:01:46.063083Z",
      "salary_min": 65000,
      "salary_max": 75000,
      "suspicion_score": 10,
      "keywords": [
        "community organizer political"
      ],
      "is_monitoring_entry": false
    },
    {
      "type": "job_posting",
      "source": "adzuna",
      "title": "Community and Advocacy Organizer",
      "company": "Nc Association Of Ed",
      "city": "US",
      "state": "",
      "url": "https://www.adzuna.com/details/4811113387?utm_medium=api&utm_source=a70fa881",
      "date": "2026-04-08T18:01:46.063164Z",
      "salary_min": 90420.45,
      "salary_max": 90420.45,
      "suspicion_score": 10,
      "keywords": [
        "community organizer political"
      ],
      "is_monitoring_entry": false
    },
    {
      "type": "job_posting",
      "source": "adzuna",
      "title": "Regional Manager of State & Local Government Relations - West Region",
      "company": "JPMorgan Chase",
      "city": "US",
      "state": "",
      "url": "https://www.adzuna.com/land/ad/5568776536?se=hj9gAnUz8RGvrL3U9cJsgw&utm_medium=api&utm_source=a70fa881&v=D45BC38453437DEDF4FBAD1EBA38DCEA0925536B",
      "date": "2026-04-08T18:01:47.592793Z",
      "salary_min": 177870.98,
      "salary_max": 177870.98,
      "suspicion_score": 10,
      "keywords": [
        "advocacy campaign"
      ],
      "is_monitoring_entry": false
    },
    {
      "type": "job_posting",
      "source": "adzuna",
      "title": "Digital Strategy Intern",
      "company": "AMERICAN CANCER SOCIETY",
      "city": "US",
      "state": "",
      "url": "https://www.adzuna.com/details/5660444335?utm_medium=api&utm_source=a70fa881",
      "date": "2026-04-08T18:01:47.592891Z",
      "salary_min": 45806.43,
      "salary_max": 45806.43,
      "suspicion_score": 10,
      "keywords": [
        "advocacy campaign"
      ],
      "is_monitoring_entry": false
    },
    {
      "type": "job_posting",
      "source": "adzuna",
      "title": "Regional County Services Coordinator",
      "company": "Texas Democratic Party",
      "city": "US",
      "state": "",
      "url": "https://www.adzuna.com/details/5677566141?utm_medium=api&utm_source=a70fa881",
      "date": "2026-04-08T18:01:46.063186Z",
      "salary_min": 51708.44,
      "salary_max": 51708.44,
      "suspicion_score": 5,
      "keywords": [
        "community organizer political"
      ],
      "is_monitoring_entry": false
    },
    {
      "type": "job_posting",
      "source": "adzuna",
      "title": "Travel Certified Occupational Therapist Assistant (COTA) - $1,680 to $1,800 per week in Humansville, MO",
      "company": "AlliedTravelCareers",
      "city": "US",
      "state": "",
      "url": "https://www.adzuna.com/land/ad/5693275390?se=vkwCAnUz8RGeXOBckQe1UA&utm_medium=api&utm_source=a70fa881&v=06BAE42024B773F0C92626B06CB148D93724CFFA",
      "date": "2026-04-08T18:01:46.654700Z",
      "salary_min": 87360,
      "salary_max": 93600,
      "suspicion_score": 5,
      "keywords": [
        "mobilization coordinator"
      ],
      "is_monitoring_entry": false
    },
    {
      "type": "job_posting",
      "source": "adzuna",
      "title": "Travel Occupational Therapist (OT) - $2,100 to $2,350 per week in Camarillo, CA",
      "company": "AlliedTravelCareers",
      "city": "US",
      "state": "",
      "url": "https://www.adzuna.com/land/ad/5693268838?se=vkwCAnUz8RGeXOBckQe1UA&utm_medium=api&utm_source=a70fa881&v=796FC151F0B398F85D59184E9B4CCD0E8B266F36",
      "date": "2026-04-08T18:01:46.654725Z",
      "salary_min": 109200,
      "salary_max": 122200,
      "suspicion_score": 5,
      "keywords": [
        "mobilization coordinator"
      ],
      "is_monitoring_entry": false
    },
    {
      "type": "job_posting",
      "source": "adzuna",
      "title": "REGULATORY ANALYST II - 43001687",
      "company": "State of Florida",
      "city": "US",
      "state": "",
      "url": "https://www.adzuna.com/details/5692469144?utm_medium=api&utm_source=a70fa881",
      "date": "2026-04-08T18:01:41.907354Z",
      "salary_min": 63220.46,
      "salary_max": 63220.46,
      "suspicion_score": 0,
      "keywords": [
        "paid protest"
      ],
      "is_monitoring_entry": false
    },
    {
      "type": "job_posting",
      "source": "adzuna",
      "title": "Field Marketing Manager",
      "company": "Erie Home",
      "city": "US",
      "state": "",
      "url": "https://www.adzuna.com/land/ad/5693374291?se=Lp62_3Qz8RGvrL3U9cJsgw&utm_medium=api&utm_source=a70fa881&v=44D9F749BF2C0A6D622888B07BA30191B78FCA34",
      "date": "2026-04-08T18:01:42.909915Z",
      "salary_min": 110566.96,
      "salary_max": 110566.96,
      "suspicion_score": 0,
      "keywords": [
        "canvasser political"
      ],
      "is_monitoring_entry": false
    },
    {
      "type": "job_posting",
      "source": "adzuna",
      "title": "Research Fellow Jr.(JRFP) (Code:EU29444)",
      "company": "European Institute of Policy Research and Human Rights AISBL",
      "city": "US",
      "state": "",
      "url": "https://www.adzuna.com/land/ad/5693303576?se=nF0FAXUz8RG4_oxdqTiYHg&utm_medium=api&utm_source=a70fa881&v=C69CD812371118102F121C4707F1D7423AC3E795",
      "date": "2026-04-08T18:01:45.076718Z",
      "salary_min": 85024.66,
      "salary_max": 85024.66,
      "suspicion_score": 0,
      "keywords": [
        "political activist"
      ],
      "is_monitoring_entry": false
    },
    {
      "type": "job_posting",
      "source": "adzuna",
      "title": "Campaign Management - International, Quality & Field Actions",
      "company": "Stellantis",
      "city": "US",
      "state": "",
      "url": "https://www.adzuna.com/land/ad/5666176058?se=KoNgAXUz8RG4_oxdqTiYHg&utm_medium=api&utm_source=a70fa881&v=92AACA05D9DDDDBF9AEB81DFCB6E48C7B434E3F5",
      "date": "2026-04-08T18:01:45.584566Z",
      "salary_min": 54693.76,
      "salary_max": 54693.76,
      "suspicion_score": 0,
      "keywords": [
        "campaign field"
      ],
      "is_monitoring_entry": false
    },
    {
      "type": "job_posting",
      "source": "adzuna",
      "title": "SEM Strategist (North America)",
      "company": "Palo Alto Networks",
      "city": "US",
      "state": "",
      "url": "https://www.adzuna.com/land/ad/5665795527?se=KoNgAXUz8RG4_oxdqTiYHg&utm_medium=api&utm_source=a70fa881&v=D6B87818C6F548A942B213C133D0C8534CD84ECF",
      "date": "2026-04-08T18:01:45.584610Z",
      "salary_min": 170542.45,
      "salary_max": 170542.45,
      "suspicion_score": 0,
      "keywords": [
        "campaign field"
      ],
      "is_monitoring_entry": false
    },
    {
      "type": "job_posting",
      "source": "adzuna",
      "title": "Marketing Director",
      "company": "Connect Tech Talent",
      "city": "US",
      "state": "",
      "url": "https://www.adzuna.com/details/5662478591?utm_medium=api&utm_source=a70fa881",
      "date": "2026-04-08T18:01:45.584737Z",
      "salary_min": 102221.84,
      "salary_max": 102221.84,
      "suspicion_score": 0,
      "keywords": [
        "campaign field"
      ],
      "is_monitoring_entry": false
    },
    {
      "type": "job_posting",
      "source": "adzuna",
      "title": "Field Marketing Lead",
      "company": "Cinch Careers Page- External",
      "city": "US",
      "state": "",
      "url": "https://www.adzuna.com/details/5665453779?utm_medium=api&utm_source=a70fa881",
      "date": "2026-04-08T18:01:45.584757Z",
      "salary_min": 65464.66,
      "salary_max": 65464.66,
      "suspicion_score": 0,
      "keywords": [
        "campaign field"
      ],
      "is_monitoring_entry": false
    },
    {
      "type": "job_posting",
      "source": "adzuna",
      "title": "Shift Supervisor",
      "company": "Graham-Windham Inc.",
      "city": "US",
      "state": "",
      "url": "https://www.adzuna.com/details/5391538151?utm_medium=api&utm_source=a70fa881",
      "date": "2026-04-08T18:01:46.063065Z",
      "salary_min": 54605.57,
      "salary_max": 54605.57,
      "suspicion_score": 0,
      "keywords": [
        "community organizer political"
      ],
      "is_monitoring_entry": false
    },
    {
      "type": "job_posting",
      "source": "adzuna",
      "title": "Organizing Director, SEIU Local 221",
      "company": "Current SEIU",
      "city": "US",
      "state": "",
      "url": "https://www.adzuna.com/details/5532915397?utm_medium=api&utm_source=a70fa881",
      "date": "2026-04-08T18:01:46.063143Z",
      "salary_min": 110000,
      "salary_max": 120000,
      "suspicion_score": 0,
      "keywords": [
        "community organizer political"
      ],
      "is_monitoring_entry": false
    },
    {
      "type": "job_posting",
      "source": "adzuna",
      "title": "Mobility Coordinator",
      "company": "GE Vernova",
      "city": "US",
      "state": "",
      "url": "https://www.adzuna.com/land/ad/5566637040?se=vkwCAnUz8RGeXOBckQe1UA&utm_medium=api&utm_source=a70fa881&v=D705923391B470A4D6BA85E0204CBDC3DEE31852",
      "date": "2026-04-08T18:01:46.654611Z",
      "salary_min": 84624.15,
      "salary_max": 84624.15,
      "suspicion_score": 0,
      "keywords": [
        "mobilization coordinator"
      ],
      "is_monitoring_entry": false
    },
    {
      "type": "job_posting",
      "source": "adzuna",
      "title": "Global Mobility Coordinator",
      "company": "Lowe's",
      "city": "US",
      "state": "",
      "url": "https://www.adzuna.com/land/ad/5657069612?se=vkwCAnUz8RGeXOBckQe1UA&utm_medium=api&utm_source=a70fa881&v=F8B22C466856F2CD29307BB6FD4FBECF87B02D10",
      "date": "2026-04-08T18:01:46.654652Z",
      "salary_min": 62981.98,
      "salary_max": 62981.98,
      "suspicion_score": 0,
      "keywords": [
        "mobilization coordinator"
      ],
      "is_monitoring_entry": false
    },
    {
      "type": "job_posting",
      "source": "adzuna",
      "title": "Hr Readiness and Mobilization Coordinator",
      "company": "LHH US",
      "city": "US",
      "state": "",
      "url": "https://www.adzuna.com/land/ad/5693338211?se=vkwCAnUz8RGeXOBckQe1UA&utm_medium=api&utm_source=a70fa881&v=F45F1E6AADEA0048BF643835CF45D89577935732",
      "date": "2026-04-08T18:01:46.654675Z",
      "salary_min": 52172.08,
      "salary_max": 52172.08,
      "suspicion_score": 0,
      "keywords": [
        "mobilization coordinator"
      ],
      "is_monitoring_entry": false
    }
  ],
  "jobPostingPatterns": {
    "totalJobs": 50
  },
  "flaggedOrganizations": [
    {
      "type": "independent_expenditure",
      "source": "fec",
      "committee_id": "C00573733",
      "committee_name": "SECURITY IS STRENGTH PAC",
      "amount": 75900.0,
      "date": "2026-04-02",
      "state": "SC"
    },
    {
      "type": "independent_expenditure",
      "source": "fec",
      "committee_id": "C00829432",
      "committee_name": "DEFENDING AMERICA'S FUTURE",
      "amount": 25074.0,
      "date": "2026-04-02",
      "state": "AL"
    },
    {
      "type": "independent_expenditure",
      "source": "fec",
      "committee_id": "C00829952",
      "committee_name": "HOPE IN ACTION PAC",
      "amount": 74130.0,
      "date": "2026-04-02",
      "state": "LA"
    },
    {
      "type": "independent_expenditure",
      "source": "fec",
      "committee_id": "C00633248",
      "committee_name": "314 ACTION FUND",
      "amount": 10000.0,
      "date": "2026-04-02",
      "state": "PA"
    },
    {
      "type": "independent_expenditure",
      "source": "fec",
      "committee_id": "C00633248",
      "committee_name": "314 ACTION FUND",
      "amount": 40000.0,
      "date": "2026-04-02",
      "state": "PA"
    },
    {
      "type": "independent_expenditure",
      "source": "fec",
      "committee_id": "C00936153",
      "committee_name": "STRONGER TOGETHER PA",
      "amount": 272247.0,
      "date": "2026-04-01",
      "state": "PA"
    },
    {
      "type": "independent_expenditure",
      "source": "fec",
      "committee_id": "C00943753",
      "committee_name": "KENTUCKY 4TH PAC",
      "amount": 950000.0,
      "date": "2026-04-01",
      "state": "KY"
    },
    {
      "type": "independent_expenditure",
      "source": "fec",
      "committee_id": "C00573733",
      "committee_name": "SECURITY IS STRENGTH PAC",
      "amount": 71812.58,
      "date": "2026-04-01",
      "state": "SC"
    },
    {
      "type": "independent_expenditure",
      "source": "fec",
      "committee_id": "C00542217",
      "committee_name": "TEXANS FOR A CONSERVATIVE MAJORITY",
      "amount": 400000.0,
      "date": "2026-04-01",
      "state": "TX"
    },
    {
      "type": "independent_expenditure",
      "source": "fec",
      "committee_id": "C00542217",
      "committee_name": "TEXANS FOR A CONSERVATIVE MAJORITY",
      "amount": 752084.87,
      "date": "2026-04-01",
      "state": "TX"
    },
    {
      "type": "independent_expenditure",
      "source": "fec",
      "committee_id": "C00687103",
      "committee_name": "AMERICANS FOR PROSPERITY ACTION, INC. (AFP ACTION) DBA CVA ACTION AND DBA LIBRE ACTION",
      "amount": 16485.0,
      "date": "2026-04-01",
      "state": "NC"
    },
    {
      "type": "independent_expenditure",
      "source": "fec",
      "committee_id": "C00687103",
      "committee_name": "AMERICANS FOR PROSPERITY ACTION, INC. (AFP ACTION) DBA CVA ACTION AND DBA LIBRE ACTION",
      "amount": 4766.25,
      "date": "2026-04-01",
      "state": "NC"
    },
    {
      "type": "new_committee",
      "source": "fec",
      "committee_id": "C00946533",
      "name": "FIGHT FASCISM",
      "committee_type": "V",
      "first_file_date": "2026-04-07",
      "state": "TX",
      "city": null
    },
    {
      "type": "new_committee",
      "source": "fec",
      "committee_id": "C00946608",
      "name": "KEEP IT ALASKA PAC",
      "committee_type": "O",
      "first_file_date": "2026-04-07",
      "state": "WI",
      "city": null
    },
    {
      "type": "new_committee",
      "source": "fec",
      "committee_id": "C00946624",
      "name": "PROTECTING WYOMING VALUES",
      "committee_type": "O",
      "first_file_date": "2026-04-07",
      "state": "WI",
      "city": null
    },
    {
      "type": "new_committee",
      "source": "fec",
      "committee_id": "C00946590",
      "name": "MAKING CONGRESS GREAT AGAIN PAC",
      "committee_type": "O",
      "first_file_date": "2026-04-07",
      "state": "WI",
      "city": null
    },
    {
      "type": "new_committee",
      "source": "fec",
      "committee_id": "C00946574",
      "name": "TENNESSEE STAND PAC",
      "committee_type": "O",
      "first_file_date": "2026-04-07",
      "state": "TN",
      "city": null
    },
    {
      "type": "new_committee",
      "source": "fec",
      "committee_id": "C00946640",
      "name": "RESTORE AMERICA'S MISSION (RAM) PAC",
      "committee_type": "O",
      "first_file_date": "2026-04-07",
      "state": "MD",
      "city": null
    },
    {
      "type": "new_committee",
      "source": "fec",
      "committee_id": "C00946376",
      "name": "ANTHROPPAC",
      "committee_type": "O",
      "first_file_date": "2026-04-06",
      "state": "DC",
      "city": null
    },
    {
      "type": "new_committee",
      "source": "fec",
      "committee_id": "C00946509",
      "name": "CALIFORNIA DEMOCRACY ALLIANCE",
      "committee_type": "O",
      "first_file_date": "2026-04-06",
      "state": "DC",
      "city": null
    },
    {
      "type": "new_committee",
      "source": "fec",
      "committee_id": "C00946012",
      "name": "ASSOCIATION OF TEXAS CONSERVATIVES",
      "committee_type": "O",
      "first_file_date": "2026-04-02",
      "state": "TX",
      "city": null
    },
    {
      "type": "new_committee",
      "source": "fec",
      "committee_id": "C00945683",
      "name": "SACRAMENTO PEOPLE POWER FEDERAL PAC",
      "committee_type": "O",
      "first_file_date": "2026-03-31",
      "state": "CA",
      "city": null
    },
    {
      "type": "new_committee",
      "source": "fec",
      "committee_id": "C00945618",
      "name": "UNITED FOR PROGRESS",
      "committee_type": "O",
      "first_file_date": "2026-03-31",
      "state": "NY",
      "city": null
    },
    {
      "type": "new_committee",
      "source": "fec",
      "committee_id": "C00945691",
      "name": "SMOKY MOUNTAIN PRINCIPLES PAC",
      "committee_type": "O",
      "first_file_date": "2026-03-31",
      "state": "TN",
      "city": null
    },
    {
      "type": "new_committee",
      "source": "fec",
      "committee_id": "C00945527",
      "name": "EAGLE RISING PAC",
      "committee_type": "O",
      "first_file_date": "2026-03-30",
      "state": "OK",
      "city": null
    },
    {
      "type": "new_committee",
      "source": "fec",
      "committee_id": "C00945535",
      "name": "MIKE TER MAAT FOR VICE PRESIDENT",
      "committee_type": "O",
      "first_file_date": "2026-03-30",
      "state": "VA",
      "city": null
    },
    {
      "type": "new_committee",
      "source": "fec",
      "committee_id": "C00945501",
      "name": "DEFEND OHIO PAC",
      "committee_type": "O",
      "first_file_date": "2026-03-29",
      "state": "OH",
      "city": null
    },
    {
      "type": "new_committee",
      "source": "fec",
      "committee_id": "C00945444",
      "name": "ONE BLUE PAC",
      "committee_type": "O",
      "first_file_date": "2026-03-27",
      "state": "PA",
      "city": null
    },
    {
      "type": "new_committee",
      "source": "fec",
      "committee_id": "C00945436",
      "name": "NEW YORK FIGHTS - LUCHANDO POR NUEVA YORK",
      "committee_type": "O",
      "first_file_date": "2026-03-27",
      "state": "NY",
      "city": null
    },
    {
      "type": "new_committee",
      "source": "fec",
      "committee_id": "C00945410",
      "name": "HEARTLAND VICTORY PAC",
      "committee_type": "O",
      "first_file_date": "2026-03-27",
      "state": "OK",
      "city": null
    },
    {
      "type": "new_committee",
      "source": "fec",
      "committee_id": "C00945246",
      "name": "DARE PATRIOTS",
      "committee_type": "V",
      "first_file_date": "2026-03-26",
      "state": "NC",
      "city": null
    },
    {
      "type": "new_committee",
      "source": "fec",
      "committee_id": "C00945170",
      "name": "JAZZE GORMAN",
      "committee_type": "O",
      "first_file_date": "2026-03-26",
      "state": "TX",
      "city": null
    },
    {
      "type": "new_committee",
      "source": "fec",
      "committee_id": "C00945238",
      "name": "MASSACHUSETTS TEACHERS ASSOCIATION INDEPENDENT EXPENDITURE POLITICAL ACTION COMMITTEE",
      "committee_type": "O",
      "first_file_date": "2026-03-26",
      "state": "MA",
      "city": null
    },
    {
      "type": "new_committee",
      "source": "fec",
      "committee_id": "C00945337",
      "name": "MAKE IRAN GREAT AGAIN",
      "committee_type": "O",
      "first_file_date": "2026-03-26",
      "state": "FL",
      "city": null
    },
    {
      "type": "new_committee",
      "source": "fec",
      "committee_id": "C00945196",
      "name": "THE AFFORDABILITY PROJECT",
      "committee_type": "O",
      "first_file_date": "2026-03-26",
      "state": "DC",
      "city": null
    },
    {
      "type": "new_committee",
      "source": "fec",
      "committee_id": "C00945204",
      "name": "GULF COUNTY CONSERVATISM",
      "committee_type": "O",
      "first_file_date": "2026-03-26",
      "state": "FL",
      "city": null
    },
    {
      "type": "new_committee",
      "source": "fec",
      "committee_id": "C00945303",
      "name": "WORKING FAMILIES FOR SAN FRANCISCO PAC",
      "committee_type": "O",
      "first_file_date": "2026-03-26",
      "state": "CA",
      "city": null
    },
    {
      "type": "new_committee",
      "source": "fec",
      "committee_id": "C00944843",
      "name": "MAIN STREET STRONG PAC",
      "committee_type": "O",
      "first_file_date": "2026-03-24",
      "state": "KS",
      "city": null
    },
    {
      "type": "new_committee",
      "source": "fec",
      "committee_id": "C00944702",
      "name": "DEFEND THE WEST PAC",
      "committee_type": "V",
      "first_file_date": "2026-03-23",
      "state": "FL",
      "city": null
    },
    {
      "type": "new_committee",
      "source": "fec",
      "committee_id": "C00944447",
      "name": "AMERICAN PUBLIC VOICE PAC",
      "committee_type": "O",
      "first_file_date": "2026-03-21",
      "state": "UT",
      "city": null
    }
  ]
}